Workbook
Name ADRESSA: '契約金振り込み依頼書'!$AO$7:$AP$15
Name ADRESSB: '契約金振り込み依頼書'!$AO$7:$AO$15

Sheet 初期入力
A1: 初期入力欄 | B1: （ピンク色の箇所に記入またはタブで選択お願いします）
A2: 請負契約書入力分
A3: 工事名称 | B3: 大阪市旭区新森 テスト太郎様邸新築工事 | I3: ★マークがついているタブは単独名義の場合、一部削除する操作必要
A4: 客先氏名 | B4: テスト太郎
A5: 客先住所 | B5: 大阪府大阪市中央区本町1-1-1
A6: 客先氏名2 | B6: テスト花子 | D6: 様 | E6: ←連名の場合は2列目に様を入力する
A7: 客先住所2 | B7: 大阪府大阪市中央区本町1-1-1 | I7: ↓下記4列はプルダウンで選択してください。
A8: 重要事項説明者 | B8: 田中 聡 | I8: ←重要事項説明書を依頼する方を選択してください。
A9: 建築士登録番号 | B9: =IFERROR(VLOOKUP(B8, L18:O28, 3, FALSE), "値が見つかりません") -> 一級 | C9: 建築士 | D9: =VLOOKUP(B8, L18:O28, 4, FALSE) -> 大臣 | E9: 登録第 | F9: =VLOOKUP($B$8,$L$18:$M$28,2,0) -> 253424 | G9: ←3つ選択必要 | I9: 田中 聡（一級）建築士【大臣登録】（第253424号） 佐古 祐太（二級）建築士 大阪府知事登録（第58870号)
A10: 建築士の種類 | B10: =IF(B8="田中 聡", "■管理建築士 □所属する建築士", "□管理建築士 ■所属する建築士") -> ■管理建築士 □所属する建築士 | I10: ←田中さんは【管理建築士】、それ以外の方は【所属する建築士】の■になっているタブを選んでください。
A11: 単独or共有 | B11: 共有 | I11: 西野 秀樹（一級）建築士【大臣登録】（第332632号） 箕浦 三四郎（一級）建築士【大臣登録】（第354989号）
A12: 営業担当 | B12: 田畑 美香 | I12: 古久保 知佳子（二級）大阪府知事登録（第56598号) 村上 由貴子（二級）京都府知事登録（第18527号）
A13: 請負契約日 | C13: 2026 | D13: 年 | E13: 1 | F13: 月 | G13: 15 | H13: 日 | I13: ←数字のみ入力必要 | L13: 林 恭生（二級）和歌山県知事（第6667） 北村 晃平（一級）【大臣登録】（第362717号）
A14: 変更契約日 | C14: 2026 | D14: 年 | E14: 3 | F14: 月 | G14: 15 | H14: 日 | L14: 安藤 千智 （二級）建築士 京都府知事登録（第19339号）
A15: 工事場所 | B15: 大阪府大阪市旭区新森1-2-3 | I15: ←【地番記載】謄本通りの書き方にて
A16: 構造 | B16: 木造軸組工法
A17: 建物階数 | B17: 2 | E17: 変更契約→ | F17: 2 | I17: ←階数選択 | L17: 設計担当 | M17: 番号 | N17: 級 | O17: 登録
A18: 棟数 | B18: 1 | F18: 1 | L18: 田中 聡 | M18: 253424 | N18: 一級 | O18: 大臣
A19: 1階床面積 | B19: 49.04 | I19: ←面積表通り記載 | L19: 北村 晃平 | M19: 362717 | N19: 一級 | O19: 大臣
A20: 対象の場合〇入力 | B20: 〇 | F20: 〇 | L20: 林 恭生 | M20: 6667 | N20: 二級 | O20: 和歌山県知事
A21: 2階床面積 | B21: 44.81 | I21: ←面積表通り記載 | L21: 箕浦 三四郎 | M21: 354989 | N21: 一級 | O21: 大臣
A22: 対象の場合〇入力 | B22: 〇 | F22: 〇 | L22: 荘野 善宏 | M22: 10409 | N22: 二級 | O22: 三重県知事
A23: 3階床面積 | B23: 0 | I23: ←面積表通り記載 | L23: 内藤 智之 | M23: 44439 | N23: 二級 | O23: 大阪府知事
A24: 対象の場合〇入力 | L24: 足立 雅哉 | M24: 319770 | N24: 一級 | O24: 大臣
A25: 施工面積 | B25: 28.4 | L25: 若狹 龍成 | M25: 9571 | N25: 二級 | O25: 愛媛県知事
A26: 対象の場合〇入力 | B26: 〇 | F26: 〇 | L26: 髙濱 洋文 | M26: 305600 | N26: 一級 | O26: 大臣
A27: 着手期日 | B27: 46143 | F27: =B27 -> 45861 | I27: ←資金計画書通り記載 | L27: 佐古 祐太 | M27: 58870 | N27: 二級 | O27: 大阪府知事
A28: 完成期日 | B28: 46295 | F28: =B28 -> 46042 | I28: 令和の年数注意 | L28: 古久保 知佳子 | M28: 56598 | N28: 二級 | O28: 大阪府知事
A29: 引渡期日 | B29: 46310 | F29: =B29 -> 46066
A30: 契約日 | B30: 46037 | F30: 45923
A31: 工事価格(税抜き） | B31: 25208700 | I31: ←数字間違い、位間違い注意
A32: 取引に関わる消費税 | B32: =ROUNDDOWN(B31*0.1,0) -> 2520870 | F32: =ROUNDDOWN(F31*0.1,0) -> 0
A33: 合計額(請負代金） | B33: =SUM(B31:D32) -> 27729570 | F33: =SUM(F31:H32) -> 0
A34: 1回金 建築申込時 | B34: 100000 | F34: =B34 -> 100000
A35: お支払い予定日 | B35: 45992 | F35: =IF((初期入力!B35)="","",初期入力!B35) -> 45356 | I35: ←令和の年数注意
A36: 2回金 請負契約時 | B36: 1000000 | F36: =B36 -> 1000000
A37: お支払い予定日 | B37: 46037 | F37: =B37 -> 45376
A38: 3回金 着工時 | B38: 8300000 | F38: =B38 -> 8300000
A39: お支払い予定日 | B39: 46143 | F39: =B39 -> 46233
A40: 4回金 上棟時 | B40: 8300000 | F40: =B40 -> 8300000
A41: お支払い予定日 | B41: 46188 | F41: =B41 -> 46273
A42: 5回金 引渡時 | B42: =B33-B34-B36-B38-B40 -> 10029570 | F42: =F33-F34-F36-F38-F40 -> -17700000 | I42: ←計算式入っているので触らない
A43: お支払い予定日 | B43: =B29 -> 46066 | F43: =F29 -> 46066 | I43: ←令和の年数注意
A44: 契約番号 | B44: 103999 | I44: ←100124・最初の1は飾り、ブルーは年度ごとの契約順番、赤色は年度
A45: 工事をしない日
A46: 工事しない時間帯
A47: 瑕疵保険会社 | B47: 株式会社 日本住宅保証検査機構
A48: 太陽光契約書
A49: 契約日 | C49: 0 | D49: 年 | E49: 0 | F49: 月 | G49: 0 | H49: 日 | I49: ←太陽光の契約日
A50: 1回金 請負時 | B50: 0
A51: 太陽光契約日 | B51: 45301 | I51: ←令和の年数注意
A52: 工事価格(税抜き） | B52: 1818182 | I52: ←数字間違い、位間違い注意
A53: 取引に関わる消費税 | B53: 181818
A54: 合計額(請負代金） | B54: =B52+B53 -> 2000000
A55: 着手期日 | B55: =F39 -> 46233 | I55: ←令和の年数注意
A56: 完成期日 | B56: =B28 -> 46042
A57: 引渡期日 | B57: =F43 -> 46066

Sheet ★重要事項説明書・省エネ説明義務化
A1: 重 要 事 項 説 明 書
N2: =初期入力!C13 -> 2025 | P2: 年 | Q2: =初期入力!E13 -> 7 | R2: 月 | S2: =初期入力!G13 -> 25 | T2: 日
A3: =初期入力!B4 -> 0 | F3: 様
A4: =IF(初期入力!B6="","",初期入力!B6) | F4: =初期入力!D6 -> 様 | V4: ←単独の場合削除 A～Ｆを選択してＤｅｌｅｔｅボタンを押してください。
A6: 本重要事項説明は、建築士法第24条の7に基づき、設計受託契約又は工事監理受託契約に先立って、あらかじめ契
A7: 約の内容及びその履行に関する事項を説明するものです。本説明内容は最終的な契約内容とは必ずしも同一になる | V7: ※JIO瑕疵担保保険の重要事項説明のビデオ鑑賞・契約確認シート記名押印も合わせてすること！
A8: とは限りません。
A10: 受託業務名称： | D10: =初期入力!B3 -> 大阪市旭区新森 池田様邸新築工事 | K10: 設計・工事監理業務
A12: 建築士事務所の名称 | G12: ： | H12: 株式会社Gハウス 一級建築士事務所
A13: 建築士事務所の所在地 | G13: ： | H13: 大阪府大阪市旭区新森2-23-12
A14: 開設者氏名 | G14: ： | H14: 株式会社Gハウス 代表取締役 趙 晃啓
A15: (法人の場合は開設者の名称及び代表者氏名)
A18: 1.対象となる建築物の概要
A19: 建設予定地 | E19: ： | F19: =初期入力!B15 -> 大阪府大阪市旭区新森
A20: 主要用途 | E20: ： | F20: 一戸建ての住宅
A21: 工事種別 | E21: ： | F21: 新築
A22: 規模等 | E22: ： | F22: =初期入力!B16 -> 木造軸組工法 | J22: =初期入力!B17 -> 2 | K22: 階建て | M22: =工事請負契約書!F111 -> 100.95 | O22: ㎡
A24: 2.作成する設計図書の種類(設計契約受託の場合)
A25: 案内図、配置図、求積図、平面図、立面図、断面図、その他建築確認申請図書一式
A32: 3.工事と設計図書との照合の方法及び工事監理の実施状況に関する報告の方法
C33: (工事監理契約受託の場合)
A34: ①工事と設計図書との照合の方法：
A35: 施工業者からの施工報告及び現場監督からの現場管理報告により確認します。
A36: 特定工程 | C36: =IF(J22=2,"1回","2回") -> 1回 | D36: 、完了検査 | F36: 1回 | G36: による合計 | I36: =IF(J22=2,"2回","3回") -> 2回 | J36: の現場立会検査。
A37: ②工事監理の実施状況に関する報告の方法：
A38: 特定工程の検査済証、施工資料及び施工写真を提出します。
A39: 完了検査の検査済証、施工資料及び施工写真を提出します。
A42: 4.設計又は工事監理の一部を委託する場合の計画 | W42: 構造設計
A43: ①設計又は工事監理の一部を委託する予定： | J43: ■あり □なし | W43: 株式会社ワークスワン
A44: ②委託する業務の概要及び委託先（ありの場合の計画） | W44: 大阪市西区南堀江1-2-6サムティ南堀江ビル6F
A45: 委託する業務の概要 | G45: ： | H45: 構造設計 | W45: 大賀 信幸
A46: 建築士事務所の名称 | G46: ： | H46: 株式会社ワークスワン
A47: 建築士事務所の名称所在地 | G47: ： | H47: 大阪市西区南堀江1-2-6サムティ南堀江ビル6F | W47: 構造設計
A48: 開設者氏名 | G48: ： | H48: 大賀 信幸 | W48: Taki建築設計
W49: 大阪府泉南市信達大苗代1123-6
A50: 委託する業務の概要 | G50: ： | H50: 該当なし | W50: 瀧本 護
A51: 建築士事務所の名称 | G51: ：
A52: 建築士事務所の所在地 | G52: ：
A53: 開設者氏名 | G53: ：
A56: 5.設計又は工事監理に従事することとなる建築士・建築設備士
A57: ①設計業務に従事することとなる建築士・建築設備士 | K57: ②工事監理業務に従事することとなる建築士・建築設備士
A58: 【氏名】 | D58: 田中 聡 | K58: 【氏名】 | M58: 田中 聡 | W58: 田中 聡
A59: 【資格】 | D59: （一級）建築士【大臣登録】（第253424号） | K59: 【資格】 | M59: （一級）建築士 【大臣登録】（第253424号） | W59: （一級）建築士 【大臣登録】（第253424号）
A61: 【氏名】 | D61: 大賀 信幸 | K61: 【氏名】 | M61: 該当なし | W61: 大賀 信幸
A62: 【資格】 | D62: （一級）建築士【大臣登録】（第248355号） | K62: 【資格】 | W62: （一級）建築士 【大臣登録】（第248355号）
A64: 【氏名】 | D64: 該当なし | K64: 【氏名】 | M64: 該当なし | W64: 瀧本 護
A65: 【資格】 | K65: 【資格】 | W65: （二級）建築士 大阪府知事登録（第52909号）
W67: 安藤 千智
W68: （二級）建築士 京都府知事登録（第19339号）
A72: （建築設備の設計に関し意見を聴く者） | K72: （建築設備の設計に関し意見を聴く者）
A73: 【氏名】 | D73: 該当なし | K73: 【氏名】 | N73: 該当なし
A74: 【資格】 | D74: 建築設備士 | K74: 【資格】 | N74: 建築設備士
A78: * 平成21年5月27日以降に設計に必要となる構造設計及び設備設計一級建築士が関与する場合は、その氏名及び資格
A79: について記載する必要があります。
A82: 6.報酬の額及び支払の時期
C84: ① 報酬の額 | F84: ： | G84: 建築工事請負契約書に定める。
C86: ② 支払の時期 | F86: ： | G86: 建築工事請負契約書に定める。
A91: 7.契約の解除に関する事項
A92: 建築主は、正当と認められる事由があるときに限り、建築士事務所が本件業務を完了する以前において、書面をもって通知
A93: して、本件業務について契約の解除をすることができます。かかる場合において本件業務に関する成果品およびその対価の
A94: 取扱いについては、出来高払いを基本として協議のうえ定めるものとします。
A101: （説明をする建築士）
A102: 氏 名 | C102: ： | D102: =初期入力!B8 -> 田中 聡
A103: 資格等 | C103: ： | D103: =初期入力!B9 -> 一級 | F103: 建築士 | H103: =初期入力!B10 -> ■管理建築士 □所属する建築士
A106: 上記の建築士から建築士免許証（免許証明書）の提示のもと重要事項の説明を受け、重要事項説明書を受領しました。
A108: （説明を受けた建築主）
A109: 住 所 | C109: ： | E109: =初期入力!B5 -> 0
A110: 氏 名 | C110: ： | E110: =初期入力!B4 -> 0
A111: 住 所 | C111: ： | E111: =IF(初期入力!B7="","",初期入力!B7)
A112: 氏 名 | C112: ： | E112: =IF(初期入力!B6="","",初期入力!B6)
A116: 省エネ基準への適合性に関する説明書
O118: =初期入力!C13 -> 2025 | Q118: 年 | R118: =初期入力!E13 -> 7 | S118: 月 | T118: =初期入力!G13 -> 25 | U118: 日
A120: =初期入力!B4 -> 0 | F120: 様 | V120: ←単独の場合削除 A～Ｆを選択してＤｅｌｅｔｅボタンを押してください。
A121: =IF(初期入力!B6="","",初期入力!B6) | F121: =初期入力!D6 -> 様
A123: 建築物のエネルギー消費性能の向上に関する法律第27条第1項の規定による説明をします。
A124: この説明書に記載の事項は、事実に相違ありません。
A126: ［建築物に関する事項］
A127: 所在地： | C127: =初期入力!B15 -> 大阪府大阪市旭区新森
A128: 建築物エネルギー消費性能基準への適合性：
A129: ■ 適合 □ 不適合 建築物エネルギー消費性能の確保のためとるべき措置：
A135: ［建築士に関する事項］
A137: 氏名 | B137: ： | C137: =初期入力!B8 -> 田中 聡
A138: 資格 | B138: ： | C138: =初期入力!B9 -> 一級 | E138: 建築士 | F138: =初期入力!D9 -> 大臣 | I138: 登録第 | K138: =初期入力!F9 -> 253424
A141: ［建築士事務所に関する事項］
A143: 名称： 株式会社Gハウス
A144: 所在地： 大阪府大阪市旭区新森2-23-12
A145: 区分(一級、二級、木造)： 一級 建築士事務所
A148: (備考)
A149: BELS取得予定

Sheet 工事請負契約書
B2: NO. | C2: =初期入力!B44 -> 103824
A10: =初期入力!B3 -> 大阪市旭区新森 池田様邸新築工事
A14: 建築工事請負契約書
D53: 株式会社 Gハウス
S56: 20250724 | W56: 制定
D59: 建築工事請負契約書
A63: 注文者： | D63: =初期入力!B4 -> 0 | I63: =IF(初期入力!B6="","",初期入力!B6) | P63: (以下「甲」という)と
A65: 請負者： | D65: 株式会社 Gハウス | P65: (以下「乙」という)とは
D67: =初期入力!B3 -> 大阪市旭区新森 池田様邸新築工事
A69: の施工について、次の各条項・資金計画書・設計図書・その他添付資料に基づき請負契約を締結し、
A70: 契約成立を証するため、本書の電磁的記録を作成し、甲および乙が合意の後電子署名を施し、各自
A71: 電磁的記録を保管する。
A74: なお、この請負契約書に添付の設計図書は、参考図面であり確定図面でないものとします。
A75: この請負契約締結後、甲乙協議の上、確定設計図書を作成するものとします。
K79: =初期入力!C13 -> 2025 | M79: 年 | N79: =初期入力!E13 -> 7 | P79: 月 | Q79: =初期入力!G13 -> 25 | S79: 日
A82: 甲1住所 | D82: =初期入力!B5 -> 0
A84: 甲1氏名 | D84: =初期入力!B4 -> 0 | Q84: 印
A86: 甲2住所 | D86: =IF(初期入力!B7="","",初期入力!B7)
A88: 甲2氏名 | D88: =IF(初期入力!B6="","",初期入力!B6) | Q88: 印
A90: 乙住所 | D90: 大阪府大阪市旭区新森2-23-12
A92: 乙氏名 | D92: 株式会社 Gハウス | J92: 代表取締役 趙晃啓 | Q92: 印
A96: 工事名称 | D96: =初期入力!B3 -> 大阪市旭区新森 池田様邸新築工事 | K96: 新・増・改 | P96: 建物所有形態
K97: 築工事 | P97: =初期入力!B11 -> 共有
A98: 工事場所 | D98: =初期入力!B15 -> 大阪府大阪市旭区新森
A100: 構 造 | D100: =初期入力!B16 -> 木造軸組工法 | J100: =初期入力!B17 -> 2 | M100: 階建 | P100: =初期入力!B18 -> 1 | T100: 棟
A103: =初期入力!B20 -> 〇 | B103: 1階床面積 | E103: ㎡ | F103: =初期入力!B19 -> 49.04 | I103: 工 期 | K103: 官庁許可日から 60日 以内に着工予定
I104: 着手期日 | K104: =初期入力!B27 -> 45861
A105: =IF(初期入力!B22="","",初期入力!B22) -> 〇 | B105: 2階床面積 | E105: ㎡ | F105: =初期入力!B21 -> 44.81 | K105: 着手の日から 180日 以内に完成予定
I106: 完成期日 | K106: =初期入力!B28 -> 46042
A107: =IF(初期入力!B24="","",初期入力!B24) | B107: 3階床面積 | E107: ㎡ | F107: =初期入力!B23 -> 0 | K107: 完成の日から 60日 以内に引渡予定
I108: 引渡期日 | K108: =初期入力!B29 -> 46066
A109: =IF(初期入力!B26="","",初期入力!B26) -> 〇 | B109: 施工面積 | E109: ㎡ | F109: =初期入力!B25 -> 7.1
B111: 工事面積 合計 | E111: ㎡ | F111: =F103+F105+F109+F107 -> 100.95
A114: 工事価格(消費税額を除く) | H114: 金 | I114: =初期入力!B31 -> 25208700 | L114: 円也
A115: 取引に係る消費税額 | H115: 金 | I115: =初期入力!B32 -> 2520870 | L115: 円也
A116: 合計額(請負代金) | H116: 金 | I116: =初期入力!B33 -> 27729570 | L116: 円也
A118: 回 次 | D118: お支払時期 | G118: お支払金額 | M118: お支払予定日
A119: 合計額の支払方法 | B119: 1回金 | D119: 建築申込時 | H119: 金 | I119: =初期入力!B34 -> 100000 | L119: 円也 | M119: =IF((初期入力!B35)="","",初期入力!B35) -> 45356
B120: 2回金 | D120: 請負契約時 | H120: 金 | I120: =初期入力!B36 -> 1000000 | L120: 円也 | M120: =初期入力!B37 -> 45376
B121: 3回金 | D121: 着工時 | H121: 金 | I121: =初期入力!B38 -> 8300000 | L121: 円也 | M121: =初期入力!B39 -> 46233
B122: 4回金 | D122: 上棟時 | H122: 金 | I122: =初期入力!B40 -> 8300000 | L122: 円也 | M122: =初期入力!B41 -> 46273
B123: 5回金 | D123: 引渡時 | H123: 金 | I123: =初期入力!B42 -> 10029570 | L123: 円也 | M123: =初期入力!B43 -> 46066
A128: 個別事項
A130: (1)部分使用の有無(無) (2)部分引渡しの有無(無)
A132: (3)種類または品質に関して契約の内容に適合しない場合におけるその不適合を担保すべき責任の履行
A133: に関して講ずべき保証保険契約の締結その他の措置に関する定めの有無(有)(建設業法第
A134: 19条第1項第13号)
A135: ①この工事が、「特定住宅瑕疵担保責任の履行の確保等に関する法律」(平成19年法律第66号)
A136: に定める特定住宅建設瑕疵担保責任の対象工事に該当する場合、講ずべき瑕疵担保責任の履行を確
A137: 保するための資力確保措置の内容(保証金の供託又は責任保険契約の締結)は、添付別紙のとおり
A138: とする。
A139: ②上記①を除くその他の措置の内容 | J139: 無
A141: (4)工事を施工しない日又は時間帯の定めの有無(無)(建設業法19条第1項第4号)
A142: 工事を施工しない日
A143: 工事を施工しない時間帯
A144: ・解体工事に要する費用等
A145: この工事が「建設工事に関わる資材の再資源化等に関する法律」(平成12年法律第104号)第9条
A146: 第1項に規定する対象建設工事に該当する場合、同法第13条第1項の主務省令で定める事項について
A147: は、添付別紙のとおりとする。
C156: 建築工事請負契約約款
A159: 第1条（信義誠実の原則）
A160: 1. 甲と乙は、人が日常生活を営むことができる性能・機能を有する住宅 を乙が建築することを目的として
A161: 本契約を締結するものであることを相互に確認します。
A162: 2. 甲と乙とは、各々対等な立場において、互いに協力し、信義を守り、誠実に本契約を履行するものとします。
A163: 3. 本契約に定める条件に従い、乙は受託業務・工事を完成して本契約の目的物を甲に引き渡すものとし、
A164: 甲はその請負代金（業務報酬及び消費税を含みます。以下同じ。）を乙に支払うものとします。
A165: なお、設計・工事監理業務が本契約に含まれない場合には、本約款における設計・工事監理に関する
A166: 適用されません。
A167: 4. 甲は、乙が本契約に基づく義務の履行を適切かつ円滑に実施できるよう協力するものとし、
A168: 必要となる情報等がある場合は、乙の求めに応じて、速やかに提供するものとします。
A169: 第2条（一括委任・一括下請負）
A170: 1. 乙は、工事の全部又は一部を第三者に委任し、もしくは請け負わせることができるものとし、
... A563: 以上
C566: (特定商取引に関する法律の適用を受ける場合のクーリングオフについての説明書）
A569: ご契約いただきます請負新築工事またはインテリア商品等販売が｢特定商取引に関する法律｣の適用を受ける
A570: 場合(注)で、クーリングオフを行おうとする場合にはこの説明書・工事請負契約約款を充分お読みください。
A572: (注)「特定商取引に関する法律」の適用を受ける場合：訪問販売、電話勧誘販売による取引
A575: Ⅰ 契約の解除(クーリングオフ)を行おうとする場合
A576: ① ｢特定商取引に関する法律｣の適用を受ける場合(注)で、クーリングオフを行おうとする場合には、この
A577: 書面を受領した日から起算して8日以内は、お客様(注文者)は書面又は電磁的記録をもって工事請負契約の
A578: 解除(クーリングオフと呼びます)ができ、その効力は解除する旨の文書を発したときに生ずるものとします。
A579: ただし、次のような場合等にはクーリングオフの権利行使はできません。
A580: ア)お客様(注文者)が請負新築工事建物等を営業用に使用する場合やお客様(注文者)からのご請求により
A581: ご自宅でのお申し込みまたはご契約を行った場合等
A582: イ)壁紙などの消耗品を使用(最小包装単位)又は、3000円未満の現金取引
A583: ② 上記クーリングオフの行使を妨げるために請負者が不実のことを告げたことによりお客様(注文者)が
... A601: （特約事項）
C614: 保証書
A617: 保証書原本は、建物お引渡し時にお渡しいたしますが、その内容は次のとおりとなっております。
A619: 1. 保証内容
A620: ① 保証期間
A621: この契約の目的物の保証期間は､引渡し日から保証項目一覧表記載のとおりの期間と
A622: します。なお、付帯設備および付属施設のうちメーカーの保証のあるものについては、
A623: 当該メーカーの定める保証期間とします。
A624: ② 保証期間内の補修等
A625: 保証期間に、この契約の目的物に保証項目一覧表記載の保証の対象となる現象があらわ
A626: れ、当社がそれを認めた場合は、無償で補修またはお取替えいたします。
A627: なお、付帯設備および付属施設のうちメーカーの保証のあるものについては、当該メー
A628: カーの定める保証内容によります。
A629: ③ 保証期間終了後の補修等
...

Sheet 追加変更請負契約書 
B2: NO. | C2: =初期入力!B44 -> 103824
A10: =初期入力!B3 -> 大阪市旭区新森 池田様邸新築工事
A14: 建築工事追加変更請負契約書
C52: 株式会社 Gハウス
P55: 20250616 | T55: 制定
D58: 建築工事追加変更請負契約書
A62: 注文者： | D62: =初期入力!B4 -> 0 | H62: =IF(初期入力!B6="","",初期入力!B6) | R62: (以下「甲」という)と
A64: 請負者： | D64: 株式会社 Gハウス | R64: (以下「乙」という)とは
D66: =初期入力!B3 -> 大阪市旭区新森 池田様邸新築工事
A68: の施工について、次の各条項･資金計画書･設計図書･その他添付資料に基づき追加変更請負契約
A69: を締結し、契約成立を証するため、本書の電磁的記録を作成し、甲および乙が合意の後電子署名を施し、
A70: 各自電磁的記録を保管する。
J75: =初期入力!C14 -> 2026 | L75: 年 | M75: =初期入力!E14 -> 12 | O75: 月 | P75: =初期入力!G14 -> 25 | R75: 日
A78: 甲１住所 | D78: =初期入力!B5 -> 0
A80: 甲１氏名 | D80: =初期入力!B4 -> 0 | Q80: 印
A82: 甲２住所 | D82: =IF(初期入力!B7="","",初期入力!B7)
A84: 甲２氏名 | D84: =IF(初期入力!B6="","",初期入力!B6) | Q84: 印
A86: 乙住所 | D86: 大阪府大阪市旭区新森2-23-12
A88: 乙氏名 | D88: 株式会社 Gハウス | I88: 代表取締役 趙晃啓 | Q88: 印
A92: 工事名称 | D92: =初期入力!B3 -> 大阪市旭区新森 池田様邸新築工事 | K92: 新 増 改 | N92: 建物所有形態
K93: 築工事 | N93: =初期入力!B11 -> 共有
A94: 工事場所 | D94: =初期入力!B15 -> 大阪府大阪市旭区新森
A96: 構 造 | D96: =初期入力!B16 -> 木造軸組工法 | J96: =初期入力!B17 -> 2 | M96: 階建 | N96: =初期入力!B18 -> 1 | T96: 棟
A99: =初期入力!B20 -> 〇 | B99: 1階床面積 | E99: ㎡ | F99: =初期入力!F19 -> 0 | I99: 工 期 | L99: 官庁許可日から 60日 以内に着工予定
I100: 着手期日 | L100: =初期入力!F27 -> 45861
A101: =IF(初期入力!B22="","",初期入力!B22) -> 〇 | B101: 2階床面積 | E101: ㎡ | F101: =初期入力!F21 -> 0 | L101: 着手の日から 180日 以内に完成予定
I102: 完成期日 | L102: =初期入力!F28 -> 46042
A103: =IF(初期入力!B24="","",初期入力!B24) | B103: 3階床面積 | E103: ㎡ | F103: =初期入力!F23 -> 0 | L103: 完成の日から 60日 以内に引渡予定
I104: 引渡期日 | L104: =初期入力!F27 -> 45861
A105: =IF(初期入力!B26="","",初期入力!B26) -> 〇 | B105: 施工面積 | E105: ㎡ | F105: =初期入力!F25 -> 0
B107: 工事面積 合計 | E107: ㎡ | F107: =F99+F101+F103+F105 -> 0
A110: 工事価格(消費税額を除く) | H110: 金 | I110: =初期入力!F31 -> 0 | M110: 円也
A111: 取引に係る消費税額 | H111: 金 | I111: =初期入力!F32 -> 0 | M111: 円也
A112: 合計額(請負代金) | H112: 金 | I112: =初期入力!F33 -> 0 | M112: 円也
A114: 回 次 | D114: お支払時期 | G114: お支払金額 | N114: お支払予定日
A115: 合計額の支払方法 | B115: 1回金 | D115: 建築申込時 | H115: 金 | I115: =初期入力!F34 -> 100000 | M115: 円也 | N115: =IF(初期入力!F35="","",初期入力!F35) -> 45356
B116: 2回金 | D116: 請負契約時 | H116: 金 | I116: =初期入力!F36 -> 1000000 | M116: 円也 | N116: =初期入力!F37 -> 45376
B117: 3回金 | D117: 着工時 | H117: 金 | I117: =初期入力!F38 -> 8300000 | M117: 円也 | N117: =初期入力!F39 -> 46233
B118: 4回金 | D118: 上棟時 | H118: 金 | I118: =初期入力!F40 -> 8300000 | M118: 円也 | N118: =初期入力!F41 -> 46273
B119: 5回金 | D119: 引渡時 | H119: 金 | I119: =初期入力!F42 -> -17700000 | M119: 円也 | N119: =初期入力!F43 -> 46066
A125: 個別事項
A127: (1)部分使用の有無 (無) (2)部分引渡しの有無 (無)
A129: (3)種類又は品質に関して契約の内容に適合しない場合におけるその不適合を担保すべき責任の履行
A130: に関して講ずべき保証保険契約の締結その他の措置に関する定めの有無(有)(建設業法第
A131: 19条第1項第13号)
A132: ①この工事が、「特定住宅瑕疵担保責任の履行の確保等に関する法律」(平成19年法律第66号)
A133: に定める特定住宅建設瑕疵担保責任の対象工事に該当する場合、講ずべき瑕疵担保責任の履行を確
A134: 保するための資力確保措置の内容(保証金の供託又は責任保険契約の締結)は、添付別紙のとおり
A135: とする。
A136: ②上記①を除くその他の措置の内容 | I136: 無
A138: (4)工事を施工しない日又は時間帯の定めの有無 (無) (建設業法19条第1項第4号)
A139: 工事を施工しない日
A140: 工事を施工しない時間帯
A141: ・解体工事に要する費用等
A142: この工事が「建設工事に関わる資材の再資源化等に関する法律」(平成12年法律第104号)第9条
A143: 第1項に規定する対象建設工事に該当する場合、同法第13条第1項の主務省令で定める事項について
A144: は、添付別紙のとおりとする。
C152: 建築工事請負契約約款
A155: 第1条(総則)
A156: 甲と乙とは、契約書記載の建築工事に関し契約書に定めるもののほか、この約款に基づき、
A157: 信義に従い互いに協力してこの契約を履行します。
A158: 第2条(権利義務の譲渡禁止)
A159: 甲および乙は、相手方の事前の書面による承諾を得なければ、この契約によって生じる権利
A160: または義務を第三者に譲渡または承継させることはできません。
A161: 第3条(甲が二名以上の場合)
A162: 甲が二名以上の場合は、甲の全員が連帯してこの契約に基づく義務を履行します。
A163: 第4条(請負人)
A164: 1. 乙は、この工事の確定図面及び仕様書等により、頭書の請負金額をもって、原則として、前記
A165: の期間内に工事を完成させるものとします。
A166: 2. 乙は、図面または仕様書等について、疑いを生じたとき、または表示が明確ではないあるいは
... A513: 合意書
A515: 発注者： | C515: =初期入力!B4&" "&初期入力!B6 | I515: (以下「甲」という。)と受注者：株式会社Gハウス(以下
A516: 「乙」という。)は、現在、世界的な情勢（木材価格高騰や半導体不足など）に伴い、日本国での著しい
A517: 建築資材等の減少、不足、遅延、中止等が生じている状況を鑑み、甲乙間の令和 | M517: =初期入力!C14 -> 2026 | O517: 年 | P517: =初期入力!E14 -> 12 | Q517: 月 | R517: =初期入力!G14 -> 25 | S517: 日 | T517: 付
A518: 工事請負契約(以下「本件契約」という。)について、以下のとおり合意する。
A520: 第1条(工事の変更・追加)
A521: 乙は、工事材料等の価格高騰、輸入量の減少、輸入の遅延その他経済情勢の変化及びこれらに伴う建築資材
A522: 等の納品の遅延(以下「対象事象」という。)によって、仕様の変更(品番の変更等を含む)又は追加等の設
A523: 計・工事の変更を行う必要があるときは、甲に対して、設計・工事の内容の変更を求めることができる。
A525: 第2条(建築資材等の発注について)
A526: 乙は本件契約に定める工期内に工事が完成するよう善良なる管理者の注意をもって努めるものとし、甲は乙が
A527: 変更契約後ただちに建築資材を発注することに同意する。
A528: 甲はやむを得ず変更契約後に設計および仕様の変更をする際は変更手数料(発注キャンセル料を含む)300,000
A529: 円(税別)を負担することに予め同意をする。なお、設計および仕様の変更時期によっては既に建築資材が納
A530: 品されている場合があり、その場合、甲は上記変更手数料に加えてキャンセルした建築資材の材料費用を負担
A531: ることに予め同意する。
... A546: 各自その電磁的記録を保管する。
C548: =初期入力!C14 -> 2026 | E548: 年 | F548: =初期入力!E14 -> 12 | G548: 月 | H548: =初期入力!G14 -> 25 | I548: 日
D550: 甲(発注者)住所 | H550: =初期入力!B5 -> 0
D552: 氏名 | H552: =初期入力!B4 -> 0 | Q552: 印
D554: 甲(発注者)住所 | H554: =IF(初期入力!B7="","",初期入力!B7)
D556: 氏名 | H556: =IF(初期入力!B6="","",初期入力!B6) | Q556: 印
D558: 乙(受注者)住所 | H558: 大阪府大阪市旭区新森2-23-12
D560: 氏名 | H560: 株式会社Gハウス | Q560: 印
N564: =初期入力!C14 -> 2026 | P564: 年 | Q564: =初期入力!E14 -> 12 | R564: 月 | S564: =初期入力!G14 -> 25 | T564: 日
A566: 株式会社 Gハウス
A567: 代表取締役 趙 晃啓 様
J568: 住所 | K568: =初期入力!B5 -> 0
J569: 氏名 | K569: =初期入力!B4&" "&初期入力!B6
A572: 太陽光発電システムデータの取得･利用に関する同意書
...

Sheet 変更合意書
B1: 工事請負契約に関する一部変更合意書
P3: NO. | Q3: =初期入力!B44 -> 103824
A4: 下記契約当事者の発注者・受注者間において締結した | F4: =初期入力!C13 -> 2025 | G4: 年 | H4: =初期入力!E13 -> 7 | I4: 月 | J4: =初期入力!G13 -> 25 | K4: 日 | L4: 付 | M4: =初期入力!B3 -> 大阪市旭区新森 池田様邸新築工事
A5: 請負契約書(以下｢原契約書｣という)に関する契約事項の一部について下記の通り変更する事に合意する。
A6: 尚、本合意書に定める事項以外については、原契約書の定めを適用するものとする。
A7: この契約の証として、本書の電磁的記録を作成し、甲および乙が合意の後電子署名を施し、
A8: 各自電磁的記録を保管する。
E9: 記
A10: 項目 | C10: 変更前の契約事項 | H10: 変更後の合意事項
A11: 1 工事内容 | C11: 原契約書添付の設計図、見積書の通り | H11: 本合意書添付の設計図、見積書の通り
A12: 2 工事名称 | C12: 注文者(甲) | H12: 注文者(甲)
C13: 住所 | D13: =初期入力!B5 -> 0 | H13: 住所
C14: 氏名 | D14: =初期入力!B4 -> 0 | H14: 氏名
A15: 但し、寄託した契約証拠金等の付随的な契約上の地位はそのまま、変更後の原契約に包括承継される。 | C15: 住所 | D15: =IF(初期入力!B7="","",初期入力!B7) | H15: 住所
C16: 氏名 | D16: =IF(初期入力!B6="","",初期入力!B6) | H16: 氏名
A17: 3 工事場所
A18: 4 工事面積 | C18: ㎡ | K18: ㎡
A19: 5 工期 | C19: 着工 | D19: 年 月 日 | H19: 着工 | M19: 年 月 日
C20: 引渡 | D20: 年 月 日 | H20: 引渡 | M20: 年 月 日
A21: 6 請負代金 | C21: 原契約書記載の通り | H21: (増･減額) | Q21: 円
C22: 請負代金 | H22: 請負代金
C23: (消費税込) | G23: 円 | H23: (消費税込) | Q23: 円
A24: 7 請負代金の 支払い条件 | E24: 金額 | L24: 金額
C25: 建築申込金 | G25: 円 | H25: 建築申込金 | Q25: 円
C26: 契約金 | G26: 円 | H26: 契約金 | Q26: 円
A27: 変更部分のみ記載 | C27: 着工金 | G27: 円 | H27: 着工金 | Q27: 円
C28: 上棟金 | G28: 円 | H28: 上棟金 | Q28: 円
C29: 最終金 | G29: 円 | H29: 最終金 | Q29: 円
A30: 8 その他
A33: 年 月 日
C34: 住所 | E34: =初期入力!B5 -> 0
C35: 注文者(甲) | E35: =初期入力!B4 -> 0 | P35: 印
C37: 住所 | E37: =初期入力!B7 -> 0
C38: 注文者(甲) | E38: =初期入力!B6 -> 0 | P38: 印
C40: 住所 | E40: 大阪府大阪市旭区新森2-23-12
E41: 株式会社Gハウス
C42: 請負者(乙) | E42: 代表取締役 趙 晃啓 | P42: 印

Sheet HOURS以外制約事項
D1: LIFE+ | E1: の仕様 制約事項一覧 | I1: ←商品名タブにて選択必要
C2: 項目 | D2: 標準内容 | F2: 備考
A3: □ | B3: 1 | C3: 間取り | D3: =IF($D$1="LACIE",VLOOKUP(C3,作業用タブ1!$D$2:$F$27,2,FALSE),IF($D$1="LIFE+",VLOOKUP(C3,作業用タブ1!$D$33:$F$58,2,FALSE),IF($D$1="LIFE",VLOOKUP(C3,作業用タブ1!$D$64:$F$89,2,FALSE),IF($D$1="BASE",VLOOKUP(C3,作業用タブ1!$D$95:$F$120,2,FALSE),IF($D$1="LIFE+（キャンペーン）",VLOOKUP(C3,作業用タブ1!$D$126:$F$151,2,FALSE),IF($D$1="LIFE（キャンペーン）",VLOOKUP(C3,作業用タブ1!$D$157:$F$182,2,FALSE),IF($D$1="LIFE+（キャンペーン）",VLOOKUP(C3,作業用タブ1!$D$126:$F$151,2,FALSE),IF($D$1="LIFE（キャンペーン）",VLOOKUP(C3,作業用タブ1!$D$157:$F$182,2,FALSE))))))))) -> 完全自由設計 ※4マス×910mm間隔に柱または壁の設置が必要です。 | F3: =IF($D$1="LACIE",VLOOKUP(C3,作業用タブ1!$D$2:$F$27,3,FALSE),IF($D$1="LIFE+",VLOOKUP(C3,作業用タブ1!$D$33:$F$58,3,FALSE),IF($D$1="LIFE",VLOOKUP(C3,作業用タブ1!$D$64:$F$89,3,FALSE),IF($D$1="BASE",VLOOKUP(C3,作業用タブ1!$D$95:$F$120,3,FALSE),IF($D$1="LIFE+（キャンペーン）",VLOOKUP(C3,作業用タブ1!$D$126:$F$151,3,FALSE),IF($D$1="LIFE（キャンペーン）",VLOOKUP(C3,作業用タブ1!$D$157:$F$182,3,FALSE))))))) -> 申請業務に進んでいくため、基本設計確定後の変更は出来ません。
A4: □ | B4: 2 | C4: 坪単価 | D4: =IF($D$1="LACIE",VLOOKUP(C4,作業用タブ1!$D$2:$F$27,2,FALSE),IF($D$1="LIFE+",VLOOKUP(C4,作業用タブ1!$D$33:$F$58,2,FALSE),IF($D$1="LIFE",VLOOKUP(C4,作業用タブ1!$D$64:$F$89,2,FALSE),IF($D$1="BASE",VLOOKUP(C4,作業用タブ1!$D$95:$F$120,2,FALSE),IF($D$1="LIFE+（キャンペーン）",VLOOKUP(C4,作業用タブ1!$D$126:$F$151,2,FALSE),IF($D$1="LIFE（キャンペーン）",VLOOKUP(C4,作業用タブ1!$D$157:$F$182,2,FALSE))))))) -> 本体工事価格は 63万円(税別) 30坪未満の場合割増計算となり、1坪下がる度に15,000円×坪数＝追加費用が発生します。 3階建ての場合は坪単価＋40,000円UP 下屋の場合は下屋部分㎡×30,000円UP | F4: =IF($D$1="LACIE",VLOOKUP(C4,作業用タブ1!$D$2:$F$27,3,FALSE),IF($D$1="LIFE+",VLOOKUP(C4,作業用タブ1!$D$33:$F$58,3,FALSE),IF($D$1="LIFE",VLOOKUP(C4,作業用タブ1!$D$64:$F$89,3,FALSE),IF($D$1="BASE",VLOOKUP(C4,作業用タブ1!$D$95:$F$120,3,FALSE),IF($D$1="LIFE+（キャンペーン）",VLOOKUP(C4,作業用タブ1!$D$126:$F$151,3,FALSE),IF($D$1="LIFE（キャンペーン）",VLOOKUP(C4,作業用タブ1!$D$157:$F$182,3,FALSE))))))) -> 例）28坪の場合、30坪に対して2坪下がる 30,000円×28坪＝840,000円UP
A5: □ | B5: 3 | C5: 施工面積 | D5: =IF($D$1="LACIE",VLOOKUP(C5,作業用タブ1!$D$2:$F$27,2,FALSE),IF($D$1="LIFE+",VLOOKUP(C5,作業用タブ1!$D$33:$F$58,2,FALSE),IF($D$1="LIFE",VLOOKUP(C5,作業用タブ1!$D$64:$F$89,2,FALSE),IF($D$1="BASE",VLOOKUP(C5,作業用タブ1!$D$95:$F$120,2,FALSE),IF($D$1="LIFE+（キャンペーン）",VLOOKUP(C5,作業用タブ1!$D$126:$F$151,2,FALSE),IF($D$1="LIFE（キャンペーン）",VLOOKUP(C5,作業用タブ1!$D$157:$F$182,2,FALSE))))))) -> 建物価格は「施工面積 × 坪単価」にて算出します。 施工面積は、延床面積に加え、外壁に三方を囲まれたビルトインガレージ、半ビルトインガレージを含み、当社基準により算出します。 また、以下の工事は、施工面積に含まれていない場合でも、別途費用が加算されます。 ① 軒の出・オーバーハング工事 ：42,000円／㎡（税別） ② 下屋工事 ：30,000円／㎡（税別） ③ バルコニー工事・吹抜工事 ：60,000円／㎡（税別） ※対象となる面積は、設計図書に基づき当社が算出します。 | F5: =IF($D$1="LACIE",VLOOKUP(C5,作業用タブ1!$D$2:$F$27,3,FALSE),IF($D$1="LIFE+",VLOOKUP(C5,作業用タブ1!$D$33:$F$58,3,FALSE),IF($D$1="LIFE",VLOOKUP(C5,作業用タブ1!$D$64:$F$89,3,FALSE),IF($D$1="BASE",VLOOKUP(C5,作業用タブ1!$D$95:$F$120,3,FALSE),IF($D$1="LIFE+（キャンペーン）",VLOOKUP(C5,作業用タブ1!$D$126:$F$151,3,FALSE),IF($D$1="LIFE（キャンペーン）",VLOOKUP(C5,作業用タブ1!$D$157:$F$182,3,FALSE))))))) -> 左記内容の対象となる面積については別紙1の参考写真をご確認下さい。
A6: □ | B6: 4 | C6: 住宅ローン | D6: =IF($D$1="LACIE",VLOOKUP(C6,作業用タブ1!$D$2:$F$27,2,FALSE),IF($D$1="LIFE+",VLOOKUP(C6,作業用タブ1!$D$33:$F$58,2,FALSE),IF($D$1="LIFE",VLOOKUP(C6,作業用タブ1!$D$64:$F$89,2,FALSE),IF($D$1="BASE",VLOOKUP(C6,作業用タブ1!$D$95:$F$120,2,FALSE),IF($D$1="LIFE+（キャンペーン）",VLOOKUP(C6,作業用タブ1!$D$126:$F$151,2,FALSE),IF($D$1="LIFE（キャンペーン）",VLOOKUP(C6,作業用タブ1!$D$157:$F$182,2,FALSE))))))) -> 住宅ローンの手続きはお施主様自身でお願いします。 当社でしかご用意ができない書類や図面等はお渡しします。 | F6: =IF($D$1="LACIE",VLOOKUP(C6,作業用タブ1!$D$2:$F$27,3,FALSE),IF($D$1="LIFE+",VLOOKUP(C6,作業用タブ1!$D$33:$F$58,3,FALSE),IF($D$1="LIFE",VLOOKUP(C6,作業用タブ1!$D$64:$F$89,3,FALSE),IF($D$1="BASE",VLOOKUP(C6,作業用タブ1!$D$95:$F$120,3,FALSE),IF($D$1="LIFE+（キャンペーン）",VLOOKUP(C6,作業用タブ1!$D$126:$F$151,3,FALSE),IF($D$1="LIFE（キャンペーン）",VLOOKUP(C6,作業用タブ1!$D$157:$F$182,3,FALSE))))))) -> ※事前審査も同様
A7: □ | B7: 5 | C7: =IF(OR($D$1="LIFE+（キャンペーン）",$D$1="LIFE（キャンペーン）"),"キャンペーン適応","打ち合わせ 期間") -> 打ち合わせ 期間 | D7: =IF($D$1="LACIE",VLOOKUP(C7,作業用タブ1!$D$2:$F$27,2,FALSE),IF($D$1="LIFE+",VLOOKUP(C7,作業用タブ1!$D$33:$F$58,2,FALSE),IF($D$1="LIFE",VLOOKUP(C7,作業用タブ1!$D$64:$F$89,2,FALSE),IF($D$1="BASE",VLOOKUP(C7,作業用タブ1!$D$95:$F$120,2,FALSE),IF($D$1="LIFE+（キャンペーン）",VLOOKUP(C7,作業用タブ1!$D$126:$F$151,2,FALSE),IF($D$1="LIFE（キャンペーン）",VLOOKUP(C7,作業用タブ1!$D$157:$F$182,2,FALSE))))))) -> 最大3ヵ月間 (回数：6回) | F7: =IF($D$1="LACIE",VLOOKUP(C7,作業用タブ1!$D$2:$F$27,3,FALSE),IF($D$1="LIFE+",VLOOKUP(C7,作業用タブ1!$D$33:$F$58,3,FALSE),IF($D$1="LIFE",VLOOKUP(C7,作業用タブ1!$D$64:$F$89,3,FALSE),IF($D$1="BASE",VLOOKUP(C7,作業用タブ1!$D$95:$F$120,3,FALSE),IF($D$1="LIFE+（キャンペーン）",VLOOKUP(C7,作業用タブ1!$D$126:$F$151,3,FALSE),IF($D$1="LIFE（キャンペーン）",VLOOKUP(C7,作業用タブ1!$D$157:$F$182,3,FALSE))))))) -> 打ち合わせ回数6回以下で下記の特典があります。 6回：★10万円相当 5回：★★20万円相当 ※初回ヒアリングは除く
A8: □ | B8: 6 | C8: 仕様 | D8: =IF($D$1="LACIE",VLOOKUP(C8,作業用タブ1!$D$2:$F$27,2,FALSE),IF($D$1="LIFE+",VLOOKUP(C8,作業用タブ1!$D$33:$F$58,2,FALSE),IF($D$1="LIFE",VLOOKUP(C8,作業用タブ1!$D$64:$F$89,2,FALSE),IF($D$1="BASE",VLOOKUP(C8,作業用タブ1!$D$95:$F$120,2,FALSE),IF($D$1="LIFE+（キャンペーン）",VLOOKUP(C8,作業用タブ1!$D$126:$F$151,2,FALSE),IF($D$1="LIFE（キャンペーン）",VLOOKUP(C8,作業用タブ1!$D$157:$F$182,2,FALSE))))))) -> セミオーダー制 当社の設計士がこだわり抜いた【 STYLE BOOK 】からのみ選択できます。 | F8: =(IF($D$1="LACIE",VLOOKUP(C8,作業用タブ1!$D$2:$F$27,3,FALSE),IF($D$1="LIFE+",VLOOKUP(C8,作業用タブ1!$D$33:$F$58,3,FALSE),IF($D$1="LIFE",VLOOKUP(C8,作業用タブ1!$D$64:$F$89,3,FALSE),IF($D$1="BASE",VLOOKUP(C8,作業用タブ1!$D$95:$F$120,3,FALSE),IF($D$1="LIFE+（キャンペーン）",VLOOKUP(C8,作業用タブ1!$D$126:$F$151,3,FALSE),IF($D$1="LIFE（キャンペーン）",VLOOKUP(C8,作業用タブ1!$D$157:$F$182,3,FALSE))))))))
A9: □ | B9: 7 | C9: 長期優良住宅 | D9: =IF($D$1="LACIE",VLOOKUP(C9,作業用タブ1!$D$2:$F$27,2,FALSE),IF($D$1="LIFE+",VLOOKUP(C9,作業用タブ1!$D$33:$F$58,2,FALSE),IF($D$1="LIFE",VLOOKUP(C9,作業用タブ1!$D$64:$F$89,2,FALSE),IF($D$1="BASE",VLOOKUP(C9,作業用タブ1!$D$95:$F$120,2,FALSE),IF($D$1="LIFE+（キャンペーン）",VLOOKUP(C9,作業用タブ1!$D$126:$F$151,2,FALSE),IF($D$1="LIFE（キャンペーン）",VLOOKUP(C9,作業用タブ1!$D$157:$F$182,2,FALSE))))))) -> 認定基準として、少なくとも1の階の床面積(階段部分を除く)が40㎡以上かつ床面積の合計75㎡必要です。 また、都市計画法第53条許可の対象となる地域では認定対象外です。 | F9: =IF($D$1="LACIE",VLOOKUP(C9,作業用タブ1!$D$2:$F$27,3,FALSE),IF($D$1="LIFE+",VLOOKUP(C9,作業用タブ1!$D$33:$F$58,3,FALSE),IF($D$1="LIFE",VLOOKUP(C9,作業用タブ1!$D$64:$F$89,3,FALSE),IF($D$1="BASE",VLOOKUP(C9,作業用タブ1!$D$95:$F$120,3,FALSE),IF($D$1="LIFE+（キャンペーン）",VLOOKUP(C9,作業用タブ1!$D$126:$F$151,3,FALSE),IF($D$1="LIFE（キャンペーン）",VLOOKUP(C9,作業用タブ1!$D$157:$F$182,3,FALSE))))))) -> 詳細は設計打ち合わせにてご確認ください。
A10: □ | B10: 8 | C10: Ua値 | D10: =IF($D$1="LACIE",VLOOKUP(C10,作業用タブ1!$D$2:$F$27,2,FALSE),IF($D$1="LIFE+",VLOOKUP(C10,作業用タブ1!$D$33:$F$58,2,FALSE),IF($D$1="LIFE",VLOOKUP(C10,作業用タブ1!$D$64:$F$89,2,FALSE),IF($D$1="BASE",VLOOKUP(C10,作業用タブ1!$D$95:$F$120,2,FALSE),IF($D$1="LIFE+（キャンペーン）",VLOOKUP(C10,作業用タブ1!$D$126:$F$151,2,FALSE),IF($D$1="LIFE（キャンペーン）",VLOOKUP(C10,作業用タブ1!$D$157:$F$182,2,FALSE))))))) -> 0.46W/㎡･Kを目安としております。但し、間取りや窓の個数･種類によって数値が変わり、0.46W/㎡･Kを確保できない場合があります。 | F10: =IF($D$1="LACIE",VLOOKUP(C10,作業用タブ1!$D$2:$F$27,3,FALSE),IF($D$1="LIFE+",VLOOKUP(C10,作業用タブ1!$D$33:$F$58,3,FALSE),IF($D$1="LIFE",VLOOKUP(C10,作業用タブ1!$D$64:$F$89,3,FALSE),IF($D$1="BASE",VLOOKUP(C10,作業用タブ1!$D$95:$F$120,3,FALSE),IF($D$1="LIFE+（キャンペーン）",VLOOKUP(C10,作業用タブ1!$D$126:$F$151,3,FALSE),IF($D$1="LIFE（キャンペーン）",VLOOKUP(C10,作業用タブ1!$D$157:$F$182,3,FALSE)))))))
A11: □ | B11: 9 | C11: 窓 | D11: =IF($D$1="LACIE",VLOOKUP(C11,作業用タブ1!$D$2:$F$27,2,FALSE),IF($D$1="LIFE+",VLOOKUP(C11,作業用タブ1!$D$33:$F$58,2,FALSE),IF($D$1="LIFE",VLOOKUP(C11,作業用タブ1!$D$64:$F$89,2,FALSE),IF($D$1="BASE",VLOOKUP(C11,作業用タブ1!$D$95:$F$120,2,FALSE),IF($D$1="LIFE+（キャンペーン）",VLOOKUP(C11,作業用タブ1!$D$126:$F$151,2,FALSE),IF($D$1="LIFE（キャンペーン）",VLOOKUP(C11,作業用タブ1!$D$157:$F$182,2,FALSE))))))) -> 施工面積が35坪未満12ヵ所、35～40坪13ヵ所、40～45坪14ヵ所、45～50坪15ヵ所、50坪以上16ヵ所までが標準個数です。 ※既製品のみ選定可能とし特注品の選択不可。 | F11: =IF($D$1="LACIE",VLOOKUP(C11,作業用タブ1!$D$2:$F$27,3,FALSE),IF($D$1="LIFE+",VLOOKUP(C11,作業用タブ1!$D$33:$F$58,3,FALSE),IF($D$1="LIFE",VLOOKUP(C11,作業用タブ1!$D$64:$F$89,3,FALSE),IF($D$1="BASE",VLOOKUP(C11,作業用タブ1!$D$95:$F$120,3,FALSE),IF($D$1="LIFE+（キャンペーン）",VLOOKUP(C11,作業用タブ1!$D$126:$F$151,3,FALSE),IF($D$1="LIFE（キャンペーン）",VLOOKUP(C11,作業用タブ1!$D$157:$F$182,3,FALSE))))))) -> 掃き出し窓(手動シャッター付)H2200は2ヵ所まで
A12: □ | B12: 10 | C12: 建具 | D12: =IF($D$1="LACIE",VLOOKUP(C12,作業用タブ1!$D$2:$F$27,2,FALSE),IF($D$1="LIFE+",VLOOKUP(C12,作業用タブ1!$D$33:$F$58,2,FALSE),IF($D$1="LIFE",VLOOKUP(C12,作業用タブ1!$D$64:$F$89,2,FALSE),IF($D$1="BASE",VLOOKUP(C12,作業用タブ1!$D$95:$F$120,2,FALSE),IF($D$1="LIFE+（キャンペーン）",VLOOKUP(C12,作業用タブ1!$D$126:$F$151,2,FALSE),IF($D$1="LIFE（キャンペーン）",VLOOKUP(C12,作業用タブ1!$D$157:$F$182,2,FALSE))))))) -> 開き扉H2400㎜標準(各居室・トイレ・脱衣室・ランドリーそれぞれ1ヵ所ずつ) ※片引き戸2ヵ所まで標準 | F12: =IF($D$1="LACIE",VLOOKUP(C12,作業用タブ1!$D$2:$F$27,3,FALSE),IF($D$1="LIFE+",VLOOKUP(C12,作業用タブ1!$D$33:$F$58,3,FALSE),IF($D$1="LIFE",VLOOKUP(C12,作業用タブ1!$D$64:$F$89,3,FALSE),IF($D$1="BASE",VLOOKUP(C12,作業用タブ1!$D$95:$F$120,3,FALSE),IF($D$1="LIFE+（キャンペーン）",VLOOKUP(C12,作業用タブ1!$D$126:$F$151,3,FALSE),IF($D$1="LIFE（キャンペーン）",VLOOKUP(C12,作業用タブ1!$D$157:$F$182,3,FALSE))))))) -> 引き戸3枚目以上及び収納扉等、リビング・書斎・洗面室・ファミリーCL・その他の部屋はオプションです。
A13: □ | B13: 11 | C13: 床材 | D13: =IF($D$1="LACIE",VLOOKUP(C13,作業用タブ1!$D$2:$F$27,2,FALSE),IF($D$1="LIFE+",VLOOKUP(C13,作業用タブ1!$D$33:$F$58,2,FALSE),IF($D$1="LIFE",VLOOKUP(C13,作業用タブ1!$D$64:$F$89,2,FALSE),IF($D$1="BASE",VLOOKUP(C13,作業用タブ1!$D$95:$F$120,2,FALSE),IF($D$1="LIFE+（キャンペーン）",VLOOKUP(C13,作業用タブ1!$D$126:$F$151,2,FALSE),IF($D$1="LIFE（キャンペーン）",VLOOKUP(C13,作業用タブ1!$D$157:$F$182,2,FALSE))))))) -> 無垢床材を使用した場合、伸縮、床鳴り、及び経年劣化による変色が発生 する場合があります。
A14: □ | B14: 12 | C14: 換気システム | D14: =IF($D$1="LACIE",VLOOKUP(C14,作業用タブ1!$D$2:$F$27,2,FALSE),IF($D$1="LIFE+",VLOOKUP(C14,作業用タブ1!$D$33:$F$58,2,FALSE),IF($D$1="LIFE",VLOOKUP(C14,作業用タブ1!$D$64:$F$89,2,FALSE),IF($D$1="BASE",VLOOKUP(C14,作業用タブ1!$D$95:$F$120,2,FALSE),IF($D$1="LIFE+（キャンペーン）",VLOOKUP(C14,作業用タブ1!$D$126:$F$151,2,FALSE),IF($D$1="LIFE（キャンペーン）",VLOOKUP(C14,作業用タブ1!$D$157:$F$182,2,FALSE))))))) -> 換気システムは全熱交換型第一種換気システム(Panasonic)が標準です。 | F14: =IF($D$1="LACIE",VLOOKUP(C14,作業用タブ1!$D$2:$F$27,3,FALSE),IF($D$1="LIFE+",VLOOKUP(C14,作業用タブ1!$D$33:$F$58,3,FALSE),IF($D$1="LIFE",VLOOKUP(C14,作業用タブ1!$D$64:$F$89,3,FALSE),IF($D$1="BASE",VLOOKUP(C14,作業用タブ1!$D$95:$F$120,3,FALSE),IF($D$1="LIFE+（キャンペーン）",VLOOKUP(C14,作業用タブ1!$D$126:$F$151,3,FALSE),IF($D$1="LIFE（キャンペーン）",VLOOKUP(C14,作業用タブ1!$D$157:$F$182,3,FALSE))))))) -> DSDD換気システム(okatomi)はオプションとなり、請負契約までに確定が必要です。請負契約後は変更できません。
A15: □ | B15: 13 | C15: ユニットバス | D15: =IF($D$1="LACIE",VLOOKUP(C15,作業用タブ1!$D$2:$F$27,2,FALSE),IF($D$1="LIFE+",VLOOKUP(C15,作業用タブ1!$D$33:$F$58,2,FALSE),IF($D$1="LIFE",VLOOKUP(C15,作業用タブ1!$D$64:$F$89,2,FALSE),IF($D$1="BASE",VLOOKUP(C15,作業用タブ1!$D$95:$F$120,2,FALSE),IF($D$1="LIFE+（キャンペーン）",VLOOKUP(C15,作業用タブ1!$D$126:$F$151,2,FALSE),IF($D$1="LIFE（キャンペーン）",VLOOKUP(C15,作業用タブ1!$D$157:$F$182,2,FALSE))))))) -> 天井有り | F15: =IF($D$1="LACIE",VLOOKUP(C15,作業用タブ1!$D$2:$F$27,3,FALSE),IF($D$1="LIFE+",VLOOKUP(C15,作業用タブ1!$D$33:$F$58,3,FALSE),IF($D$1="LIFE",VLOOKUP(C15,作業用タブ1!$D$64:$F$89,3,FALSE),IF($D$1="BASE",VLOOKUP(C15,作業用タブ1!$D$95:$F$120,3,FALSE),IF($D$1="LIFE+（キャンペーン）",VLOOKUP(C15,作業用タブ1!$D$126:$F$151,3,FALSE),IF($D$1="LIFE（キャンペーン）",VLOOKUP(C15,作業用タブ1!$D$157:$F$182,3,FALSE))))))) -> 天井無しの施工はDSDD換気システムをオプションで採用される場合のみ対応可能です。ご選択いただけるメーカーが限られますのでご注意ください。
A16: □ | B16: 14 | C16: エコキュート タンク | D16: =IF($D$1="LACIE",VLOOKUP(C16,作業用タブ1!$D$2:$F$27,2,FALSE),IF($D$1="LIFE+",VLOOKUP(C16,作業用タブ1!$D$33:$F$58,2,FALSE),IF($D$1="LIFE",VLOOKUP(C16,作業用タブ1!$D$64:$F$89,2,FALSE),IF($D$1="BASE",VLOOKUP(C16,作業用タブ1!$D$95:$F$120,2,FALSE),IF($D$1="LIFE+（キャンペーン）",VLOOKUP(C16,作業用タブ1!$D$126:$F$151,2,FALSE),IF($D$1="LIFE（キャンペーン）",VLOOKUP(C16,作業用タブ1!$D$157:$F$182,2,FALSE))))))) -> 室外置き | F16: =IF($D$1="LACIE",VLOOKUP(C16,作業用タブ1!$D$2:$F$27,3,FALSE),IF($D$1="LIFE+",VLOOKUP(C16,作業用タブ1!$D$33:$F$58,3,FALSE),IF($D$1="LIFE",VLOOKUP(C16,作業用タブ1!$D$64:$F$89,3,FALSE),IF($D$1="BASE",VLOOKUP(C16,作業用タブ1!$D$95:$F$120,3,FALSE),IF($D$1="LIFE+（キャンペーン）",VLOOKUP(C16,作業用タブ1!$D$126:$F$151,3,FALSE),IF($D$1="LIFE（キャンペーン）",VLOOKUP(C16,作業用タブ1!$D$157:$F$182,3,FALSE))))))) -> 室内置きはオプションです。
A17: □ | B17: 15 | C17: 点検口 | D17: =IF($D$1="LACIE",VLOOKUP(C17,作業用タブ1!$D$2:$F$27,2,FALSE),IF($D$1="LIFE+",VLOOKUP(C17,作業用タブ1!$D$33:$F$58,2,FALSE),IF($D$1="LIFE",VLOOKUP(C17,作業用タブ1!$D$64:$F$89,2,FALSE),IF($D$1="BASE",VLOOKUP(C17,作業用タブ1!$D$95:$F$120,2,FALSE),IF($D$1="LIFE+（キャンペーン）",VLOOKUP(C17,作業用タブ1!$D$126:$F$151,2,FALSE),IF($D$1="LIFE（キャンペーン）",VLOOKUP(C17,作業用タブ1!$D$157:$F$182,2,FALSE))))))) -> 換気システムや配管の定期点検及び不具合が起きた場合に備えて1,2Fに必要な箇所に天井･床下点検口を3～4つ以上設置しています。 | F17: =IF($D$1="LACIE",VLOOKUP(C17,作業用タブ1!$D$2:$F$27,3,FALSE),IF($D$1="LIFE+",VLOOKUP(C17,作業用タブ1!$D$33:$F$58,3,FALSE),IF($D$1="LIFE",VLOOKUP(C17,作業用タブ1!$D$64:$F$89,3,FALSE),IF($D$1="BASE",VLOOKUP(C17,作業用タブ1!$D$95:$F$120,3,FALSE),IF($D$1="LIFE+（キャンペーン）",VLOOKUP(C17,作業用タブ1!$D$126:$F$151,3,FALSE),IF($D$1="LIFE（キャンペーン）",VLOOKUP(C17,作業用タブ1!$D$157:$F$182,3,FALSE))))))) -> 点検口の個数および位置については間取りプランにより変動します。
A18: □ | B18: 16 | C18: 大工工事 | D18: =IF($D$1="LACIE",VLOOKUP(C18,作業用タブ1!$D$2:$F$27,2,FALSE),IF($D$1="LIFE+",VLOOKUP(C18,作業用タブ1!$D$33:$F$58,2,FALSE),IF($D$1="LIFE",VLOOKUP(C18,作業用タブ1!$D$64:$F$89,2,FALSE),IF($D$1="BASE",VLOOKUP(C18,作業用タブ1!$D$95:$F$120,2,FALSE),IF($D$1="LIFE+（キャンペーン）",VLOOKUP(C18,作業用タブ1!$D$126:$F$151,2,FALSE),IF($D$1="LIFE（キャンペーン）",VLOOKUP(C18,作業用タブ1!$D$157:$F$182,2,FALSE))))))) -> 造作工事はSTYLE BOOKに記載の内容のみ対応しています。 | F18: =IF($D$1="LACIE",VLOOKUP(C18,作業用タブ1!$D$2:$F$27,3,FALSE),IF($D$1="LIFE+",VLOOKUP(C18,作業用タブ1!$D$33:$F$58,3,FALSE),IF($D$1="LIFE",VLOOKUP(C18,作業用タブ1!$D$64:$F$89,3,FALSE),IF($D$1="BASE",VLOOKUP(C18,作業用タブ1!$D$95:$F$120,3,FALSE),IF($D$1="LIFE+（キャンペーン）",VLOOKUP(C18,作業用タブ1!$D$126:$F$151,3,FALSE),IF($D$1="LIFE（キャンペーン）",VLOOKUP(C18,作業用タブ1!$D$157:$F$182,3,FALSE))))))) -> 記載無き内容については提携リフォーム会社様へご相談ください。
A19: □ | B19: 17 | C19: トラブル防止 | D19: =IF($D$1="LACIE",VLOOKUP(C19,作業用タブ1!$D$2:$F$27,2,FALSE),IF($D$1="LIFE+",VLOOKUP(C19,作業用タブ1!$D$33:$F$58,2,FALSE),IF($D$1="LIFE",VLOOKUP(C19,作業用タブ1!$D$64:$F$89,2,FALSE),IF($D$1="BASE",VLOOKUP(C19,作業用タブ1!$D$95:$F$120,2,FALSE),IF($D$1="LIFE+（キャンペーン）",VLOOKUP(C19,作業用タブ1!$D$126:$F$151,2,FALSE),IF($D$1="LIFE（キャンペーン）",VLOOKUP(C19,作業用タブ1!$D$157:$F$182,2,FALSE))))))) -> STYLE BOOKに掲載の商品は、告知無しで変更になる場合があります。 ※各メーカーの商品改定および更新が定期的に行われるため、 契約締結時に交付されたSTYLE BOOKの記載価格・内容が適用されます。 | F19: =IF($D$1="LACIE",VLOOKUP(C19,作業用タブ1!$D$2:$F$27,3,FALSE),IF($D$1="LIFE+",VLOOKUP(C19,作業用タブ1!$D$33:$F$58,3,FALSE),IF($D$1="LIFE",VLOOKUP(C19,作業用タブ1!$D$64:$F$89,3,FALSE),IF($D$1="BASE",VLOOKUP(C19,作業用タブ1!$D$95:$F$120,3,FALSE),IF($D$1="LIFE+（キャンペーン）",VLOOKUP(C19,作業用タブ1!$D$126:$F$151,3,FALSE),IF($D$1="LIFE（キャンペーン）",VLOOKUP(C19,作業用タブ1!$D$157:$F$182,3,FALSE))))))) -> 打ち合わせ中に選定商品が廃番になることもありますのでご注意ください。 SNS等へのデータのUPはご遠慮ください。
A20: □ | B20: 18 | C20: オプション | D20: =IF($D$1="LACIE",VLOOKUP(C20,作業用タブ1!$D$2:$F$27,2,FALSE),IF($D$1="LIFE+",VLOOKUP(C20,作業用タブ1!$D$33:$F$58,2,FALSE),IF($D$1="LIFE",VLOOKUP(C20,作業用タブ1!$D$64:$F$89,2,FALSE),IF($D$1="BASE",VLOOKUP(C20,作業用タブ1!$D$95:$F$120,2,FALSE),IF($D$1="LIFE+（キャンペーン）",VLOOKUP(C20,作業用タブ1!$D$126:$F$151,2,FALSE),IF($D$1="LIFE（キャンペーン）",VLOOKUP(C20,作業用タブ1!$D$157:$F$182,2,FALSE))))))) -> 標準仕様の一部をやめることによる減額(＝マイナスオプション)は対応不可です。 | F20: =IF($D$1="LACIE",VLOOKUP(C20,作業用タブ1!$D$2:$F$27,3,FALSE),IF($D$1="LIFE+",VLOOKUP(C20,作業用タブ1!$D$33:$F$58,3,FALSE),IF($D$1="LIFE",VLOOKUP(C20,作業用タブ1!$D$64:$F$89,3,FALSE),IF($D$1="BASE",VLOOKUP(C20,作業用タブ1!$D$95:$F$120,3,FALSE),IF($D$1="LIFE+（キャンペーン）",VLOOKUP(C20,作業用タブ1!$D$126:$F$151,3,FALSE),IF($D$1="LIFE（キャンペーン）",VLOOKUP(C20,作業用タブ1!$D$157:$F$182,3,FALSE)))))))
A21: □ | B21: 19 | C21: 式典 | D21: =IF($D$1="LACIE",VLOOKUP(C21,作業用タブ1!$D$2:$F$27,2,FALSE),IF($D$1="LIFE+",VLOOKUP(C21,作業用タブ1!$D$33:$F$58,2,FALSE),IF($D$1="LIFE",VLOOKUP(C21,作業用タブ1!$D$64:$F$89,2,FALSE),IF($D$1="BASE",VLOOKUP(C21,作業用タブ1!$D$95:$F$120,2,FALSE),IF($D$1="LIFE+（キャンペーン）",VLOOKUP(C21,作業用タブ1!$D$126:$F$151,2,FALSE),IF($D$1="LIFE（キャンペーン）",VLOOKUP(C21,作業用タブ1!$D$157:$F$182,2,FALSE))))))) -> 地鎮祭および上棟式は省略しています。 | F21: =IF($D$1="LACIE",VLOOKUP(C21,作業用タブ1!$D$2:$F$27,3,FALSE),IF($D$1="LIFE+",VLOOKUP(C21,作業用タブ1!$D$33:$F$58,3,FALSE),IF($D$1="LIFE",VLOOKUP(C21,作業用タブ1!$D$64:$F$89,3,FALSE),IF($D$1="BASE",VLOOKUP(C21,作業用タブ1!$D$95:$F$120,3,FALSE),IF($D$1="LIFE+（キャンペーン）",VLOOKUP(C21,作業用タブ1!$D$126:$F$151,3,FALSE),IF($D$1="LIFE（キャンペーン）",VLOOKUP(C21,作業用タブ1!$D$157:$F$182,3,FALSE))))))) -> ご希望の方は鎮め物や上棟札を着工の2週間前までに担当者にお預けください。
A22: □ | B22: 20 | C22: 施工会社 | D22: =IF($D$1="LACIE",VLOOKUP(C22,作業用タブ1!$D$2:$F$27,2,FALSE),IF($D$1="LIFE+",VLOOKUP(C22,作業用タブ1!$D$33:$F$58,2,FALSE),IF($D$1="LIFE",VLOOKUP(C22,作業用タブ1!$D$64:$F$89,2,FALSE),IF($D$1="BASE",VLOOKUP(C22,作業用タブ1!$D$95:$F$120,2,FALSE),IF($D$1="LIFE+（キャンペーン）",VLOOKUP(C22,作業用タブ1!$D$126:$F$151,2,FALSE),IF($D$1="LIFE（キャンペーン）",VLOOKUP(C22,作業用タブ1!$D$157:$F$182,2,FALSE))))))) -> 施工については協力会社に委託する場合があります(協力会社は当社指定の一定の施工技術の基準を超えた会社)。 | F22: =IF($D$1="LACIE",VLOOKUP(C22,作業用タブ1!$D$2:$F$27,3,FALSE),IF($D$1="LIFE+",VLOOKUP(C22,作業用タブ1!$D$33:$F$58,3,FALSE),IF($D$1="LIFE",VLOOKUP(C22,作業用タブ1!$D$64:$F$89,3,FALSE),IF($D$1="BASE",VLOOKUP(C22,作業用タブ1!$D$95:$F$120,3,FALSE),IF($D$1="LIFE+（キャンペーン）",VLOOKUP(C22,作業用タブ1!$D$126:$F$151,3,FALSE),IF($D$1="LIFE（キャンペーン）",VLOOKUP(C22,作業用タブ1!$D$157:$F$182,3,FALSE)))))))
A23: □ | B23: 21 | C23: 撮影協力 | D23: =IF($D$1="LACIE",VLOOKUP(C23,作業用タブ1!$D$2:$F$27,2,FALSE),IF($D$1="LIFE+",VLOOKUP(C23,作業用タブ1!$D$33:$F$58,2,FALSE),IF($D$1="LIFE",VLOOKUP(C23,作業用タブ1!$D$64:$F$89,2,FALSE),IF($D$1="BASE",VLOOKUP(C23,作業用タブ1!$D$95:$F$120,2,FALSE),IF($D$1="LIFE+（キャンペーン）",VLOOKUP(C23,作業用タブ1!$D$126:$F$151,2,FALSE),IF($D$1="LIFE（キャンペーン）",VLOOKUP(C23,作業用タブ1!$D$157:$F$182,2,FALSE))))))) -> 広告媒体（紙面・WEB・SNSなど）への利用を目的とした撮影依頼をする場合がございます。ご協力お願いいたします。 | F23: =IF($D$1="LACIE",VLOOKUP(C23,作業用タブ1!$D$2:$F$27,3,FALSE),IF($D$1="LIFE+",VLOOKUP(C23,作業用タブ1!$D$33:$F$58,3,FALSE),IF($D$1="LIFE",VLOOKUP(C23,作業用タブ1!$D$64:$F$89,3,FALSE),IF($D$1="BASE",VLOOKUP(C23,作業用タブ1!$D$95:$F$120,3,FALSE),IF($D$1="LIFE+（キャンペーン）",VLOOKUP(C23,作業用タブ1!$D$126:$F$151,3,FALSE),IF($D$1="LIFE（キャンペーン）",VLOOKUP(C23,作業用タブ1!$D$157:$F$182,3,FALSE)))))))
A24: □ | B24: 22 | C24: お引渡し | D24: =IF($D$1="LACIE",VLOOKUP(C24,作業用タブ1!$D$2:$F$27,2,FALSE),IF($D$1="LIFE+",VLOOKUP(C24,作業用タブ1!$D$33:$F$58,2,FALSE),IF($D$1="LIFE",VLOOKUP(C24,作業用タブ1!$D$64:$F$89,2,FALSE),IF($D$1="BASE",VLOOKUP(C24,作業用タブ1!$D$95:$F$120,2,FALSE),IF($D$1="LIFE+（キャンペーン）",VLOOKUP(C24,作業用タブ1!$D$126:$F$151,2,FALSE),IF($D$1="LIFE（キャンペーン）",VLOOKUP(C24,作業用タブ1!$D$157:$F$182,2,FALSE))))))) -> 建物の残代金の全額お支払いを確認後、鍵をお渡しします。 外構工事の完成に関わらず、お支払いをお願いいたします。 | F24: =IF($D$1="LACIE",VLOOKUP(C24,作業用タブ1!$D$2:$F$27,3,FALSE),IF($D$1="LIFE+",VLOOKUP(C24,作業用タブ1!$D$33:$F$58,3,FALSE),IF($D$1="LIFE",VLOOKUP(C24,作業用タブ1!$D$64:$F$89,3,FALSE),IF($D$1="BASE",VLOOKUP(C24,作業用タブ1!$D$95:$F$120,3,FALSE),IF($D$1="LIFE+（キャンペーン）",VLOOKUP(C24,作業用タブ1!$D$126:$F$151,3,FALSE),IF($D$1="LIFE（キャンペーン）",VLOOKUP(C24,作業用タブ1!$D$157:$F$182,3,FALSE))))))) -> 外構工事をGハウス外構事業部GRAN GARDENにてご契約の方は、引渡し前に着工する場合がございます。GRAN GARDEN以外の業者様による外構工事については、責任の所在が不明確となる可能性があるため、建物のお引渡し後の着工とさせていただきます。
A25: □ | B25: 23 | C25: お引越し | D25: =IF($D$1="LACIE",VLOOKUP(C25,作業用タブ1!$D$2:$F$27,2,FALSE),IF($D$1="LIFE+",VLOOKUP(C25,作業用タブ1!$D$33:$F$58,2,FALSE),IF($D$1="LIFE",VLOOKUP(C25,作業用タブ1!$D$64:$F$89,2,FALSE),IF($D$1="BASE",VLOOKUP(C25,作業用タブ1!$D$95:$F$120,2,FALSE),IF($D$1="LIFE+（キャンペーン）",VLOOKUP(C25,作業用タブ1!$D$126:$F$151,2,FALSE),IF($D$1="LIFE（キャンペーン）",VLOOKUP(C25,作業用タブ1!$D$157:$F$182,2,FALSE))))))) -> お引越しにあたり、階段手摺の取り外しおよび設置が必要となる場合は別途25,000円(税別)発生します。 | F25: =IF($D$1="LACIE",VLOOKUP(C25,作業用タブ1!$D$2:$F$27,3,FALSE),IF($D$1="LIFE+",VLOOKUP(C25,作業用タブ1!$D$33:$F$58,3,FALSE),IF($D$1="LIFE",VLOOKUP(C25,作業用タブ1!$D$64:$F$89,3,FALSE),IF($D$1="BASE",VLOOKUP(C25,作業用タブ1!$D$95:$F$120,3,FALSE),IF($D$1="LIFE+（キャンペーン）",VLOOKUP(C25,作業用タブ1!$D$126:$F$151,3,FALSE),IF($D$1="LIFE（キャンペーン）",VLOOKUP(C25,作業用タブ1!$D$157:$F$182,3,FALSE))))))) -> お引越しに伴い必要となる工事は別途費用が発生します。
... A27: □ | B27: 25 | C27: LINE メール | D27: =IF($D$1="LACIE",VLOOKUP(C27,作業用タブ1!$D$2:$F$27,2,FALSE),IF($D$1="LIFE+",VLOOKUP(C27,作業用タブ1!$D$33:$F$58,2,FALSE),IF($D$1="LIFE",VLOOKUP(C27,作業用タブ1!$D$64:$F$89,2,FALSE),IF($D$1="BASE",VLOOKUP(C27,作業用タブ1!$D$95:$F$120,2,FALSE),IF($D$1="LIFE+（キャンペーン）",VLOOKUP(C27,作業用タブ1!$D$126:$F$151,2,FALSE),IF($D$1="LIFE（キャンペーン）",VLOOKUP(C27,作業用タブ1!$D$157:$F$182,2,FALSE))))))) -> 間違い防止のため、設計･コーディネーター担当へのご要望･ご質問等、ご相談内容をLINEやメールにてお伝えいただくことをお断りしております。打ち合わせの際にまとめて担当者にご相談いただくようにご協力お願いします。 | F27: =IF($D$1="LACIE",VLOOKUP(C27,作業用タブ1!$D$2:$F$27,3,FALSE),IF($D$1="LIFE+",VLOOKUP(C27,作業用タブ1!$D$33:$F$58,3,FALSE),IF($D$1="LIFE",VLOOKUP(C27,作業用タブ1!$D$64:$F$89,3,FALSE),IF($D$1="BASE",VLOOKUP(C27,作業用タブ1!$D$95:$F$120,3,FALSE),IF($D$1="LIFE+（キャンペーン）",VLOOKUP(C27,作業用タブ1!$D$126:$F$151,3,FALSE),IF($D$1="LIFE（キャンペーン）",VLOOKUP(C27,作業用タブ1!$D$157:$F$182,3,FALSE)))))))
E29: 住所 | F29: =初期入力!B5 -> 0
E31: 氏名 | F31: =初期入力!B4 -> 0 | G31: 印
E33: 住所 | F33: =IF(初期入力!B7="","",初期入力!B7)
E35: 氏名 | F35: =IF(初期入力!B6="","",初期入力!B6) | G35: 印

Sheet 作業用タブ1
A1: LACIE | J1: 【商品を選択】
D2: 項目 | E2: 標準内容 | F2: 備考 | J2: LACIE
B3: □ | C3: 1 | D3: 間取り | E3: 完全自由設計 ※4マス×910mm間隔に柱または壁の設置が必要です。 | F3: 申請業務に進んでいくため、基本設計確定後の変更は出来ません。 | J3: LIFE+
B4: □ | C4: 2 | D4: 坪単価 | E4: 本体工事価格は 70万円(税別) 30坪未満の場合割増計算となり、1坪下がる度に15,000円×坪数＝追加費用が発生します。 3階建ての場合は坪単価＋40,000円UP 下屋の場合は下屋部分㎡×30,000円UP | F4: 例) 28坪の場合、30坪に対して2坪下がる 30,000円×28坪＝840,000円UP | J4: LIFE
B5: □ | C5: 3 | D5: 施工面積 | E5: 建物価格は「施工面積 × 坪単価」にて算出します。 施工面積は、延床面積に加え、外壁に三方を囲まれたビルトインガレージ、半ビルトインガレージを含み、当社基準により算出します。 また、以下の工事は、施工面積に含まれていない場合でも、別途費用が加算されます。 ① 軒の出・オーバーハング工事 ：42,000円／㎡（税別） ② 下屋工事 ：30,000円／㎡（税別） ③ バルコニー工事・吹抜工事 ：60,000円／㎡（税別） ※対象となる面積は、設計図書に基づき当社が算出します。 | F5: 左記内容の対象となる面積については別紙1の参考写真をご確認下さい。
B6: □ | C6: 4 | D6: 住宅ローン | E6: 住宅ローンの手続きはお施主様自身でお願いします。 当社でしかご用意ができない書類や図面等はお渡しします。 | F6: ※事前審査も同様 | J6: BASE
B7: □ | C7: 5 | D7: 打ち合わせ 期間 | E7: 最大3ヵ月間 (回数：6回) | F7: 打ち合わせ回数6回以下で下記の特典があります。 6回：★10万円相当 5回：★★20万円相当 ※初回ヒアリングは除く
B8: □ | C8: 6 | D8: 仕様 | E8: セミオーダー制 当社の設計士がこだわり抜いた【 STYLE BOOK 】からのみ選択できます。
B9: □ | C9: 7 | D9: 長期優良住宅 | E9: 認定基準として、少なくとも1の階の床面積(階段部分を除く)が40㎡以上かつ床面積の合計75㎡必要です。 また、都市計画法第53条許可の対象となる地域では認定対象外です。 | F9: 詳細は設計打ち合わせにてご確認ください。
B10: □ | C10: 8 | D10: Ua値 | E10: 0.46W/㎡･Kを目安としております。但し、間取りや窓の個数･種類によって数値が変わり、0.46W/㎡･Kを確保できない場合があります。
B11: □ | C11: 9 | D11: 窓 | E11: 施工面積が35坪未満12ヵ所、35～40坪13ヵ所、40～45坪14ヵ所、45～50坪15ヵ所、50坪以上16ヵ所までが標準個数です。 ※既製品のみ選定可能とし特注品の選択不可。 | F11: 掃き出し窓(手動シャッター付)H2200は2ヵ所まで
B12: □ | C12: 10 | D12: 建具 | E12: 開き扉H2400㎜標準(各居室・トイレ・脱衣室・ランドリーそれぞれ1ヵ所ずつ) ※片引き戸2ヵ所まで標準 | F12: 引き戸3枚目以上及び収納扉等、リビング・書斎・洗面室・ファミリーCL・その他の部屋はオプションです。
B13: □ | C13: 11 | D13: 床材 | E13: 無垢床材を使用した場合、伸縮、床鳴り、及び経年劣化による変色が発生 する場合があります。
B14: □ | C14: 12 | D14: 換気システム | E14: 換気システムは全熱交換型第一種換気システム(Panasonic)が標準です。 | F14: DSDD換気システム(okatomi)はオプションとなり、請負契約までに確定が必要です。請負契約後は変更できません。
B15: □ | C15: 13 | D15: ユニットバス | E15: 天井有り | F15: 天井無しの施工はDSDD換気システムをオプションで採用される場合のみ対応可能です。ご選択いただけるメーカーが限られますのでご注意ください。
B16: □ | C16: 14 | D16: エコキュート タンク | E16: 室外置き | F16: 室内置きはオプションです。
B17: □ | C17: 15 | D17: 点検口 | E17: 換気システムや配管の定期点検及び不具合が起きた場合に備えて1,2Fに必要な箇所に天井･床下点検口を3～4つ以上設置しています。 | F17: 点検口の個数および位置については間取りプランにより変動します。
B18: □ | C18: 16 | D18: 大工工事 | E18: 造作工事はSTYLE BOOKに記載の内容のみ対応しています。 | F18: 記載無き内容については提携リフォーム会社様へご相談ください。
B19: □ | C19: 17 | D19: トラブル防止 | E19: STYLE BOOKに掲載の商品は、告知無しで変更になる場合があります。 ※各メーカーの商品改定及び更新が定期的に行われるため、 契約締結時に交付されたSTYLE BOOKの記載価格・内容が適用されます。 | F19: 打ち合わせ中に選定商品が廃番になることもありますのでご注意ください。 SNS等へのデータのUPはご遠慮ください。
B20: □ | C20: 18 | D20: オプション | E20: 標準仕様の一部をやめることによる減額(＝マイナスオプション)は対応不可です。
B21: □ | C21: 19 | D21: 式典 | E21: 地鎮祭および上棟式は省略しています。 | F21: ご希望の方は鎮め物や上棟札を着工の2週間前までに担当者にお預けください。
B22: □ | C22: 20 | D22: 施工会社 | E22: 施工については協力会社に委託する場合があります(協力会社は当社指定の一定の施工技術の基準を超えた会社)。
B23: □ | C23: 21 | D23: 撮影協力 | E23: 広告媒体（紙面・WEB・SNSなど）への利用を目的とした撮影依頼をする場合がございます。ご協力お願いいたします。
B24: □ | C24: 22 | D24: お引渡し | E24: 建物の残代金の全額お支払いを確認後、鍵をお渡しします。 外構工事の完成に関わらず、お支払いをお願いいたします。 | F24: 外構工事をGハウス外構事業部GRAN GARDENにてご契約の方は、引渡し前に着工する場合がございます。GRAN GARDEN以外の業者様による外構工事については、責任の所在が不明確となる可能性があるため、建物のお引渡し後の着工とさせていただきます。
B25: □ | C25: 23 | D25: お引越し | E25: お引越しにあたり、階段手摺の取り外しおよび設置が必要となる場合は別途25,000円(税別)発生します。 | F25: お引越しに伴い必要となる工事は別途費用が発生します。
B26: □ | C26: 24 | D26: 補助金 | E26: 補助金の手続きはお施主様自身でお願いします。 | F26: ※当社で代理申請する場合は別途費用が発生します。 ZEH補助金はGハウスの行程では対応不可です。
B27: □ | C27: 25 | D27: LINE メール | E27: 間違い防止のため、設計･コーディネーター担当へのご要望･ご質問等、ご相談内容をLINEやメールにてお伝えいただくことをお断りしております。打ち合わせの際にまとめて担当者にご相談いただくようにご協力お願いします。
A32: LIFE+
D33: 項目 | E33: 標準内容 | F33: 備考
B34: □ | C34: 1 | D34: 間取り | E34: 完全自由設計 ※4マス×910mm間隔に柱または壁の設置が必要です。 | F34: 申請業務に進んでいくため、基本設計確定後の変更は出来ません。
B35: □ | C35: 2 | D35: 坪単価 | E35: 本体工事価格は 63万円(税別) 30坪未満の場合割増計算となり、1坪下がる度に15,000円×坪数＝追加費用が発生します。 3階建ての場合は坪単価＋40,000円UP 下屋の場合は下屋部分㎡×30,000円UP | F35: 例）28坪の場合、30坪に対して2坪下がる 30,000円×28坪＝840,000円UP
B36: □ | C36: 3 | D36: 施工面積 | E36: 建物価格は「施工面積 × 坪単価」にて算出します。 施工面積は、延床面積に加え、外壁に三方を囲まれたビルトインガレージ、半ビルトインガレージを含み、当社基準により算出します。 また、以下の工事は、施工面積に含まれていない場合でも、別途費用が加算されます。 ① 軒の出・オーバーハング工事 ：42,000円／㎡（税別） ② 下屋工事 ：30,000円／㎡（税別） ③ バルコニー工事・吹抜工事 ：60,000円／㎡（税別） ※対象となる面積は、設計図書に基づき当社が算出します。 | F36: 左記内容の対象となる面積については別紙1の参考写真をご確認下さい。
B37: □ | C37: 4 | D37: 住宅ローン | E37: 住宅ローンの手続きはお施主様自身でお願いします。 当社でしかご用意ができない書類や図面等はお渡しします。 | F37: ※事前審査も同様
B38: □ | C38: 5 | D38: 打ち合わせ 期間 | E38: 最大3ヵ月間 (回数：6回) | F38: 打ち合わせ回数6回以下で下記の特典があります。 6回：★10万円相当 5回：★★20万円相当 ※初回ヒアリングは除く
B39: □ | C39: 6 | D39: 仕様 | E39: セミオーダー制 当社の設計士がこだわり抜いた【 STYLE BOOK 】からのみ選択できます。
B40: □ | C40: 7 | D40: 長期優良住宅 | E40: 認定基準として、少なくとも1の階の床面積(階段部分を除く)が40㎡以上かつ床面積の合計75㎡必要です。 また、都市計画法第53条許可の対象となる地域では認定対象外です。 | F40: 詳細は設計打ち合わせにてご確認ください。
B41: □ | C41: 8 | D41: Ua値 | E41: 0.46W/㎡･Kを目安としております。但し、間取りや窓の個数･種類によって数値が変わり、0.46W/㎡･Kを確保できない場合があります。
B42: □ | C42: 9 | D42: 窓 | E42: 施工面積が35坪未満12ヵ所、35～40坪13ヵ所、40～45坪14ヵ所、45～50坪15ヵ所、50坪以上16ヵ所までが標準個数です。 ※既製品のみ選定可能とし特注品の選択不可。 | F42: 掃き出し窓(手動シャッター付)H2200は2ヵ所まで
B43: □ | C43: 10 | D43: 建具 | E43: 開き扉H2400㎜標準(各居室・トイレ・脱衣室・ランドリーそれぞれ1ヵ所ずつ) ※片引き戸2ヵ所まで標準 | F43: 引き戸3枚目以上及び収納扉等、リビング・書斎・洗面室・ファミリーCL・その他の部屋はオプションです。
B44: □ | C44: 11 | D44: 床材 | E44: 無垢床材を使用した場合、伸縮、床鳴り、及び経年劣化による変色が発生 する場合があります。
B45: □ | C45: 12 | D45: 換気システム | E45: 換気システムは全熱交換型第一種換気システム(Panasonic)が標準です。 | F45: DSDD換気システム(okatomi)はオプションとなり、請負契約までに確定が必要です。請負契約後は変更できません。
B46: □ | C46: 13 | D46: ユニットバス | E46: 天井有り | F46: 天井無しの施工はDSDD換気システムをオプションで採用される場合のみ対応可能です。ご選択いただけるメーカーが限られますのでご注意ください。
B47: □ | C47: 14 | D47: エコキュート タンク | E47: 室外置き | F47: 室内置きはオプションです。
B48: □ | C48: 15 | D48: 点検口 | E48: 換気システムや配管の定期点検及び不具合が起きた場合に備えて1,2Fに必要な箇所に天井･床下点検口を3～4つ以上設置しています。 | F48: 点検口の個数および位置については間取りプランにより変動します。
B49: □ | C49: 16 | D49: 大工工事 | E49: 造作工事はSTYLE BOOKに記載の内容のみ対応しています。 | F49: 記載無き内容については提携リフォーム会社様へご相談ください。
B50: □ | C50: 17 | D50: トラブル防止 | E50: STYLE BOOKに掲載の商品は、告知無しで変更になる場合があります。 ※各メーカーの商品改定および更新が定期的に行われるため、 契約締結時に交付されたSTYLE BOOKの記載価格・内容が適用されます。 | F50: 打ち合わせ中に選定商品が廃番になることもありますのでご注意ください。 SNS等へのデータのUPはご遠慮ください。
B51: □ | C51: 18 | D51: オプション | E51: 標準仕様の一部をやめることによる減額(＝マイナスオプション)は対応不可です。
B52: □ | C52: 19 | D52: 式典 | E52: 地鎮祭および上棟式は省略しています。 | F52: ご希望の方は鎮め物や上棟札を着工の2週間前までに担当者にお預けください。
B53: □ | C53: 20 | D53: 施工会社 | E53: 施工については協力会社に委託する場合があります(協力会社は当社指定の一定の施工技術の基準を超えた会社)。
B54: □ | C54: 21 | D54: 撮影協力 | E54: 広告媒体（紙面・WEB・SNSなど）への利用を目的とした撮影依頼をする場合がございます。ご協力お願いいたします。
B55: □ | C55: 22 | D55: お引渡し | E55: 建物の残代金の全額お支払いを確認後、鍵をお渡しします。 外構工事の完成に関わらず、お支払いをお願いいたします。 | F55: 外構工事をGハウス外構事業部GRAN GARDENにてご契約の方は、引渡し前に着工する場合がございます。GRAN GARDEN以外の業者様による外構工事については、責任の所在が不明確となる可能性があるため、建物のお引渡し後の着工とさせていただきます。
B56: □ | C56: 23 | D56: お引越し | E56: お引越しにあたり、階段手摺の取り外しおよび設置が必要となる場合は別途25,000円(税別)発生します。 | F56: お引越しに伴い必要となる工事は別途費用が発生します。
B57: □ | C57: 24 | D57: 補助金 | E57: 補助金の手続きはお施主様自身でお願いします。 | F57: ※当社で代理申請する場合は別途費用が発生します。 ZEH補助金はGハウスの行程では対応不可です。
B58: □ | C58: 25 | D58: LINE メール | E58: 間違い防止のため、設計･コーディネーター担当へのご要望･ご質問等、ご相談内容をLINEやメールにてお伝えいただくことをお断りしております。打ち合わせの際にまとめて担当者にご相談いただくようにご協力お願いします。
A63: LIFE
D64: 項目 | E64: 標準内容 | F64: 備考
B65: □ | C65: 1 | D65: 間取り | E65: 完全自由設計 ※4マス×910mm間隔に柱または壁の設置が必要です。 | F65: 申請業務に進んでいくため、基本設計確定後の変更は出来ません。
B66: □ | C66: 2 | D66: 坪単価 | E66: 本体工事価格は,坪55万円(税別) 30坪未満の場合割増計算となり、1坪下がる度に15,000円×坪数＝追加費用が発生します。 3階建ての場合は坪単価＋40,000円UP 下屋の場合は下屋部分㎡×30,000円UP | F66: 例）28坪の場合、30坪に対して2坪下がる 30,000円×28坪＝840,000円UP
B67: □ | C67: 3 | D67: 施工面積 | E67: 建物価格は「施工面積 × 坪単価」にて算出します。 施工面積は、延床面積に加え、外壁に三方を囲まれたビルトインガレージ、半ビルトインガレージを含み、当社基準により算出します。 また、以下の工事は、施工面積に含まれていない場合でも、別途費用が加算されます。 ① 軒の出・オーバーハング工事 ：42,000円／㎡（税別） ② 下屋工事 ：30,000円／㎡（税別） ③ バルコニー工事・吹抜工事 ：60,000円／㎡（税別） ※対象となる面積は、設計図書に基づき当社が算出します。 | F67: 左記内容の対象となる面積については別紙1の参考写真をご確認下さい。
B68: □ | C68: 4 | D68: 住宅ローン | E68: 住宅ローンの手続きはお施主様自身でお願いします。 当社でしかご用意ができない書類や図面等はお渡しします。 | F68: ※事前審査も同様
B69: □ | C69: 5 | D69: 打ち合わせ 期間 | E69: 最大3ヵ月間 （回数：6回） | F69: 打ち合わせ回数6回以下で下記の特典があります。 6回：★10万円相当 5回：★★20万円相当 ※初回ヒアリングは除く
B70: □ | C70: 6 | D70: 仕様 | E70: セミオーダー制 当社の設計士がこだわり抜いた【 STYLE BOOK 】からのみ選択できます。
B71: □ | C71: 7 | D71: 長期優良住宅 | E71: 認定基準として、少なくとも1の階の床面積が階段部分を除いて40㎡以上必要です。 また、都市計画法第53条許可の対象となる地域では認定対象外です。 | F71: 詳細は設計打ち合わせにてご確認ください。
B72: □ | C72: 8 | D72: Ua値 | E72: 0.46W/㎡･Kを目安としております。但し、間取りや窓の個数･種類によって数値が変わり、0.46W/㎡･Kを確保できない場合があります。
B73: □ | C73: 9 | D73: 窓 | E73: 施工面積が35坪未満10ヵ所、35～40坪11ヵ所、40～45坪12ヵ所、45～50坪13ヵ所、50坪以上14ヵ所までが標準個数です。 ※既製品のみ選定可能とし特注品の選択不可。 | F73: 掃き出し窓H2200は2ヵ所まで （手動シャッター2ヵ所まで）
B74: □ | C74: 10 | D74: 建具 | E74: 開き扉H2400㎜標準(各居室・トイレ・脱衣室・ランドリーそれぞれ1ヵ所ずつ) ※片引き戸2ヵ所まで標準 | F74: 引き戸3枚目以上及び収納扉等、リビング・書斎・洗面室・ファミリーCL・その他の部屋はオプションです。
B75: □ | C75: 11 | D75: 床材 | E75: 無垢床材を使用した場合、伸縮、床鳴り、及び経年劣化による変色が発生 する場合があります。
B76: □ | C76: 12 | D76: 換気システム | E76: 換気システムは全熱交換型第一種換気システム(Panasonic)が標準です。 | F76: DSDD換気システム(okatomi)はオプションとなり、請負契約までに確定が必要です。請負契約後は変更できません。
B77: □ | C77: 13 | D77: ユニットバス | E77: 天井有り | F77: 天井無しの施工はDSDD換気システムをオプションで採用される場合のみ対応可能です。ご選択いただけるメーカーが限られますのでご注意ください。
B78: □ | C78: 14 | D78: エコキュート タンク | E78: 室外置き | F78: 室内置きはオプションです。
B79: □ | C79: 15 | D79: 点検口 | E79: 換気システムや配管の定期点検及び不具合が起きた場合に備えて1Fに必要な箇所に天井･床下点検口を3～4つ以上設置しています。 | F79: 点検口の個数および位置については間取りプランにより変動します。
B80: □ | C80: 16 | D80: 大工工事 | E80: 造作工事はSTYLE BOOKに記載の内容のみ対応しています。 | F80: 記載無き内容については提携リフォーム会社様へご相談ください。
B81: □ | C81: 17 | D81: トラブル防止 | E81: STYLE BOOKに掲載の商品は、告知無しで変更になる場合があります。 ※各メーカーの商品改定及び更新が定期的に行われるため、 契約締結時に交付されたSTYLE BOOKの記載価格・内容が適用されます。 | F81: 打ち合わせ中に選定商品が廃番になることもありますのでご注意ください。 SNS等へのデータのUPはご遠慮ください。
B82: □ | C82: 18 | D82: オプション | E82: 標準仕様の一部をやめることによる減額（＝マイナスオプション）は対応不可です。
B83: □ | C83: 19 | D83: 式典 | E83: 地鎮祭および上棟式は省略しています。 | F83: ご希望の方は鎮め物や上棟札を着工の2週間前までに担当者にお預けください。
B84: □ | C84: 20 | D84: 施工会社 | E84: 施工については協力会社に委託する場合があります（協力会社は当社指定の一定の施工技術の基準を超えた会社）。
B85: □ | C85: 21 | D85: 撮影協力 | E85: 広告媒体（紙面・WEB・SNSなど）への利用を目的とした撮影依頼をする場合がございます。ご協力お願いいたします。
B86: □ | C86: 22 | D86: お引渡し | E86: 建物の残代金の全額お支払いを確認後、鍵をお渡しします。 外構工事の完成に関わらず、お支払いをお願いいたします。 | F86: 外構工事をGハウス外構事業部GRAN GARDENにてご契約の方は、引渡し前に着工する場合がございます。GRAN GARDEN以外の業者様による外構工事については、責任の所在が不明確となる可能性があるため、建物のお引渡し後の着工とさせていただきます。
B87: □ | C87: 23 | D87: お引越し | E87: お引越しにあたり、階段手摺の取り外しおよび設置が必要となる場合は別途25,000円(税別)発生します。 | F87: お引越しに伴い必要となる工事は別途費用が発生します。
B88: □ | C88: 24 | D88: 補助金 | E88: 補助金の手続きはお施主様自身でお願いします。 | F88: ※当社で代理申請する場合は別途費用が発生します。 ZEH補助金はGハウスの行程では対応不可です。
B89: □ | C89: 25 | D89: LINE メール | E89: 間違い防止のため、設計･コーディネーター担当へのご要望･ご質問等、ご相談内容をLINEやメールにてお伝えいただくことをお断りしております。打ち合わせの際にまとめて担当者にご相談いただくようにご協力お願いします。
A94: BASE
D95: 項目 | E95: 標準内容 | F95: 備考
B96: □ | C96: 1 | D96: 間取り | E96: 完全自由設計 ※4マス×910mm間隔に柱または壁の設置が必要です。 | F96: 申請業務に進んでいくため、基本設計確定後の変更は出来ません。
B97: □ | C97: 2 | D97: 坪単価 | E97: 本体工事価格は,坪50万円(税別) 30坪未満の場合割増計算となり、1坪下がる度に15,000円×坪数＝追加費用が発生します。 3階建ての場合は坪単価＋40,000円UP 下屋の場合は下屋部分㎡×30,000円UP | F97: 例）28坪の場合、30坪に対して2坪下がる 30,000円×28坪＝840,000円UP
B98: □ | C98: 3 | D98: 施工面積 | E98: 建物価格は「施工面積 × 坪単価」にて算出します。 施工面積は、延床面積に加え、外壁に三方を囲まれたビルトインガレージ、半ビルトインガレージを含み、当社基準により算出します。 また、以下の工事は、施工面積に含まれていない場合でも、別途費用が加算されます。 ① 軒の出・オーバーハング工事 ：42,000円／㎡（税別） ② 下屋工事 ：30,000円／㎡（税別） ③ バルコニー工事・吹抜工事 ：60,000円／㎡（税別） ※対象となる面積は、設計図書に基づき当社が算出します。 | F98: 左記内容の対象となる面積については別紙1の参考写真をご確認下さい。
B99: □ | C99: 4 | D99: 住宅ローン | E99: 住宅ローンの手続きはお施主様自身でお願いします。 当社でしかご用意ができない書類や図面等はお渡しします。 | F99: ※事前審査も同様
B100: □ | C100: 5 | D100: 打ち合わせ 期間 | E100: 最大3ヵ月間 （回数：6回） | F100: 打ち合わせ回数6回以下で下記の特典があります。 6回：★10万円相当 5回：★★20万円相当 ※初回ヒアリングは除く
B101: □ | C101: 6 | D101: 仕様 | E101: セミオーダー制 当社の設計士がこだわり抜いた【 STYLE BOOK 】からのみ選択できます。
B102: □ | C102: 7 | D102: 長期優良住宅 | E102: 認定基準として、少なくとも1の階の床面積が階段部分を除いて40㎡以上必要です。 また、都市計画法第53条許可の対象となる地域では認定対象外です。 | F102: 別途申請費用および構造計算費用がかかります。
B103: □ | C103: 8 | D103: Ua値 | E103: 0.46W/㎡･Kを目安としております。但し、間取りや窓の個数･種類によって数値が変わり、0.46W/㎡･Kを確保できない場合があります。
B104: □ | C104: 9 | D104: 窓 | E104: 施工面積が35坪未満10ヵ所、35～40坪11ヵ所、40～45坪12ヵ所、45～50坪13ヵ所、50坪以上14ヵ所までが標準個数です。 ※既製品のみ選定可能とし特注品の選択不可。 | F104: 掃き出し窓H2200は2ヵ所まで （手動シャッター2ヵ所まで）
B105: □ | C105: 10 | D105: 建具 | E105: 開き扉H2400㎜標準(各居室・トイレ・脱衣室・ランドリーそれぞれ1ヵ所ずつ) ※片引き戸2ヵ所まで標準 | F105: 引き戸3枚目以上及び収納扉等、リビング・書斎・洗面室・ファミリーCL・その他の部屋はオプションです。
B106: □ | C106: 11 | D106: 床材 | E106: 無垢床材を使用した場合、伸縮、床鳴り、及び経年劣化による変色が発生 する場合があります。
B107: □ | C107: 12 | D107: 換気システム | E107: 換気システムは全熱交換型第一種換気システム(Panasonic)が標準です。 | F107: DSDD換気システム(okatomi)はオプションとなり、請負契約までに確定が必要です。請負契約後は変更できません。
B108: □ | C108: 13 | D108: ユニットバス | E108: 天井有り | F108: 天井無しの施工はDSDD換気システムをオプションで採用される場合のみ対応可能です。ご選択いただけるメーカーが限られますのでご注意ください。
B109: □ | C109: 14 | D109: エコキュート タンク | E109: 室外置き | F109: 室内置きはオプションです。
B110: □ | C110: 15 | D110: 点検口 | E110: 換気システムや配管の定期点検及び不具合が起きた場合に備えて1Fに必要な箇所に天井･床下点検口を3～4つ以上設置しています。 | F110: 点検口の個数および位置については間取りプランにより変動します。
B111: □ | C111: 16 | D111: 大工工事 | E111: 造作工事はSTYLE BOOKに記載の内容のみ対応しています。 | F111: 記載無き内容については提携リフォーム会社様へご相談ください。
B112: □ | C112: 17 | D112: トラブル防止 | E112: STYLE BOOKに掲載の商品は、告知無しで変更になる場合があります。 ※各メーカーの商品改定及び更新が定期的に行われるため、 契約締結時に交付されたSTYLE BOOKの記載価格・内容が適用されます。 | F112: 打ち合わせ中に選定商品が廃番になることもありますのでご注意ください。 SNS等へのデータのUPはご遠慮ください。
...

Sheet LIFE,LIFE+キャンペーン制約事項
D1: LIFE+（キャンペーン） | E1: の仕様 制約事項一覧 | I1: ←商品名タブにて選択必要
C2: 項目 | D2: 標準内容 | F2: 備考
A3: □ | B3: 1 | C3: 間取り | D3: =IF($D$1="LACIE",VLOOKUP(C3,#REF!,2,FALSE),IF($D$1="LIFE+",VLOOKUP(C3,#REF!,2,FALSE),IF($D$1="LIFE",VLOOKUP(C3,#REF!,2,FALSE),IF($D$1="BASE",VLOOKUP(C3,#REF!,2,FALSE),IF($D$1="LIFE+（キャンペーン）",VLOOKUP(C3,#REF!,2,FALSE),IF($D$1="LIFE（キャンペーン）",VLOOKUP(C3,#REF!,2,FALSE),IF($D$1="LIFE+（キャンペーン）",VLOOKUP(C3,#REF!,2,FALSE),IF($D$1="LIFE（キャンペーン）",VLOOKUP(C3,#REF!,2,FALSE))))))))) -> #REF! | F3: =IF($D$1="LACIE",VLOOKUP(C3,#REF!,3,FALSE),IF($D$1="LIFE+",VLOOKUP(C3,#REF!,3,FALSE),IF($D$1="LIFE",VLOOKUP(C3,#REF!,3,FALSE),IF($D$1="BASE",VLOOKUP(C3,#REF!,3,FALSE),IF($D$1="LIFE+（キャンペーン）",VLOOKUP(C3,#REF!,3,FALSE),IF($D$1="LIFE（キャンペーン）",VLOOKUP(C3,#REF!,3,FALSE))))))) -> #REF!
A4: □ | B4: 2 | C4: 坪単価 | D4: =IF($D$1="LACIE",VLOOKUP(C4,#REF!,2,FALSE),IF($D$1="LIFE+",VLOOKUP(C4,#REF!,2,FALSE),IF($D$1="LIFE",VLOOKUP(C4,#REF!,2,FALSE),IF($D$1="BASE",VLOOKUP(C4,#REF!,2,FALSE),IF($D$1="LIFE+（キャンペーン）",VLOOKUP(C4,#REF!,2,FALSE),IF($D$1="LIFE（キャンペーン）",VLOOKUP(C4,#REF!,2,FALSE))))))) -> #REF! | F4: =IF($D$1="LACIE",VLOOKUP(C4,#REF!,3,FALSE),IF($D$1="LIFE+",VLOOKUP(C4,#REF!,3,FALSE),IF($D$1="LIFE",VLOOKUP(C4,#REF!,3,FALSE),IF($D$1="BASE",VLOOKUP(C4,#REF!,3,FALSE),IF($D$1="LIFE+（キャンペーン）",VLOOKUP(C4,#REF!,3,FALSE),IF($D$1="LIFE（キャンペーン）",VLOOKUP(C4,#REF!,3,FALSE))))))) -> #REF!
A5: □ | B5: 3 | C5: 住宅ローン | D5: =IF($D$1="LACIE",VLOOKUP(C5,#REF!,2,FALSE),IF($D$1="LIFE+",VLOOKUP(C5,#REF!,2,FALSE),IF($D$1="LIFE",VLOOKUP(C5,#REF!,2,FALSE),IF($D$1="BASE",VLOOKUP(C5,#REF!,2,FALSE),IF($D$1="LIFE+（キャンペーン）",VLOOKUP(C5,#REF!,2,FALSE),IF($D$1="LIFE（キャンペーン）",VLOOKUP(C5,#REF!,2,FALSE))))))) -> #REF! | F5: =IF($D$1="LACIE",VLOOKUP(C5,#REF!,3,FALSE),IF($D$1="LIFE+",VLOOKUP(C5,#REF!,3,FALSE),IF($D$1="LIFE",VLOOKUP(C5,#REF!,3,FALSE),IF($D$1="BASE",VLOOKUP(C5,#REF!,3,FALSE),IF($D$1="LIFE+（キャンペーン）",VLOOKUP(C5,#REF!,3,FALSE),IF($D$1="LIFE（キャンペーン）",VLOOKUP(C5,#REF!,3,FALSE))))))) -> #REF!
A6: □ | B6: 4 | C6: =IF(OR($D$1="LIFE+（キャンペーン）",$D$1="LIFE（キャンペーン）"),"打ち合わせ 期間") -> 打ち合わせ 期間 | D6: =IF($D$1="LACIE",VLOOKUP(C6,#REF!,2,FALSE),IF($D$1="LIFE+",VLOOKUP(C6,#REF!,2,FALSE),IF($D$1="LIFE",VLOOKUP(C6,#REF!,2,FALSE),IF($D$1="BASE",VLOOKUP(C6,#REF!,2,FALSE),IF($D$1="LIFE+（キャンペーン）",VLOOKUP(C6,#REF!,2,FALSE),IF($D$1="LIFE（キャンペーン）",VLOOKUP(C6,#REF!,2,FALSE))))))) -> #REF! | F6: =IF($D$1="LACIE",VLOOKUP(C6,#REF!,3,FALSE),IF($D$1="LIFE+",VLOOKUP(C6,#REF!,3,FALSE),IF($D$1="LIFE",VLOOKUP(C6,#REF!,3,FALSE),IF($D$1="BASE",VLOOKUP(C6,#REF!,3,FALSE),IF($D$1="LIFE+（キャンペーン）",VLOOKUP(C6,#REF!,3,FALSE),IF($D$1="LIFE（キャンペーン）",VLOOKUP(C6,#REF!,3,FALSE))))))) -> #REF!
A7: □ | B7: 5 | C7: 仕様 | D7: =IF($D$1="LACIE",VLOOKUP(C7,#REF!,2,FALSE),IF($D$1="LIFE+",VLOOKUP(C7,#REF!,2,FALSE),IF($D$1="LIFE",VLOOKUP(C7,#REF!,2,FALSE),IF($D$1="BASE",VLOOKUP(C7,#REF!,2,FALSE),IF($D$1="LIFE+（キャンペーン）",VLOOKUP(C7,#REF!,2,FALSE),IF($D$1="LIFE（キャンペーン）",VLOOKUP(C7,#REF!,2,FALSE))))))) -> #REF! | F7: =(IF($D$1="LACIE",VLOOKUP(C7,#REF!,3,FALSE),IF($D$1="LIFE+",VLOOKUP(C7,#REF!,3,FALSE),IF($D$1="LIFE",VLOOKUP(C7,#REF!,3,FALSE),IF($D$1="BASE",VLOOKUP(C7,#REF!,3,FALSE),IF($D$1="LIFE+（キャンペーン）",VLOOKUP(C7,#REF!,3,FALSE),IF($D$1="LIFE（キャンペーン）",VLOOKUP(C7,#REF!,3,FALSE)))))))) -> #REF!
A8: □ | B8: 6 | C8: 長期優良住宅 | D8: =IF($D$1="LACIE",VLOOKUP(C8,#REF!,2,FALSE),IF($D$1="LIFE+",VLOOKUP(C8,#REF!,2,FALSE),IF($D$1="LIFE",VLOOKUP(C8,#REF!,2,FALSE),IF($D$1="BASE",VLOOKUP(C8,#REF!,2,FALSE),IF($D$1="LIFE+（キャンペーン）",VLOOKUP(C8,#REF!,2,FALSE),IF($D$1="LIFE（キャンペーン）",VLOOKUP(C8,#REF!,2,FALSE))))))) -> #REF! | F8: =IF($D$1="LACIE",VLOOKUP(C8,#REF!,3,FALSE),IF($D$1="LIFE+",VLOOKUP(C8,#REF!,3,FALSE),IF($D$1="LIFE",VLOOKUP(C8,#REF!,3,FALSE),IF($D$1="BASE",VLOOKUP(C8,#REF!,3,FALSE),IF($D$1="LIFE+（キャンペーン）",VLOOKUP(C8,#REF!,3,FALSE),IF($D$1="LIFE（キャンペーン）",VLOOKUP(C8,#REF!,3,FALSE))))))) -> #REF!
A9: □ | B9: 7 | C9: Ua値 | D9: =IF($D$1="LACIE",VLOOKUP(C9,#REF!,2,FALSE),IF($D$1="LIFE+",VLOOKUP(C9,#REF!,2,FALSE),IF($D$1="LIFE",VLOOKUP(C9,#REF!,2,FALSE),IF($D$1="BASE",VLOOKUP(C9,#REF!,2,FALSE),IF($D$1="LIFE+（キャンペーン）",VLOOKUP(C9,#REF!,2,FALSE),IF($D$1="LIFE（キャンペーン）",VLOOKUP(C9,#REF!,2,FALSE))))))) -> #REF! | F9: =IF($D$1="LACIE",VLOOKUP(C9,#REF!,3,FALSE),IF($D$1="LIFE+",VLOOKUP(C9,#REF!,3,FALSE),IF($D$1="LIFE",VLOOKUP(C9,#REF!,3,FALSE),IF($D$1="BASE",VLOOKUP(C9,#REF!,3,FALSE),IF($D$1="LIFE+（キャンペーン）",VLOOKUP(C9,#REF!,3,FALSE),IF($D$1="LIFE（キャンペーン）",VLOOKUP(C9,#REF!,3,FALSE))))))) -> #REF!
A10: □ | B10: 8 | C10: 窓 | D10: =IF($D$1="LACIE",VLOOKUP(C10,#REF!,2,FALSE),IF($D$1="LIFE+",VLOOKUP(C10,#REF!,2,FALSE),IF($D$1="LIFE",VLOOKUP(C10,#REF!,2,FALSE),IF($D$1="BASE",VLOOKUP(C10,#REF!,2,FALSE),IF($D$1="LIFE+（キャンペーン）",VLOOKUP(C10,#REF!,2,FALSE),IF($D$1="LIFE（キャンペーン）",VLOOKUP(C10,#REF!,2,FALSE))))))) -> #REF! | F10: =IF($D$1="LACIE",VLOOKUP(C10,#REF!,3,FALSE),IF($D$1="LIFE+",VLOOKUP(C10,#REF!,3,FALSE),IF($D$1="LIFE",VLOOKUP(C10,#REF!,3,FALSE),IF($D$1="BASE",VLOOKUP(C10,#REF!,3,FALSE),IF($D$1="LIFE+（キャンペーン）",VLOOKUP(C10,#REF!,3,FALSE),IF($D$1="LIFE（キャンペーン）",VLOOKUP(C10,#REF!,3,FALSE))))))) -> #REF!
A11: □ | B11: 9 | C11: 建具 | D11: =IF($D$1="LACIE",VLOOKUP(C11,#REF!,2,FALSE),IF($D$1="LIFE+",VLOOKUP(C11,#REF!,2,FALSE),IF($D$1="LIFE",VLOOKUP(C11,#REF!,2,FALSE),IF($D$1="BASE",VLOOKUP(C11,#REF!,2,FALSE),IF($D$1="LIFE+（キャンペーン）",VLOOKUP(C11,#REF!,2,FALSE),IF($D$1="LIFE（キャンペーン）",VLOOKUP(C11,#REF!,2,FALSE))))))) -> #REF! | F11: =IF($D$1="LACIE",VLOOKUP(C11,#REF!,3,FALSE),IF($D$1="LIFE+",VLOOKUP(C11,#REF!,3,FALSE),IF($D$1="LIFE",VLOOKUP(C11,#REF!,3,FALSE),IF($D$1="BASE",VLOOKUP(C11,#REF!,3,FALSE),IF($D$1="LIFE+（キャンペーン）",VLOOKUP(C11,#REF!,3,FALSE),IF($D$1="LIFE（キャンペーン）",VLOOKUP(C11,#REF!,3,FALSE))))))) -> #REF!
A12: □ | B12: 10 | C12: 床材 | D12: =IF($D$1="LACIE",VLOOKUP(C12,#REF!,2,FALSE),IF($D$1="LIFE+",VLOOKUP(C12,#REF!,2,FALSE),IF($D$1="LIFE",VLOOKUP(C12,#REF!,2,FALSE),IF($D$1="BASE",VLOOKUP(C12,#REF!,2,FALSE),IF($D$1="LIFE+（キャンペーン）",VLOOKUP(C12,#REF!,2,FALSE),IF($D$1="LIFE（キャンペーン）",VLOOKUP(C12,#REF!,2,FALSE))))))) -> #REF!
A13: □ | B13: 11 | C13: 換気システム | D13: =IF($D$1="LACIE",VLOOKUP(C13,#REF!,2,FALSE),IF($D$1="LIFE+",VLOOKUP(C13,#REF!,2,FALSE),IF($D$1="LIFE",VLOOKUP(C13,#REF!,2,FALSE),IF($D$1="BASE",VLOOKUP(C13,#REF!,2,FALSE),IF($D$1="LIFE+（キャンペーン）",VLOOKUP(C13,#REF!,2,FALSE),IF($D$1="LIFE（キャンペーン）",VLOOKUP(C13,#REF!,2,FALSE))))))) -> #REF! | F13: =IF($D$1="LACIE",VLOOKUP(C13,#REF!,3,FALSE),IF($D$1="LIFE+",VLOOKUP(C13,#REF!,3,FALSE),IF($D$1="LIFE",VLOOKUP(C13,#REF!,3,FALSE),IF($D$1="BASE",VLOOKUP(C13,#REF!,3,FALSE),IF($D$1="LIFE+（キャンペーン）",VLOOKUP(C13,#REF!,3,FALSE),IF($D$1="LIFE（キャンペーン）",VLOOKUP(C13,#REF!,3,FALSE))))))) -> #REF!
A14: □ | B14: 12 | C14: ユニットバス | D14: =IF($D$1="LACIE",VLOOKUP(C14,#REF!,2,FALSE),IF($D$1="LIFE+",VLOOKUP(C14,#REF!,2,FALSE),IF($D$1="LIFE",VLOOKUP(C14,#REF!,2,FALSE),IF($D$1="BASE",VLOOKUP(C14,#REF!,2,FALSE),IF($D$1="LIFE+（キャンペーン）",VLOOKUP(C14,#REF!,2,FALSE),IF($D$1="LIFE（キャンペーン）",VLOOKUP(C14,#REF!,2,FALSE))))))) -> #REF! | F14: =IF($D$1="LACIE",VLOOKUP(C14,#REF!,3,FALSE),IF($D$1="LIFE+",VLOOKUP(C14,#REF!,3,FALSE),IF($D$1="LIFE",VLOOKUP(C14,#REF!,3,FALSE),IF($D$1="BASE",VLOOKUP(C14,#REF!,3,FALSE),IF($D$1="LIFE+（キャンペーン）",VLOOKUP(C14,#REF!,3,FALSE),IF($D$1="LIFE（キャンペーン）",VLOOKUP(C14,#REF!,3,FALSE))))))) -> #REF!
A15: □ | B15: 13 | C15: エコキュート タンク | D15: =IF($D$1="LACIE",VLOOKUP(C15,#REF!,2,FALSE),IF($D$1="LIFE+",VLOOKUP(C15,#REF!,2,FALSE),IF($D$1="LIFE",VLOOKUP(C15,#REF!,2,FALSE),IF($D$1="BASE",VLOOKUP(C15,#REF!,2,FALSE),IF($D$1="LIFE+（キャンペーン）",VLOOKUP(C15,#REF!,2,FALSE),IF($D$1="LIFE（キャンペーン）",VLOOKUP(C15,#REF!,2,FALSE))))))) -> #REF! | F15: =IF($D$1="LACIE",VLOOKUP(C15,#REF!,3,FALSE),IF($D$1="LIFE+",VLOOKUP(C15,#REF!,3,FALSE),IF($D$1="LIFE",VLOOKUP(C15,#REF!,3,FALSE),IF($D$1="BASE",VLOOKUP(C15,#REF!,3,FALSE),IF($D$1="LIFE+（キャンペーン）",VLOOKUP(C15,#REF!,3,FALSE),IF($D$1="LIFE（キャンペーン）",VLOOKUP(C15,#REF!,3,FALSE))))))) -> #REF!
A16: □ | B16: 14 | C16: 点検口 | D16: =IF($D$1="LACIE",VLOOKUP(C16,#REF!,2,FALSE),IF($D$1="LIFE+",VLOOKUP(C16,#REF!,2,FALSE),IF($D$1="LIFE",VLOOKUP(C16,#REF!,2,FALSE),IF($D$1="BASE",VLOOKUP(C16,#REF!,2,FALSE),IF($D$1="LIFE+（キャンペーン）",VLOOKUP(C16,#REF!,2,FALSE),IF($D$1="LIFE（キャンペーン）",VLOOKUP(C16,#REF!,2,FALSE))))))) -> #REF! | F16: =IF($D$1="LACIE",VLOOKUP(C16,#REF!,3,FALSE),IF($D$1="LIFE+",VLOOKUP(C16,#REF!,3,FALSE),IF($D$1="LIFE",VLOOKUP(C16,#REF!,3,FALSE),IF($D$1="BASE",VLOOKUP(C16,#REF!,3,FALSE),IF($D$1="LIFE+（キャンペーン）",VLOOKUP(C16,#REF!,3,FALSE),IF($D$1="LIFE（キャンペーン）",VLOOKUP(C16,#REF!,3,FALSE))))))) -> #REF!
A17: □ | B17: 15 | C17: 大工工事 | D17: =IF($D$1="LACIE",VLOOKUP(C17,#REF!,2,FALSE),IF($D$1="LIFE+",VLOOKUP(C17,#REF!,2,FALSE),IF($D$1="LIFE",VLOOKUP(C17,#REF!,2,FALSE),IF($D$1="BASE",VLOOKUP(C17,#REF!,2,FALSE),IF($D$1="LIFE+（キャンペーン）",VLOOKUP(C17,#REF!,2,FALSE),IF($D$1="LIFE（キャンペーン）",VLOOKUP(C17,#REF!,2,FALSE))))))) -> #REF! | F17: =IF($D$1="LACIE",VLOOKUP(C17,#REF!,3,FALSE),IF($D$1="LIFE+",VLOOKUP(C17,#REF!,3,FALSE),IF($D$1="LIFE",VLOOKUP(C17,#REF!,3,FALSE),IF($D$1="BASE",VLOOKUP(C17,#REF!,3,FALSE),IF($D$1="LIFE+（キャンペーン）",VLOOKUP(C17,#REF!,3,FALSE),IF($D$1="LIFE（キャンペーン）",VLOOKUP(C17,#REF!,3,FALSE))))))) -> #REF!
A18: □ | B18: 16 | C18: トラブル防止 | D18: =IF($D$1="LACIE",VLOOKUP(C18,#REF!,2,FALSE),IF($D$1="LIFE+",VLOOKUP(C18,#REF!,2,FALSE),IF($D$1="LIFE",VLOOKUP(C18,#REF!,2,FALSE),IF($D$1="BASE",VLOOKUP(C18,#REF!,2,FALSE),IF($D$1="LIFE+（キャンペーン）",VLOOKUP(C18,#REF!,2,FALSE),IF($D$1="LIFE（キャンペーン）",VLOOKUP(C18,#REF!,2,FALSE))))))) -> #REF! | F18: =IF($D$1="LACIE",VLOOKUP(C18,#REF!,3,FALSE),IF($D$1="LIFE+",VLOOKUP(C18,#REF!,3,FALSE),IF($D$1="LIFE",VLOOKUP(C18,#REF!,3,FALSE),IF($D$1="BASE",VLOOKUP(C18,#REF!,3,FALSE),IF($D$1="LIFE+（キャンペーン）",VLOOKUP(C18,#REF!,3,FALSE),IF($D$1="LIFE（キャンペーン）",VLOOKUP(C18,#REF!,3,FALSE))))))) -> #REF!
A19: □ | B19: 17 | C19: オプション | D19: =IF($D$1="LACIE",VLOOKUP(C19,#REF!,2,FALSE),IF($D$1="LIFE+",VLOOKUP(C19,#REF!,2,FALSE),IF($D$1="LIFE",VLOOKUP(C19,#REF!,2,FALSE),IF($D$1="BASE",VLOOKUP(C19,#REF!,2,FALSE),IF($D$1="LIFE+（キャンペーン）",VLOOKUP(C19,#REF!,2,FALSE),IF($D$1="LIFE（キャンペーン）",VLOOKUP(C19,#REF!,2,FALSE))))))) -> #REF! | F19: =IF($D$1="LACIE",VLOOKUP(C19,#REF!,3,FALSE),IF($D$1="LIFE+",VLOOKUP(C19,#REF!,3,FALSE),IF($D$1="LIFE",VLOOKUP(C19,#REF!,3,FALSE),IF($D$1="BASE",VLOOKUP(C19,#REF!,3,FALSE),IF($D$1="LIFE+（キャンペーン）",VLOOKUP(C19,#REF!,3,FALSE),IF($D$1="LIFE（キャンペーン）",VLOOKUP(C19,#REF!,3,FALSE))))))) -> #REF!
A20: □ | B20: 18 | C20: 式典 | D20: =IF($D$1="LACIE",VLOOKUP(C20,#REF!,2,FALSE),IF($D$1="LIFE+",VLOOKUP(C20,#REF!,2,FALSE),IF($D$1="LIFE",VLOOKUP(C20,#REF!,2,FALSE),IF($D$1="BASE",VLOOKUP(C20,#REF!,2,FALSE),IF($D$1="LIFE+（キャンペーン）",VLOOKUP(C20,#REF!,2,FALSE),IF($D$1="LIFE（キャンペーン）",VLOOKUP(C20,#REF!,2,FALSE))))))) -> #REF! | F20: =IF($D$1="LACIE",VLOOKUP(C20,#REF!,3,FALSE),IF($D$1="LIFE+",VLOOKUP(C20,#REF!,3,FALSE),IF($D$1="LIFE",VLOOKUP(C20,#REF!,3,FALSE),IF($D$1="BASE",VLOOKUP(C20,#REF!,3,FALSE),IF($D$1="LIFE+（キャンペーン）",VLOOKUP(C20,#REF!,3,FALSE),IF($D$1="LIFE（キャンペーン）",VLOOKUP(C20,#REF!,3,FALSE))))))) -> #REF!
A21: □ | B21: 19 | C21: 施工会社 | D21: =IF($D$1="LACIE",VLOOKUP(C21,#REF!,2,FALSE),IF($D$1="LIFE+",VLOOKUP(C21,#REF!,2,FALSE),IF($D$1="LIFE",VLOOKUP(C21,#REF!,2,FALSE),IF($D$1="BASE",VLOOKUP(C21,#REF!,2,FALSE),IF($D$1="LIFE+（キャンペーン）",VLOOKUP(C21,#REF!,2,FALSE),IF($D$1="LIFE（キャンペーン）",VLOOKUP(C21,#REF!,2,FALSE))))))) -> #REF! | F21: =IF($D$1="LACIE",VLOOKUP(C21,#REF!,3,FALSE),IF($D$1="LIFE+",VLOOKUP(C21,#REF!,3,FALSE),IF($D$1="LIFE",VLOOKUP(C21,#REF!,3,FALSE),IF($D$1="BASE",VLOOKUP(C21,#REF!,3,FALSE),IF($D$1="LIFE+（キャンペーン）",VLOOKUP(C21,#REF!,3,FALSE),IF($D$1="LIFE（キャンペーン）",VLOOKUP(C21,#REF!,3,FALSE))))))) -> #REF!
A22: □ | B22: 20 | C22: YouTube | D22: =IF($D$1="LACIE",VLOOKUP(C22,#REF!,2,FALSE),IF($D$1="LIFE+",VLOOKUP(C22,#REF!,2,FALSE),IF($D$1="LIFE",VLOOKUP(C22,#REF!,2,FALSE),IF($D$1="BASE",VLOOKUP(C22,#REF!,2,FALSE),IF($D$1="LIFE+（キャンペーン）",VLOOKUP(C22,#REF!,2,FALSE),IF($D$1="LIFE（キャンペーン）",VLOOKUP(C22,#REF!,2,FALSE))))))) -> #REF! | F22: =IF($D$1="LACIE",VLOOKUP(C22,#REF!,3,FALSE),IF($D$1="LIFE+",VLOOKUP(C22,#REF!,3,FALSE),IF($D$1="LIFE",VLOOKUP(C22,#REF!,3,FALSE),IF($D$1="BASE",VLOOKUP(C22,#REF!,3,FALSE),IF($D$1="LIFE+（キャンペーン）",VLOOKUP(C22,#REF!,3,FALSE),IF($D$1="LIFE（キャンペーン）",VLOOKUP(C22,#REF!,3,FALSE))))))) -> #REF!
A23: □ | B23: 21 | C23: お引渡し | D23: =IF($D$1="LACIE",VLOOKUP(C23,#REF!,2,FALSE),IF($D$1="LIFE+",VLOOKUP(C23,#REF!,2,FALSE),IF($D$1="LIFE",VLOOKUP(C23,#REF!,2,FALSE),IF($D$1="BASE",VLOOKUP(C23,#REF!,2,FALSE),IF($D$1="LIFE+（キャンペーン）",VLOOKUP(C23,#REF!,2,FALSE),IF($D$1="LIFE（キャンペーン）",VLOOKUP(C23,#REF!,2,FALSE))))))) -> #REF! | F23: =IF($D$1="LACIE",VLOOKUP(C23,#REF!,3,FALSE),IF($D$1="LIFE+",VLOOKUP(C23,#REF!,3,FALSE),IF($D$1="LIFE",VLOOKUP(C23,#REF!,3,FALSE),IF($D$1="BASE",VLOOKUP(C23,#REF!,3,FALSE),IF($D$1="LIFE+（キャンペーン）",VLOOKUP(C23,#REF!,3,FALSE),IF($D$1="LIFE（キャンペーン）",VLOOKUP(C23,#REF!,3,FALSE))))))) -> #REF!
A24: □ | B24: 22 | C24: お引越し | D24: =IF($D$1="LACIE",VLOOKUP(C24,#REF!,2,FALSE),IF($D$1="LIFE+",VLOOKUP(C24,#REF!,2,FALSE),IF($D$1="LIFE",VLOOKUP(C24,#REF!,2,FALSE),IF($D$1="BASE",VLOOKUP(C24,#REF!,2,FALSE),IF($D$1="LIFE+（キャンペーン）",VLOOKUP(C24,#REF!,2,FALSE),IF($D$1="LIFE（キャンペーン）",VLOOKUP(C24,#REF!,2,FALSE))))))) -> #REF! | F24: =IF($D$1="LACIE",VLOOKUP(C24,#REF!,3,FALSE),IF($D$1="LIFE+",VLOOKUP(C24,#REF!,3,FALSE),IF($D$1="LIFE",VLOOKUP(C24,#REF!,3,FALSE),IF($D$1="BASE",VLOOKUP(C24,#REF!,3,FALSE),IF($D$1="LIFE+（キャンペーン）",VLOOKUP(C24,#REF!,3,FALSE),IF($D$1="LIFE（キャンペーン）",VLOOKUP(C24,#REF!,3,FALSE))))))) -> #REF!
... A26: □ | B26: 24 | C26: LINE メール | D26: =IF($D$1="LACIE",VLOOKUP(C26,#REF!,2,FALSE),IF($D$1="LIFE+",VLOOKUP(C26,#REF!,2,FALSE),IF($D$1="LIFE",VLOOKUP(C26,#REF!,2,FALSE),IF($D$1="BASE",VLOOKUP(C26,#REF!,2,FALSE),IF($D$1="LIFE+（キャンペーン）",VLOOKUP(C26,#REF!,2,FALSE),IF($D$1="LIFE（キャンペーン）",VLOOKUP(C26,#REF!,2,FALSE))))))) -> #REF! | F26: =IF($D$1="LACIE",VLOOKUP(C26,#REF!,3,FALSE),IF($D$1="LIFE+",VLOOKUP(C26,#REF!,3,FALSE),IF($D$1="LIFE",VLOOKUP(C26,#REF!,3,FALSE),IF($D$1="BASE",VLOOKUP(C26,#REF!,3,FALSE),IF($D$1="LIFE+（キャンペーン）",VLOOKUP(C26,#REF!,3,FALSE),IF($D$1="LIFE（キャンペーン）",VLOOKUP(C26,#REF!,3,FALSE))))))) -> #REF!
E28: 住所 | F28: =初期入力!B5 -> 0
E30: 氏名 | F30: =初期入力!B4 -> 0 | G30: 印
E32: 住所 | F32: =IF(初期入力!B7="","",初期入力!B7)
E34: 氏名 | F34: =IF(初期入力!B6="","",初期入力!B6) | G34: 印

Sheet HOURS制約事項
D1: HOURS | E1: の仕様 制約事項一覧 | I1: ←商品名タブにて選択必要
C2: 項目 | D2: 標準内容 | F2: 備考
A3: □ | B3: 1 | C3: =IF($D$1="HOURS",作業用タブ2!D34,作業用タブ2!D3) -> 間取り | D3: =IF($D$1="LIFE LIMITED(キャンペーン)",VLOOKUP(C3,作業用タブ2!$D$2:$F$29,2,FALSE),IF($D$1="HOURS",VLOOKUP(C3,作業用タブ2!$D$33:$F$61,2,FALSE),IF($D$1="LIFE+ LIMITED(キャンペーン)",VLOOKUP(C3,作業用タブ2!$D$2:$F$29,2,FALSE)))) -> 完全自由設計 ※4マス×910mm間隔に柱または壁の設置が必要です。 | F3: =IF($D$1="LIFE LIMITED(キャンペーン)",VLOOKUP(C3,作業用タブ2!$D$2:$F$29,3,FALSE),IF($D$1="HOURS",VLOOKUP(C3,作業用タブ2!$D$33:$F$61,3,FALSE),IF($D$1="LIFE+ LIMITED(キャンペーン)",VLOOKUP(C3,作業用タブ2!$D$2:$F$29,3,FALSE)))) -> 申請業務に進んでいくため、基本設計確定後の変更は出来ません。
A4: □ | B4: 2 | C4: =IF($D$1="HOURS",作業用タブ2!D35,作業用タブ2!D4) -> 坪単価 | D4: =IF($D$1="LIFE LIMITED(キャンペーン)",VLOOKUP(C4,作業用タブ2!$D$2:$F$29,2,FALSE),IF($D$1="HOURS",VLOOKUP(C4,作業用タブ2!$D$33:$F$61,2,FALSE),IF($D$1="LIFE+ LIMITED(キャンペーン)",VLOOKUP(C4,作業用タブ2!$D$2:$F$29,2,FALSE)))) -> 本体工事価格は63万円(税別) 30坪未満の場合割増計算となり、1坪下がる度に15,000円×坪数＝追加費用が発生します。 3階建ての場合は坪単価＋40,000円UP 下屋の場合は下屋部分㎡×30,000円UP | F4: =IF($D$1="LIFE LIMITED(キャンペーン)",VLOOKUP(C4,作業用タブ2!$D$2:$F$29,3,FALSE),IF($D$1="HOURS",VLOOKUP(C4,作業用タブ2!$D$33:$F$61,3,FALSE),IF($D$1="LIFE+ LIMITED(キャンペーン)",VLOOKUP(C4,作業用タブ2!$D$2:$F$29,3,FALSE)))) -> 例)28坪の場合、30坪に対して2坪下がる 30,000円×28坪＝840,000円UP
A5: □ | B5: 3 | C5: 施工面積 | D5: =IF($D$1="LIFE LIMITED(キャンペーン)",VLOOKUP(C5,作業用タブ2!$D$2:$F$29,2,FALSE),IF($D$1="HOURS",VLOOKUP(C5,作業用タブ2!$D$33:$F$61,2,FALSE),IF($D$1="LIFE+ LIMITED(キャンペーン)",VLOOKUP(C5,作業用タブ2!$D$2:$F$29,2,FALSE)))) -> 建物価格は「施工面積 × 坪単価」にて算出します。 施工面積は、延床面積に加え、外壁に三方を囲まれたビルトインガレージ、半ビルトインガレージを含み、当社基準により算出します。 また、以下の工事は、施工面積に含まれていない場合でも、別途費用が加算されます。 ① 軒の出・オーバーハング工事 ：42,000円／㎡（税別） ② 下屋工事 ：30,000円／㎡（税別） ③ バルコニー工事・吹抜工事 ：60,000円／㎡（税別） ※対象となる面積は、設計図書に基づき当社が算出します。 | F5: =IF($D$1="LIFE LIMITED(キャンペーン)",VLOOKUP(C5,作業用タブ2!$D$2:$F$29,3,FALSE),IF($D$1="HOURS",VLOOKUP(C5,作業用タブ2!$D$33:$F$61,3,FALSE),IF($D$1="LIFE+ LIMITED(キャンペーン)",VLOOKUP(C5,作業用タブ2!$D$2:$F$29,3,FALSE)))) -> 左記内容の対象となる面積については別紙1の参考写真をご確認下さい。
A6: □ | B6: 4 | C6: =IF($D$1="HOURS",作業用タブ2!D37,作業用タブ2!D5) -> 住宅ローン | D6: =IF($D$1="LIFE LIMITED(キャンペーン)",VLOOKUP(C6,作業用タブ2!$D$2:$F$29,2,FALSE),IF($D$1="HOURS",VLOOKUP(C6,作業用タブ2!$D$33:$F$61,2,FALSE),IF($D$1="LIFE+ LIMITED(キャンペーン)",VLOOKUP(C6,作業用タブ2!$D$2:$F$29,2,FALSE)))) -> 住宅ローンの手続きはお施主様自身でお願いします。 当社でしかご用意ができない書類や図面等はお渡しします。 | F6: =IF($D$1="LIFE LIMITED(キャンペーン)",VLOOKUP(C6,作業用タブ2!$D$2:$F$29,3,FALSE),IF($D$1="HOURS",VLOOKUP(C6,作業用タブ2!$D$33:$F$61,3,FALSE),IF($D$1="LIFE+ LIMITED(キャンペーン)",VLOOKUP(C6,作業用タブ2!$D$2:$F$29,3,FALSE)))) -> ※事前審査も同様
A7: □ | B7: 5 | C7: =IF($D$1="HOURS",作業用タブ2!D38,作業用タブ2!D6) -> 打ち合わせ 期間 | D7: =IF($D$1="LIFE LIMITED(キャンペーン)",VLOOKUP(C7,作業用タブ2!$D$2:$F$29,2,FALSE),IF($D$1="HOURS",VLOOKUP(C7,作業用タブ2!$D$33:$F$61,2,FALSE),IF($D$1="LIFE+ LIMITED(キャンペーン)",VLOOKUP(C7,作業用タブ2!$D$2:$F$29,2,FALSE)))) -> 最大3ヵ月間 (回数：6回) | F7: =IF($D$1="LIFE LIMITED(キャンペーン)",VLOOKUP(C7,作業用タブ2!$D$2:$F$29,3,FALSE),IF($D$1="HOURS",VLOOKUP(C7,作業用タブ2!$D$33:$F$61,3,FALSE),IF($D$1="LIFE+ LIMITED(キャンペーン)",VLOOKUP(C7,作業用タブ2!$D$2:$F$29,3,FALSE)))) -> 打ち合わせ回数6回以下で下記の特典があります。 6回：★10万円相当 5回：★★20万円相当 ※初回ヒアリングは除く
A8: □ | B8: 6 | C8: =IF($D$1="HOURS",作業用タブ2!D39,作業用タブ2!D7) -> 仕様 | D8: =IF($D$1="LIFE LIMITED(キャンペーン)",VLOOKUP(C8,作業用タブ2!$D$2:$F$29,2,FALSE),IF($D$1="HOURS",VLOOKUP(C8,作業用タブ2!$D$33:$F$61,2,FALSE),IF($D$1="LIFE+ LIMITED(キャンペーン)",VLOOKUP(C8,作業用タブ2!$D$2:$F$29,2,FALSE)))) -> セミオーダー制 当社の設計士がこだわり抜いた【 STYLE BOOK 】からのみ選択できます。 | F8: =IF($D$1="LIFE LIMITED(キャンペーン)",VLOOKUP(C8,作業用タブ2!$D$2:$F$29,3,FALSE),IF($D$1="HOURS",VLOOKUP(C8,作業用タブ2!$D$33:$F$61,3,FALSE),IF($D$1="LIFE+ LIMITED(キャンペーン)",VLOOKUP(C8,作業用タブ2!$D$2:$F$29,3,FALSE))))
A9: □ | B9: 7 | C9: =IF($D$1="HOURS",作業用タブ2!D40,作業用タブ2!D8) -> 長期優良住宅 | D9: =IF($D$1="LIFE LIMITED(キャンペーン)",VLOOKUP(C9,作業用タブ2!$D$2:$F$29,2,FALSE),IF($D$1="HOURS",VLOOKUP(C9,作業用タブ2!$D$33:$F$61,2,FALSE),IF($D$1="LIFE+ LIMITED(キャンペーン)",VLOOKUP(C9,作業用タブ2!$D$2:$F$29,2,FALSE)))) -> 認定基準として、少なくとも1の階の床面積(階段部分を除く)が40㎡以上かつ床面積の合計75㎡必要です。 また、都市計画法第53条許可の対象となる地域では認定対象外です。 | F9: =IF($D$1="LIFE LIMITED(キャンペーン)",VLOOKUP(C9,作業用タブ2!$D$2:$F$29,3,FALSE),IF($D$1="HOURS",VLOOKUP(C9,作業用タブ2!$D$33:$F$61,3,FALSE),IF($D$1="LIFE+ LIMITED(キャンペーン)",VLOOKUP(C9,作業用タブ2!$D$2:$F$29,3,FALSE)))) -> 詳細は設計打ち合わせにてご確認ください。
A10: □ | B10: 8 | C10: =IF($D$1="HOURS",作業用タブ2!D41,作業用タブ2!D9) -> Ua値 | D10: =IF($D$1="LIFE LIMITED(キャンペーン)",VLOOKUP(C10,作業用タブ2!$D$2:$F$29,2,FALSE),IF($D$1="HOURS",VLOOKUP(C10,作業用タブ2!$D$33:$F$61,2,FALSE),IF($D$1="LIFE+ LIMITED(キャンペーン)",VLOOKUP(C10,作業用タブ2!$D$2:$F$29,2,FALSE)))) -> 0.46W/㎡･Kを目安としております。但し、間取りや窓の個数･種類によって数値が変わり、0.46W/㎡･Kを確保できない場合があります。 | F10: =IF($D$1="LIFE LIMITED(キャンペーン)",VLOOKUP(C10,作業用タブ2!$D$2:$F$29,3,FALSE),IF($D$1="HOURS",VLOOKUP(C10,作業用タブ2!$D$33:$F$61,3,FALSE),IF($D$1="LIFE+ LIMITED(キャンペーン)",VLOOKUP(C10,作業用タブ2!$D$2:$F$29,3,FALSE))))
A11: □ | B11: 9 | C11: =IF($D$1="HOURS",作業用タブ2!D42,作業用タブ2!D10) -> 窓 | D11: =IF($D$1="LIFE LIMITED(キャンペーン)",VLOOKUP(C11,作業用タブ2!$D$2:$F$29,2,FALSE),IF($D$1="HOURS",VLOOKUP(C11,作業用タブ2!$D$33:$F$61,2,FALSE),IF($D$1="LIFE+ LIMITED(キャンペーン)",VLOOKUP(C11,作業用タブ2!$D$2:$F$29,2,FALSE)))) -> 施工面積が35坪未満12ヵ所、35～40坪13ヵ所、40～45坪14ヵ所、45～50坪15ヵ所、50坪以上16ヵ所までが標準個数です。 ※既製品のみ選定可能とし特注品の選択不可。 | F11: =IF($D$1="LIFE LIMITED(キャンペーン)",VLOOKUP(C11,作業用タブ2!$D$2:$F$29,3,FALSE),IF($D$1="HOURS",VLOOKUP(C11,作業用タブ2!$D$33:$F$61,3,FALSE),IF($D$1="LIFE+ LIMITED(キャンペーン)",VLOOKUP(C11,作業用タブ2!$D$2:$F$29,3,FALSE)))) -> 掃き出し窓(手動シャッター付)H2200は2ヵ所まで
A12: □ | B12: 10 | C12: =IF($D$1="HOURS",作業用タブ2!D43,作業用タブ2!D11) -> 建具 | D12: =IF($D$1="LIFE LIMITED(キャンペーン)",VLOOKUP(C12,作業用タブ2!$D$2:$F$29,2,FALSE),IF($D$1="HOURS",VLOOKUP(C12,作業用タブ2!$D$33:$F$61,2,FALSE),IF($D$1="LIFE+ LIMITED(キャンペーン)",VLOOKUP(C12,作業用タブ2!$D$2:$F$29,2,FALSE)))) -> 開き扉H2400㎜標準(各居室・トイレ・脱衣室・ランドリーそれぞれ1ヵ所ずつ) ※片引き戸2ヵ所まで標準 | F12: =IF($D$1="LIFE LIMITED(キャンペーン)",VLOOKUP(C12,作業用タブ2!$D$2:$F$29,3,FALSE),IF($D$1="HOURS",VLOOKUP(C12,作業用タブ2!$D$33:$F$61,3,FALSE),IF($D$1="LIFE+ LIMITED(キャンペーン)",VLOOKUP(C12,作業用タブ2!$D$2:$F$29,3,FALSE)))) -> 引き戸3枚目以上及び収納扉等、リビング・書斎・洗面室・ファミリーCL・その他の部屋はオプションです。
A13: □ | B13: 11 | C13: 床材 | D13: =IF($D$1="LIFE LIMITED(キャンペーン)",VLOOKUP(C13,作業用タブ2!$D$2:$F$29,2,FALSE),IF($D$1="HOURS",VLOOKUP(C13,作業用タブ2!$D$33:$F$61,2,FALSE),IF($D$1="LIFE+ LIMITED(キャンペーン)",VLOOKUP(C13,作業用タブ2!$D$2:$F$29,2,FALSE)))) -> 無垢床材を使用した場合、伸縮、床鳴り、及び経年劣化による変色が発生 する場合があります。 | F13: =IF($D$1="LIFE LIMITED(キャンペーン)",VLOOKUP(C13,作業用タブ2!$D$2:$F$29,3,FALSE),IF($D$1="HOURS",VLOOKUP(C13,作業用タブ2!$D$33:$F$61,3,FALSE),IF($D$1="LIFE+ LIMITED(キャンペーン)",VLOOKUP(C13,作業用タブ2!$D$2:$F$29,3,FALSE)))) -> 0
A14: □ | B14: 12 | C14: 換気システム | D14: =IF($D$1="LIFE LIMITED(キャンペーン)",VLOOKUP(C14,作業用タブ2!$D$2:$F$29,2,FALSE),IF($D$1="HOURS",VLOOKUP(C14,作業用タブ2!$D$33:$F$61,2,FALSE),IF($D$1="LIFE+ LIMITED(キャンペーン)",VLOOKUP(C14,作業用タブ2!$D$2:$F$29,2,FALSE)))) -> 換気システムは全熱交換型第一種換気システム(Panasonic)が標準です。 | F14: =IF($D$1="LIFE LIMITED(キャンペーン)",VLOOKUP(C14,作業用タブ2!$D$2:$F$29,3,FALSE),IF($D$1="HOURS",VLOOKUP(C14,作業用タブ2!$D$33:$F$61,3,FALSE),IF($D$1="LIFE+ LIMITED(キャンペーン)",VLOOKUP(C14,作業用タブ2!$D$2:$F$29,3,FALSE)))) -> DSDD換気システム(okatomi)はオプションとなり、請負契約までに確定が必要です。請負契約後は変更できません。
A15: □ | B15: 13 | C15: =IF($D$1="HOURS",作業用タブ2!D46,作業用タブ2!D17) -> ユニットバス | D15: =IF($D$1="LIFE LIMITED(キャンペーン)",VLOOKUP(C15,作業用タブ2!$D$2:$F$29,2,FALSE),IF($D$1="HOURS",VLOOKUP(C15,作業用タブ2!$D$33:$F$61,2,FALSE),IF($D$1="LIFE+ LIMITED(キャンペーン)",VLOOKUP(C15,作業用タブ2!$D$2:$F$29,2,FALSE)))) -> 天井有り | F15: =IF($D$1="LIFE LIMITED(キャンペーン)",VLOOKUP(C15,作業用タブ2!$D$2:$F$29,3,FALSE),IF($D$1="HOURS",VLOOKUP(C15,作業用タブ2!$D$33:$F$61,3,FALSE),IF($D$1="LIFE+ LIMITED(キャンペーン)",VLOOKUP(C15,作業用タブ2!$D$2:$F$29,3,FALSE)))) -> 天井無しの施工はDSDD換気システムをオプションで採用される場合のみ対応可能です。ご選択いただけるメーカーが限られますのでご注意ください。
A16: □ | B16: 14 | C16: =IF($D$1="HOURS",作業用タブ2!D47,作業用タブ2!D13) -> エコキュート タンク | D16: =IF($D$1="LIFE LIMITED(キャンペーン)",VLOOKUP(C16,作業用タブ2!$D$2:$F$29,2,FALSE),IF($D$1="HOURS",VLOOKUP(C16,作業用タブ2!$D$33:$F$61,2,FALSE),IF($D$1="LIFE+ LIMITED(キャンペーン)",VLOOKUP(C16,作業用タブ2!$D$2:$F$29,2,FALSE)))) -> 室外置き | F16: =IF($D$1="LIFE LIMITED(キャンペーン)",VLOOKUP(C16,作業用タブ2!$D$2:$F$29,3,FALSE),IF($D$1="HOURS",VLOOKUP(C16,作業用タブ2!$D$33:$F$61,3,FALSE),IF($D$1="LIFE+ LIMITED(キャンペーン)",VLOOKUP(C16,作業用タブ2!$D$2:$F$29,3,FALSE)))) -> 室内置きはオプションです。
A17: □ | B17: 15 | C17: =IF($D$1="HOURS",作業用タブ2!D48,作業用タブ2!D14) -> 点検口 | D17: =IF($D$1="LIFE LIMITED(キャンペーン)",VLOOKUP(C17,作業用タブ2!$D$2:$F$29,2,FALSE),IF($D$1="HOURS",VLOOKUP(C17,作業用タブ2!$D$33:$F$61,2,FALSE),IF($D$1="LIFE+ LIMITED(キャンペーン)",VLOOKUP(C17,作業用タブ2!$D$2:$F$29,2,FALSE)))) -> 換気システムや配管の定期点検および不具合が起きた場合に備えて1,2Fに必要な箇所に天井･床下点検口を3～4つ以上設置しています。 | F17: =IF($D$1="LIFE LIMITED(キャンペーン)",VLOOKUP(C17,作業用タブ2!$D$2:$F$29,3,FALSE),IF($D$1="HOURS",VLOOKUP(C17,作業用タブ2!$D$33:$F$61,3,FALSE),IF($D$1="LIFE+ LIMITED(キャンペーン)",VLOOKUP(C17,作業用タブ2!$D$2:$F$29,3,FALSE)))) -> 点検口の個数および位置については間取りプランにより変動します。
A18: □ | B18: 16 | C18: エコキュート タンク | D18: =IF($D$1="LIFE LIMITED(キャンペーン)",VLOOKUP(C18,作業用タブ2!$D$2:$F$29,2,FALSE),IF($D$1="HOURS",VLOOKUP(C18,作業用タブ2!$D$33:$F$61,2,FALSE),IF($D$1="LIFE+ LIMITED(キャンペーン)",VLOOKUP(C18,作業用タブ2!$D$2:$F$29,2,FALSE)))) -> 室外置き | F18: =IF($D$1="LIFE LIMITED(キャンペーン)",VLOOKUP(C18,作業用タブ2!$D$2:$F$29,3,FALSE),IF($D$1="HOURS",VLOOKUP(C18,作業用タブ2!$D$33:$F$61,3,FALSE),IF($D$1="LIFE+ LIMITED(キャンペーン)",VLOOKUP(C18,作業用タブ2!$D$2:$F$29,3,FALSE)))) -> 室内置きはオプションです。
A19: □ | B19: 17 | C19: =IF($D$1="HOURS",作業用タブ2!D50,作業用タブ2!D18) -> トラブル防止 | D19: =IF($D$1="LIFE LIMITED(キャンペーン)",VLOOKUP(C19,作業用タブ2!$D$2:$F$29,2,FALSE),IF($D$1="HOURS",VLOOKUP(C19,作業用タブ2!$D$33:$F$61,2,FALSE),IF($D$1="LIFE+ LIMITED(キャンペーン)",VLOOKUP(C19,作業用タブ2!$D$2:$F$29,2,FALSE)))) -> STYLE BOOKに掲載の商品は、告知無しで変更になる場合があります。 ※各メーカーの商品改定及び更新が定期的に行われるため、 契約締結時に交付されたSTYLE BOOKの記載価格・内容が適用されます。 | F19: =IF($D$1="LIFE LIMITED(キャンペーン)",VLOOKUP(C19,作業用タブ2!$D$2:$F$29,3,FALSE),IF($D$1="HOURS",VLOOKUP(C19,作業用タブ2!$D$33:$F$61,3,FALSE),IF($D$1="LIFE+ LIMITED(キャンペーン)",VLOOKUP(C19,作業用タブ2!$D$2:$F$29,3,FALSE)))) -> 打ち合わせ中に選定商品が廃番になることもありますのでご注意ください。 SNS等へのデータのUPはご遠慮ください。
A20: □ | B20: 18 | C20: =IF($D$1="HOURS",作業用タブ2!D51,作業用タブ2!D19) -> 太陽光パネル | D20: =IF($D$1="LIFE LIMITED(キャンペーン)",VLOOKUP(C20,作業用タブ2!$D$2:$F$29,2,FALSE),IF($D$1="HOURS",VLOOKUP(C20,作業用タブ2!$D$33:$F$61,2,FALSE),IF($D$1="LIFE+ LIMITED(キャンペーン)",VLOOKUP(C20,作業用タブ2!$D$2:$F$29,2,FALSE)))) -> 当社指定の太陽光パネルが6.53Kw付属いたします。 ※6.53Kwに搭載出来ない場合でも減額(＝マイナスオプション)は対応不可です。 | F20: =IF($D$1="LIFE LIMITED(キャンペーン)",VLOOKUP(C20,作業用タブ2!$D$2:$F$29,3,FALSE),IF($D$1="HOURS",VLOOKUP(C20,作業用タブ2!$D$33:$F$61,3,FALSE),IF($D$1="LIFE+ LIMITED(キャンペーン)",VLOOKUP(C20,作業用タブ2!$D$2:$F$29,3,FALSE))))
A21: □ | B21: 19 | C21: =IF($D$1="HOURS",作業用タブ2!D52,作業用タブ2!D20) -> 照明器具 | D21: =IF($D$1="LIFE LIMITED(キャンペーン)",VLOOKUP(C21,作業用タブ2!$D$2:$F$29,2,FALSE),IF($D$1="HOURS",VLOOKUP(C21,作業用タブ2!$D$33:$F$61,2,FALSE),IF($D$1="LIFE+ LIMITED(キャンペーン)",VLOOKUP(C21,作業用タブ2!$D$2:$F$29,2,FALSE)))) -> 照明器具が(税抜)30万円分付属いたします。 ※(税抜)30万円に到達しない場合でも減額(＝マイナスオプション)は対応不可です。 | F21: =IF($D$1="LIFE LIMITED(キャンペーン)",VLOOKUP(C21,作業用タブ2!$D$2:$F$29,3,FALSE),IF($D$1="HOURS",VLOOKUP(C21,作業用タブ2!$D$33:$F$61,3,FALSE),IF($D$1="LIFE+ LIMITED(キャンペーン)",VLOOKUP(C21,作業用タブ2!$D$2:$F$29,3,FALSE))))
A22: □ | B22: 20 | C22: =IF($D$1="HOURS",作業用タブ2!D53,作業用タブ2!D21) -> 家具・家電・ カーテン | D22: =IF($D$1="LIFE LIMITED(キャンペーン)",VLOOKUP(C22,作業用タブ2!$D$2:$F$29,2,FALSE),IF($D$1="HOURS",VLOOKUP(C22,作業用タブ2!$D$33:$F$61,2,FALSE),IF($D$1="LIFE+ LIMITED(キャンペーン)",VLOOKUP(C22,作業用タブ2!$D$2:$F$29,2,FALSE)))) -> 合計(税抜)100万円分プレゼントいたします。 ※100万円に到達しない場合でも減額(＝マイナスオプション)は対応不可です。 | F22: =IF($D$1="LIFE LIMITED(キャンペーン)",VLOOKUP(C22,作業用タブ2!$D$2:$F$29,3,FALSE),IF($D$1="HOURS",VLOOKUP(C22,作業用タブ2!$D$33:$F$61,3,FALSE),IF($D$1="LIFE+ LIMITED(キャンペーン)",VLOOKUP(C22,作業用タブ2!$D$2:$F$29,3,FALSE)))) -> 当社で外構工事をご依頼いただけることが条件です。
A23: □ | B23: 21 | C23: =IF($D$1="HOURS",作業用タブ2!D54,作業用タブ2!D22) -> オプション | D23: =IF($D$1="LIFE LIMITED(キャンペーン)",VLOOKUP(C23,作業用タブ2!$D$2:$F$29,2,FALSE),IF($D$1="HOURS",VLOOKUP(C23,作業用タブ2!$D$33:$F$61,2,FALSE),IF($D$1="LIFE+ LIMITED(キャンペーン)",VLOOKUP(C23,作業用タブ2!$D$2:$F$29,2,FALSE)))) -> 標準仕様の一部をやめることによる減額(＝マイナスオプション)は対応不可です。 | F23: =IF($D$1="LIFE LIMITED(キャンペーン)",VLOOKUP(C23,作業用タブ2!$D$2:$F$29,3,FALSE),IF($D$1="HOURS",VLOOKUP(C23,作業用タブ2!$D$33:$F$61,3,FALSE),IF($D$1="LIFE+ LIMITED(キャンペーン)",VLOOKUP(C23,作業用タブ2!$D$2:$F$29,3,FALSE))))
A24: □ | B24: 22 | C24: =IF($D$1="HOURS",作業用タブ2!D55,作業用タブ2!D23) -> 式典 | D24: =IF($D$1="LIFE LIMITED(キャンペーン)",VLOOKUP(C24,作業用タブ2!$D$2:$F$29,2,FALSE),IF($D$1="HOURS",VLOOKUP(C24,作業用タブ2!$D$33:$F$61,2,FALSE),IF($D$1="LIFE+ LIMITED(キャンペーン)",VLOOKUP(C24,作業用タブ2!$D$2:$F$29,2,FALSE)))) -> 地鎮祭および上棟式は省略しています。 | F24: =IF($D$1="LIFE LIMITED(キャンペーン)",VLOOKUP(C24,作業用タブ2!$D$2:$F$29,3,FALSE),IF($D$1="HOURS",VLOOKUP(C24,作業用タブ2!$D$33:$F$61,3,FALSE),IF($D$1="LIFE+ LIMITED(キャンペーン)",VLOOKUP(C24,作業用タブ2!$D$2:$F$29,3,FALSE)))) -> ご希望の方は鎮め物や上棟札を着工の2週間前までに担当者にお預けください。
A25: □ | B25: 23 | C25: =IF($D$1="HOURS",作業用タブ2!D56,作業用タブ2!D24) -> 施工会社 | D25: =IF($D$1="LIFE LIMITED(キャンペーン)",VLOOKUP(C25,作業用タブ2!$D$2:$F$29,2,FALSE),IF($D$1="HOURS",VLOOKUP(C25,作業用タブ2!$D$33:$F$61,2,FALSE),IF($D$1="LIFE+ LIMITED(キャンペーン)",VLOOKUP(C25,作業用タブ2!$D$2:$F$29,2,FALSE)))) -> 施工については協力会社に委託する場合があります(協力会社は当社指定の一定の施工技術の基準を超えた会社)。 | F25: =IF($D$1="LIFE LIMITED(キャンペーン)",VLOOKUP(C25,作業用タブ2!$D$2:$F$29,3,FALSE),IF($D$1="HOURS",VLOOKUP(C25,作業用タブ2!$D$33:$F$61,3,FALSE),IF($D$1="LIFE+ LIMITED(キャンペーン)",VLOOKUP(C25,作業用タブ2!$D$2:$F$29,3,FALSE))))
A26: □ | B26: 24 | C26: =IF($D$1="HOURS",作業用タブ2!D57,作業用タブ2!D25) -> 撮影協力 | D26: =IF($D$1="LIFE LIMITED(キャンペーン)",VLOOKUP(C26,作業用タブ2!$D$2:$F$29,2,FALSE),IF($D$1="HOURS",VLOOKUP(C26,作業用タブ2!$D$33:$F$61,2,FALSE),IF($D$1="LIFE+ LIMITED(キャンペーン)",VLOOKUP(C26,作業用タブ2!$D$2:$F$29,2,FALSE)))) -> 広告媒体（紙面・WEB・SNSなど）への利用を目的とした撮影依頼をする場合がございます。ご協力お願いいたします。 | F26: =IF($D$1="LIFE LIMITED(キャンペーン)",VLOOKUP(C26,作業用タブ2!$D$2:$F$29,3,FALSE),IF($D$1="HOURS",VLOOKUP(C26,作業用タブ2!$D$33:$F$61,3,FALSE),IF($D$1="LIFE+ LIMITED(キャンペーン)",VLOOKUP(C26,作業用タブ2!$D$2:$F$29,3,FALSE))))
A27: □ | B27: 25 | C27: =IF($D$1="HOURS",作業用タブ2!D58,作業用タブ2!D26) -> お引渡し | D27: =IF($D$1="LIFE LIMITED(キャンペーン)",VLOOKUP(C27,作業用タブ2!$D$2:$F$29,2,FALSE),IF($D$1="HOURS",VLOOKUP(C27,作業用タブ2!$D$33:$F$61,2,FALSE),IF($D$1="LIFE+ LIMITED(キャンペーン)",VLOOKUP(C27,作業用タブ2!$D$2:$F$29,2,FALSE)))) -> 建物の残代金の全額お支払いを確認後、鍵をお渡しします。 外構工事の完成に関わらず、お支払いをお願いいたします。 | F27: =IF($D$1="LIFE LIMITED(キャンペーン)",VLOOKUP(C27,作業用タブ2!$D$2:$F$29,3,FALSE),IF($D$1="HOURS",VLOOKUP(C27,作業用タブ2!$D$33:$F$61,3,FALSE),IF($D$1="LIFE+ LIMITED(キャンペーン)",VLOOKUP(C27,作業用タブ2!$D$2:$F$29,3,FALSE)))) -> 外構工事をGハウス外構事業部GRAN GARDENにてご契約の方は、引渡し前に着工する場合がございます。GRAN GARDEN以外の業者様による外構工事については、責任の所在が不明確となる可能性があるため、建物のお引渡し後の着工とさせていただきます。
A28: □ | B28: 26 | C28: =IF($D$1="HOURS",作業用タブ2!D59,作業用タブ2!D27) -> お引越し | D28: =IF($D$1="LIFE LIMITED(キャンペーン)",VLOOKUP(C28,作業用タブ2!$D$2:$F$29,2,FALSE),IF($D$1="HOURS",VLOOKUP(C28,作業用タブ2!$D$33:$F$61,2,FALSE),IF($D$1="LIFE+ LIMITED(キャンペーン)",VLOOKUP(C28,作業用タブ2!$D$2:$F$29,2,FALSE)))) -> お引越しにあたり、階段手摺の取り外しおよび設置が必要となる場合は別途25,000円(税別)発生します。 | F28: =IF($D$1="LIFE LIMITED(キャンペーン)",VLOOKUP(C28,作業用タブ2!$D$2:$F$29,3,FALSE),IF($D$1="HOURS",VLOOKUP(C28,作業用タブ2!$D$33:$F$61,3,FALSE),IF($D$1="LIFE+ LIMITED(キャンペーン)",VLOOKUP(C28,作業用タブ2!$D$2:$F$29,3,FALSE)))) -> お引越しに伴い必要となる工事は別途費用が発生します。
A29: □ | B29: 27 | C29: =IF($D$1="HOURS",作業用タブ2!D60,作業用タブ2!D28) -> 補助金 | D29: =IF($D$1="LIFE LIMITED(キャンペーン)",VLOOKUP(C29,作業用タブ2!$D$2:$F$29,2,FALSE),IF($D$1="HOURS",VLOOKUP(C29,作業用タブ2!$D$33:$F$61,2,FALSE),IF($D$1="LIFE+ LIMITED(キャンペーン)",VLOOKUP(C29,作業用タブ2!$D$2:$F$29,2,FALSE)))) -> 補助金の手続きはお施主様自身でお願いします。 | F29: =IF($D$1="LIFE LIMITED(キャンペーン)",VLOOKUP(C29,作業用タブ2!$D$2:$F$29,3,FALSE),IF($D$1="HOURS",VLOOKUP(C29,作業用タブ2!$D$33:$F$61,3,FALSE),IF($D$1="LIFE+ LIMITED(キャンペーン)",VLOOKUP(C29,作業用タブ2!$D$2:$F$29,3,FALSE)))) -> ※当社で代理申請する場合は別途費用が発生します。 ZEH補助金はGハウスの行程では対応不可です。
A30: □ | B30: 28 | C30: =IF($D$1="HOURS",作業用タブ2!D61,作業用タブ2!D29) -> LINE・メール | D30: =IF($D$1="LIFE LIMITED(キャンペーン)",VLOOKUP(C30,作業用タブ2!$D$2:$F$29,2,FALSE),IF($D$1="HOURS",VLOOKUP(C30,作業用タブ2!$D$33:$F$61,2,FALSE),IF($D$1="LIFE+ LIMITED(キャンペーン)",VLOOKUP(C30,作業用タブ2!$D$2:$F$29,2,FALSE)))) -> 間違い防止のため、設計･コーディネーター担当へのご要望･ご質問等、ご相談内容をLINEやメールにてお伝えいただくことをお断りしております。打ち合わせの際にまとめて担当者にご相談いただくようにご協力お願いします。 | F30: =IF($D$1="LIFE LIMITED(キャンペーン)",VLOOKUP(C30,作業用タブ2!$D$2:$F$29,3,FALSE),IF($D$1="HOURS",VLOOKUP(C30,作業用タブ2!$D$33:$F$61,3,FALSE),IF($D$1="LIFE+ LIMITED(キャンペーン)",VLOOKUP(C30,作業用タブ2!$D$2:$F$29,3,FALSE))))
E32: 住所 | F32: =初期入力!B5 -> 0
E34: 氏名 | F34: =初期入力!B4 -> 0 | G34: 印
E36: 住所 | F36: =IF(初期入力!B7="","",初期入力!B7)
E38: 氏名 | F38: =IF(初期入力!B6="","",初期入力!B6) | G38: 印

Sheet 作業用タブ2
A1: LIFE LIMITED | I1: 【商品を選択】
D2: 項目 | E2: 標準内容 | F2: 備考
B3: □ | C3: 1 | D3: キャンペーン 適応 | E3: 設備グレードUP（坪単価税別55万円）キャンペーンが対象です。 | F3: 解体工事(古家付き土地の場合)･外構工事･登記手続きを当社にご依頼をいただける方が条件です。 | I3: HOURS
B4: □ | C4: 2 | D4: キャンペーン 適応 | E4: エアコン2台(1､2階建)･3台(3階建)をオプション工事にて設置いただける方が条件です。
B5: □ | C5: 3 | D5: キャンペーン 適応 | E5: 上棟後現場見学･完成後現場立会い･カギお渡し日を平日に行っていただける方が条件です。
B6: □ | C6: 4 | D6: キャンペーン 適応 | E6: 当社の工期に合わせて打ち合わせをしていただける方が条件です。 打ち合わせ回数：最大5回(5回目が全仕様確認日) 打ち合わせ期間：初回ヒアリング打ち合わせから間取り確定まで25日 間取り確定から最終打ち合わせまで50日 合計打ち合わせ期間は75日です。 | F6: 打ち合わせ回数5回以下で下記の特典があります。 5回：★★20万円相当 ※初回ヒアリングは除く ※WEBキャンペーンとの併用は出来ません。
B7: □ | C7: 5 | D7: 間取り | E7: 完全自由設計 ※4マス×910mm間隔に柱または壁の設置が必要です。 | F7: 申請業務に進んでいくため、基本設計確定後の変更は出来ません。
B8: □ | C8: 6 | D8: 坪単価 | E8: 30坪未満の場合割増計算となり、1坪下がる度に15,000円×坪数＝追加費用が発生します。 3階建ての場合は坪単価＋40,000円UP 下屋の場合は下屋部分㎡×30,000円UP | F8: 例）28坪の場合、30坪に対して2坪下がる 30,000円×28坪＝840,000円UP
B9: □ | C9: 7 | D9: 住宅ローン | E9: 住宅ローンの手続きはお施主様自身でお願いします。 当社でしかご用意ができない書類や図面等はお渡しします。 | F9: ※事前審査も同様
B10: □ | C10: 8 | D10: 仕様 | E10: セミオーダー制 当社の設計士がこだわり抜いた【 STYLE BOOK 】からのみ選択できます。
B11: □ | C11: 9 | D11: 長期優良住宅 | E11: 認定基準として、少なくとも1の階の床面積が階段部分を除いて40㎡以上必要です。 また、都市計画法第53条許可の対象となる地域では認定対象外です。 | F11: 詳細は設計打ち合わせにてご確認ください。
B12: □ | C12: 10 | D12: Ua値 | E12: 0.46W/㎡･Kを目安としております。但し、間取りや窓の個数・種類によって数値が変わり、0.46W/㎡･Kを確保できない場合があります。
B13: □ | C13: 11 | D13: 窓 | E13: 施工面積が35坪未満10ヵ所、35～40坪11ヵ所、40～45坪12ヵ所、45～50坪13ヵ所、50坪以上14ヵ所までが標準個数です。 ※既製品のみ選定可能とし特注品の選択不可。 | F13: 掃き出し窓H2200は2ヵ所まで （手動シャッター2ヵ所まで）
B14: □ | C14: 12 | D14: 建具 | E14: 開き扉H2400㎜標準(各居室・トイレ・脱衣室・ランドリーそれぞれ1ヵ所ずつ) ※片引き戸2ヵ所まで標準 | F14: 引き戸3枚目以上及び収納扉等、リビング・書斎・洗面室・ファミリーCL・その他の部屋はオプションです。
B15: □ | C15: 13 | D15: 床材 | E15: 無垢床材を使用した場合、伸縮、床鳴り、及び経年劣化による変色が発生 する場合があります。
B16: □ | C16: 14 | D16: 換気システム | E16: 換気システムは全熱交換型第一種換気システム(Panasonic)が標準です。 | F16: DSDD換気システム(okatomi)はオプションとなり、請負契約までに確定が必要です。請負契約後は変更できません。
B17: □ | C17: 12 | D17: ユニットバス | E17: 天井有り | F17: 天井無しの施工はDSDD換気システムをオプションで採用される場合のみ対応可能です。ご選択いただけるメーカーが限られますのでご注意ください。
B18: □ | C18: 15 | D18: エコキュート タンク | E18: 室外置き | F18: 室内置きはオプションです。
B19: □ | C19: 16 | D19: 点検口 | E19: 換気システムや配管の定期点検および不具合が起きた場合に備えて1Fに必要な箇所に天井･床下点検口を3～4つ以上設置しています。 | F19: 点検口の個数および位置については間取りプランにより変動します。
B20: □ | C20: 17 | D20: 大工工事 | E20: 造作工事はSTYLE BOOKに記載の内容のみ対応しています。 | F20: 記載無き内容については提携リフォーム会社様へご相談ください。
B21: □ | C21: 18 | D21: トラブル防止 | E21: 本キャンペーン内容に関して、SNS･YouTube･ブログ等あらゆるウェブメディアへの投稿、または知人への情報共有を固く禁じます。 STYLE BOOKに掲載の商品は、告知無しで変更になる場合があります。 ※各メーカーの商品改定及び更新が定期的に行われるため、契約締結時に交付されたSTYLE BOOKの記載価格・内容が適用されます。 | F21: 打ち合わせ中に選定商品が廃番になることもありますのでご注意ください。 SNS等へのデータのUPはご遠慮ください。
B22: □ | C22: 19 | D22: オプション | E22: 標準仕様の一部をやめることによる減額（＝マイナスオプション）は対応不可です。
B23: □ | C23: 20 | D23: 式典 | E23: 地鎮祭および上棟式は省略しています。 | F23: ご希望の方は鎮め物や上棟札を着工の2週間前までに担当者にお預けください。
B24: □ | C24: 21 | D24: 施工会社 | E24: 施工については協力会社に委託する場合があります（協力会社は当社指定の一定の施工技術の基準を超えた会社）。
B25: □ | C25: 22 | D25: 撮影協力 | E25: 広告媒体（紙面・WEB・SNSなど）への利用を目的とした撮影依頼をする場合がございます。ご協力お願いいたします。
B26: □ | C26: 23 | D26: お引渡し | E26: 建物の残代金の全額お支払いを確認後、鍵をお渡しします。 外構工事の完成に関わらず、お支払いをお願いいたします。 | F26: 外構工事をGハウス外構事業部GRAN GARDENにてご契約の方は、引渡し前に着工する場合がございます。GRAN GARDEN以外の業者様による外構工事については、責任の所在が不明確となる可能性があるため、建物のお引渡し後の着工とさせていただきます。
B27: □ | C27: 24 | D27: お引越し | E27: お引越しにあたり、階段手摺の取り外しおよび設置が必要となる場合は別途25,000円(税別)発生します。 | F27: お引越しに伴い必要となる工事は別途費用が発生します。
B28: □ | C28: 25 | D28: 補助金 | E28: 補助金の手続きはお施主様自身でお願いします。 | F28: ※当社で代理申請する場合は別途費用が発生します。 ZEH補助金はGハウスの行程では対応不可です。
B29: □ | C29: 26 | D29: LINE メール | E29: 間違い防止のため、設計･コーディネーター担当へのご要望･ご質問等、ご相談内容をLINEやメールにてお伝えいただくことをお断りしております。打ち合わせの際にまとめて担当者にご相談いただくようにご協力お願いします。
A32: HOURS
D33: 項目 | E33: 標準内容 | F33: 備考
B34: □ | C34: 1 | D34: 間取り | E34: 完全自由設計 ※4マス×910mm間隔に柱または壁の設置が必要です。 | F34: 申請業務に進んでいくため、基本設計確定後の変更は出来ません。
B35: □ | C35: 2 | D35: 坪単価 | E35: 本体工事価格は63万円(税別) 30坪未満の場合割増計算となり、1坪下がる度に15,000円×坪数＝追加費用が発生します。 3階建ての場合は坪単価＋40,000円UP 下屋の場合は下屋部分㎡×30,000円UP | F35: 例)28坪の場合、30坪に対して2坪下がる 30,000円×28坪＝840,000円UP
B36: □ | C36: 3 | D36: 施工面積 | E36: 建物価格は「施工面積 × 坪単価」にて算出します。 施工面積は、延床面積に加え、外壁に三方を囲まれたビルトインガレージ、半ビルトインガレージを含み、当社基準により算出します。 また、以下の工事は、施工面積に含まれていない場合でも、別途費用が加算されます。 ① 軒の出・オーバーハング工事 ：42,000円／㎡（税別） ② 下屋工事 ：30,000円／㎡（税別） ③ バルコニー工事・吹抜工事 ：60,000円／㎡（税別） ※対象となる面積は、設計図書に基づき当社が算出します。 | F36: 左記内容の対象となる面積については別紙1の参考写真をご確認下さい。
B37: □ | C37: 3 | D37: 住宅ローン | E37: 住宅ローンの手続きはお施主様自身でお願いします。 当社でしかご用意ができない書類や図面等はお渡しします。 | F37: ※事前審査も同様
B38: □ | C38: 4 | D38: 打ち合わせ 期間 | E38: 最大3ヵ月間 (回数：6回) | F38: 打ち合わせ回数6回以下で下記の特典があります。 6回：★10万円相当 5回：★★20万円相当 ※初回ヒアリングは除く
B39: □ | C39: 5 | D39: 仕様 | E39: セミオーダー制 当社の設計士がこだわり抜いた【 STYLE BOOK 】からのみ選択できます。
B40: □ | C40: 6 | D40: 長期優良住宅 | E40: 認定基準として、少なくとも1の階の床面積(階段部分を除く)が40㎡以上かつ床面積の合計75㎡必要です。 また、都市計画法第53条許可の対象となる地域では認定対象外です。 | F40: 詳細は設計打ち合わせにてご確認ください。
B41: □ | C41: 7 | D41: Ua値 | E41: 0.46W/㎡･Kを目安としております。但し、間取りや窓の個数･種類によって数値が変わり、0.46W/㎡･Kを確保できない場合があります。
B42: □ | C42: 8 | D42: 窓 | E42: 施工面積が35坪未満12ヵ所、35～40坪13ヵ所、40～45坪14ヵ所、45～50坪15ヵ所、50坪以上16ヵ所までが標準個数です。 ※既製品のみ選定可能とし特注品の選択不可。 | F42: 掃き出し窓(手動シャッター付)H2200は2ヵ所まで
B43: □ | C43: 9 | D43: 建具 | E43: 開き扉H2400㎜標準(各居室・トイレ・脱衣室・ランドリーそれぞれ1ヵ所ずつ) ※片引き戸2ヵ所まで標準 | F43: 引き戸3枚目以上及び収納扉等、リビング・書斎・洗面室・ファミリーCL・その他の部屋はオプションです。
B44: □ | C44: 10 | D44: 床材 | E44: 無垢床材を使用した場合、伸縮、床鳴り、及び経年劣化による変色が発生 する場合があります。
B45: □ | C45: 11 | D45: 換気システム | E45: 換気システムは全熱交換型第一種換気システム(Panasonic)が標準です。 | F45: DSDD換気システム(okatomi)はオプションとなり、請負契約までに確定が必要です。請負契約後は変更できません。
B46: □ | C46: 12 | D46: ユニットバス | E46: 天井有り | F46: 天井無しの施工はDSDD換気システムをオプションで採用される場合のみ対応可能です。ご選択いただけるメーカーが限られますのでご注意ください。
B47: □ | C47: 13 | D47: エコキュート タンク | E47: 室外置き | F47: 室内置きはオプションです。
B48: □ | C48: 14 | D48: 点検口 | E48: 換気システムや配管の定期点検および不具合が起きた場合に備えて1,2Fに必要な箇所に天井･床下点検口を3～4つ以上設置しています。 | F48: 点検口の個数および位置については間取りプランにより変動します。
B49: □ | C49: 15 | D49: 大工工事 | E49: 造作工事は【STYLE BOOK】に記載の内容のみ対応しています。 | F49: カタログに記載無き内容については提携リフォーム会社様へご相談ください。
B50: □ | C50: 16 | D50: トラブル防止 | E50: STYLE BOOKに掲載の商品は、告知無しで変更になる場合があります。 ※各メーカーの商品改定及び更新が定期的に行われるため、 契約締結時に交付されたSTYLE BOOKの記載価格・内容が適用されます。 | F50: 打ち合わせ中に選定商品が廃番になることもありますのでご注意ください。 SNS等へのデータのUPはご遠慮ください。
B51: □ | C51: 17 | D51: 太陽光パネル | E51: 当社指定の太陽光パネルが6.53Kw付属いたします。 ※6.53Kwに搭載出来ない場合でも減額(＝マイナスオプション)は対応不可です。
B52: □ | C52: 18 | D52: 照明器具 | E52: 照明器具が(税抜)30万円分付属いたします。 ※(税抜)30万円に到達しない場合でも減額(＝マイナスオプション)は対応不可です。
B53: □ | C53: 19 | D53: 家具・家電・ カーテン | E53: 合計(税抜)100万円分プレゼントいたします。 ※100万円に到達しない場合でも減額(＝マイナスオプション)は対応不可です。 | F53: 当社で外構工事をご依頼いただけることが条件です。
B54: □ | C54: 20 | D54: オプション | E54: 標準仕様の一部をやめることによる減額(＝マイナスオプション)は対応不可です。
B55: □ | C55: 21 | D55: 式典 | E55: 地鎮祭および上棟式は省略しています。 | F55: ご希望の方は鎮め物や上棟札を着工の2週間前までに担当者にお預けください。
B56: □ | C56: 22 | D56: 施工会社 | E56: 施工については協力会社に委託する場合があります(協力会社は当社指定の一定の施工技術の基準を超えた会社)。
B57: □ | C57: 23 | D57: 撮影協力 | E57: 広告媒体（紙面・WEB・SNSなど）への利用を目的とした撮影依頼をする場合がございます。ご協力お願いいたします。
B58: □ | C58: 24 | D58: お引渡し | E58: 建物の残代金の全額お支払いを確認後、鍵をお渡しします。 外構工事の完成に関わらず、お支払いをお願いいたします。 | F58: 外構工事をGハウス外構事業部GRAN GARDENにてご契約の方は、引渡し前に着工する場合がございます。GRAN GARDEN以外の業者様による外構工事については、責任の所在が不明確となる可能性があるため、建物のお引渡し後の着工とさせていただきます。
B59: □ | C59: 25 | D59: お引越し | E59: お引越しにあたり、階段手摺の取り外しおよび設置が必要となる場合は別途25,000円(税別)発生します。 | F59: お引越しに伴い必要となる工事は別途費用が発生します。
B60: □ | C60: 26 | D60: 補助金 | E60: 補助金の手続きはお施主様自身でお願いします。 | F60: ※当社で代理申請する場合は別途費用が発生します。 ZEH補助金はGハウスの行程では対応不可です。
B61: □ | C61: 27 | D61: LINE・メール | E61: 間違い防止のため、設計･コーディネーター担当へのご要望･ご質問等、ご相談内容をLINEやメールにてお伝えいただくことをお断りしております。打ち合わせの際にまとめて担当者にご相談いただくようにご協力お願いします。

Sheet LIFE LIMITED キャンペーン
C1: LIFE LIMITEDキャンペーン内容適用の覚書
A4: 発注者： | B4: =初期入力!B4 -> 0 | E4: =IF(初期入力!B6="","",初期入力!B6) | H4: (以下「甲」という。)と受注者：株式会社Ｇハウス
A5: (以下「乙」という。)において締結した | G5: =初期入力!C13 -> 2025 | H5: 年 | I5: =初期入力!E13 -> 7 | J5: 月 | K5: =初期入力!G13 -> 25 | L5: 日付工事請負契約書
A6: (以下｢原契約書｣という)に関し、甲と乙は、甲が下記のすべての要件を厳守することを条件に
A7: LIFE LIMITEDキャンペーンを適用することについて、合意する。
A8: 甲は、甲が本覚書記載の要件を厳守しない場合、本キャンペーンは無効となり原契約書の仕様
A9: もしくは契約金額またはその両方が変更される可能性があることについて乙から説明をうけ、
A10: そのことを理解したうえで、本覚書を締結する。
A11: なお、本合意書に定める事項以外については、原契約書の定めを適用するものとする。
A12: この契約の証として、本書の電磁的記録を作成し、甲および乙が合意の後電子署名を施し各自
A13: 電磁的記録を保管する。
H15: 記
A17: 1 | B17: エアコン2台(1､2階建)･3台(3階建)をオプション工事にて設置いただける方。
A18: 2 | B18: 解体工事(古家付き土地の場合)･外構工事･火災保険･登記手続きを当社にご依頼を
B19: いただける方。
A20: 3 | B20: 当社の工期に合わせて打ち合わせをしていただける方。
B21: ●打ち合わせ回数：最大5回 (5回目が全仕様確認日です。)
B22: ●打ち合わせ期間：初回ヒアリング打ち合わせから間取り確定まで25日、
B23: 間取り確定から最終打ち合わせまで50日。合計打ち合わせ期間は75日です。
B24: ※1回の打ち合わせ時間は最大3時間です。
B25: ※初回ヒアリング打ち合わせはご契約の1週間後です。
A26: 4 | B26: 上棟後現場見学･完成後現場立会い･カギお渡し日を平日に行っていただける方。
A27: 5 | B27: 完成後、1ヵ月間の見学会･YouTube撮影・スチール撮影にご協力いただける方。
A28: 6 | B28: WEB打ち合わせキャンペーンとの併用は出来ません。
B29: ※ただし、平日打ち合わせは併用可能です。
A30: 7 | B30: 本キャンペーンの存在及び内容に関して、対話、電話、電子メール、SNS・YouTube・
B31: ブログその他方法の如何を問わず、第三者に対し一切口外しない方。
N34: 以上
B35: =初期入力!C13 -> 2025 | C35: 年 | D35: =初期入力!E13 -> 7 | E35: 月 | F35: =初期入力!G13 -> 25 | G35: 日
C37: 甲(発注者)住所 | F37: =IF(初期入力!B5="","",初期入力!B5)
D39: 氏名 | F39: =IF(初期入力!B4="","",初期入力!B4) | M39: 印
C41: 甲(発注者)住所 | F41: =IF(初期入力!B7="","",初期入力!B7)
D43: 氏名 | F43: =IF(初期入力!B6="","",初期入力!B6) | M43: 印
C45: 乙(受注者)住所 | F45: 大阪府大阪市旭区新森2-23-12
D47: 氏名 | F47: 株式会社Gハウス | M47: 印

Sheet LIFE・LIFE+キャンペーン
C1: LIFE・LIFE+キャンペーン内容適用の覚書
A4: 発注者： | B4: =初期入力!B4 -> 0 | E4: =IF(初期入力!B6="","",初期入力!B6) | H4: (以下「甲」という。)と受注者：株式会社Ｇハウス
A5: (以下「乙」という。)において締結した | G5: =初期入力!C13 -> 2025 | H5: 年 | I5: =初期入力!E13 -> 7 | J5: 月 | K5: =初期入力!G13 -> 25 | L5: 日付工事請負契約書
A6: (以下｢原契約書｣という)に関し、甲と乙は、甲が下記のすべての要件を厳守することを条件に
A7: LIFE・LIFE+キャンペーンを適用することについて、合意する。
A8: 甲は、甲が本覚書記載の要件を厳守しない場合、本キャンペーンは無効となり原契約書の仕様
A9: もしくは契約金額またはその両方が変更される可能性があることについて乙から説明をうけ、
A10: そのことを理解したうえで、本覚書を締結する。
A11: なお、本合意書に定める事項以外については、原契約書の定めを適用するものとする。
A12: この契約の証として、本書の電磁的記録を作成し、甲および乙が合意の後電子署名を施し各自
A13: 電磁的記録を保管する。
H16: 記
A18: 1 | B18: 当社の工期に合わせて打ち合わせをしていただける方。
B19: ●打ち合わせ回数：最大5回 (5回目が全仕様確認日です。)
B20: ●打ち合わせ期間：初回ヒアリング打ち合わせから間取り確定まで25日、
B21: 間取り確定から最終打ち合わせまで50日。合計打ち合わせ期間は75日です。
B22: ※1回の打ち合わせ時間は最大3時間です。
B23: ※初回ヒアリング打ち合わせはご契約の1週間後です。
A26: 2 | B26: 本キャンペーンの存在及び内容に関して、対話、電話、電子メール、SNS・YouTube・
B27: ブログその他方法の如何を問わず、第三者に対し一切口外しない方。
N29: 以上
B32: =初期入力!C13 -> 2025 | C32: 年 | D32: =初期入力!E13 -> 7 | E32: 月 | F32: =初期入力!G13 -> 25 | G32: 日
C34: 甲(発注者)住所 | F34: =IF(初期入力!B5="","",初期入力!B5)
D36: 氏名 | F36: =IF(初期入力!B4="","",初期入力!B4) | M36: 印
C38: 甲(発注者)住所 | F38: =IF(初期入力!B7="","",初期入力!B7)
D40: 氏名 | F40: =IF(初期入力!B6="","",初期入力!B6) | M40: 印
C42: 乙(受注者)住所 | F42: 大阪府大阪市旭区新森2-23-12
D44: 氏名 | F44: 株式会社Gハウス | M44: 印

Sheet LIFE+ LIMITED キャンペーン 
B1: LIFE+ LIMITEDキャンペーン内容適用の覚書
A3: 発注者： | B3: =IF(初期入力!B4="","",初期入力!B4) | E3: =IF(初期入力!B6="","",初期入力!B6) | H3: (以下「甲」という。)と受注者：株式会社Ｇハウス
A4: (以下「乙」という。)は、 | E4: =初期入力!C13 -> 2025 | F4: 年 | G4: =初期入力!E13 -> 7 | H4: 月 | I4: =初期入力!G13 -> 25 | J4: 日付工事請負契約書(以下｢原契約書｣
A5: という。)に基づき、甲が下記のすべての要件を厳守する場合に「LIFE+ LIMITEDキャンペーン」を
A6: 適用することについて合意する。
A7: 甲は、本覚書記載の要件を厳守しない場合、本キャンペーンが無効となること、または原契約書の
A8: 仕様および契約金額のいずれか、または両方が変更される可能性があることについて乙から説明を
A9: 受け、これを理解したうえで本覚書を締結する。
A10: 本合意書に定める事項以外については、原契約書の定めを適用するものとする。
A11: この契約の証として、本書の電磁的記録を作成し、甲および乙が合意の後電子署名を施し、各自
A12: 電磁的記録を保管する。
H14: 記
A16: 【キャンペーンLIFE+坪単価税別55万円適用要項】（坪単価は一律）
A17: 1 | B17: 乙の外構事業部「GRAN GARDEN」にて、先行工事から外構工事まで一括で依頼すること。
B18: 乙にて登記手続き、古家付き土地の場合は解体工事を依頼すること。
B19: ※他社にて分離発注することは不可とする。
A20: 2 | B20: 乙の工期に合わせて打ち合わせを行うこと。乙の定休日における打ち合わせは不可とする。
B21: ●打ち合わせ回数は最大5回とし、5回目を全仕様確認日とする。
B22: ●打ち合わせ期間は、初回ヒアリング打ち合わせから間取り確定まで25日、間取り確定から
B23: 最終打ち合わせまで50日、合計で75日とする。
B24: ※1回の打ち合わせ時間は最大3時間とする。
B25: ※初回ヒアリング打ち合わせは契約後1週間以内に実施する。
A26: 3 | B26: 上棟後の現場見学、完成後の現場立会い、カギのお渡し日を平日に行うこと。
A27: 4 | B27: 完成後、1ヵ月間の見学会、YouTube撮影およびスチール撮影に協力すること。
A28: 5 | B28: WEB打ち合わせキャンペーン・平日打ち合わせキャンペーンとの併用は不可とする。
A29: 6 | B29: 本キャンペーンの存在および内容について、対話、電話、電子メール、SNS、YouTube、
B30: ブログなどいかなる方法においても第三者に一切口外しないことを義務とする。
O31: 以上
B32: =初期入力!C13 -> 2025 | C32: 年 | D32: =初期入力!E13 -> 7 | E32: 月 | F32: =初期入力!G13 -> 25 | G32: 日
C34: 甲(発注者)住所 | F34: =IF(初期入力!B5="","",初期入力!B5)
D36: 氏名 | F36: =IF(初期入力!B4="","",初期入力!B4) | M36: 印
C38: 甲(発注者)住所 | F38: =IF(初期入力!B7="","",初期入力!B7)
D40: 氏名 | F40: =IF(初期入力!B6="","",初期入力!B6) | M40: 印
C42: 乙(受注者)住所 | F42: 大阪府大阪市旭区新森2-23-12
D44: 氏名 | F44: 株式会社Gハウス | M44: 印

Sheet LIFE LIMITED キャンペーン 
B1: LIFE LIMITEDキャンペーン内容適用の覚書
A3: 発注者： | B3: =IF(初期入力!B4="","",初期入力!B4) | E3: =IF(初期入力!B6="","",初期入力!B6) | H3: (以下「甲」という。)と受注者：株式会社Ｇハウス
A4: (以下「乙」という。)は、 | E4: =初期入力!C13 -> 2025 | F4: 年 | G4: =初期入力!E13 -> 7 | H4: 月 | I4: =初期入力!G13 -> 25 | J4: 日付工事請負契約書(以下｢原契約書｣
A5: という。)に基づき、甲が下記のすべての要件を厳守する場合に「LIFE LIMITEDキャンペーン」を
A6: 適用することについて合意する。
A7: 甲は、本覚書記載の要件を厳守しない場合、本キャンペーンが無効となること、または原契約書の
A8: 仕様および契約金額のいずれか、または両方が変更される可能性があることについて乙から説明を
A9: 受け、これを理解したうえで本覚書を締結する。
A10: 本合意書に定める事項以外については、原契約書の定めを適用するものとする。
A11: この契約の証として、本書の電磁的記録を作成し、甲および乙が合意の後電子署名を施し、各自
A12: 電磁的記録を保管する。
H14: 記
A16: 【キャンペーンLIFE坪単価税別50万円適用要項】（坪単価は一律）
A17: 1 | B17: 乙の外構事業部「GRAN GARDEN」にて、先行工事から外構工事まで一括で依頼すること。
B18: 乙にて登記手続き、古家付き土地の場合は解体工事を依頼すること。
B19: ※他社にて分離発注することは不可とする。
A20: 2 | B20: 乙の工期に合わせて打ち合わせを行うこと。乙の定休日における打ち合わせは不可とする。
B21: ●打ち合わせ回数は最大5回とし、5回目を全仕様確認日とする。
B22: ●打ち合わせ期間は、初回ヒアリング打ち合わせから間取り確定まで25日、間取り確定から
B23: 最終打ち合わせまで50日、合計で75日とする。
B24: ※1回の打ち合わせ時間は最大3時間とする。
B25: ※初回ヒアリング打ち合わせは契約後1週間以内に実施する。
A26: 3 | B26: 上棟後の現場見学、完成後の現場立会い、カギのお渡し日を平日に行うこと。
A27: 4 | B27: 完成後、1ヵ月間の見学会、YouTube撮影およびスチール撮影に協力すること。
A28: 5 | B28: WEB打ち合わせキャンペーン・平日打ち合わせキャンペーンとの併用は不可とする。
A29: 6 | B29: 本キャンペーンの存在および内容について、対話、電話、電子メール、SNS、YouTube、
B30: ブログなどいかなる方法においても第三者に一切口外しないことを義務とする。
O31: 以上
B32: =初期入力!C13 -> 2025 | C32: 年 | D32: =初期入力!E13 -> 7 | E32: 月 | F32: =初期入力!G13 -> 25 | G32: 日
C34: 甲(発注者)住所 | F34: =IF(初期入力!B5="","",初期入力!B5)
D36: 氏名 | F36: =IF(初期入力!B4="","",初期入力!B4) | M36: 印
C38: 甲(発注者)住所 | F38: =IF(初期入力!B5="","",初期入力!B5)
D40: 氏名 | F40: =IF(初期入力!B6="","",初期入力!B6) | M40: 印
C42: 乙(受注者)住所 | F42: 大阪府大阪市旭区新森2-23-12
D44: 氏名 | F44: 株式会社Gハウス | M44: 印

Sheet 紹介料支払承諾書
D1: 紹介料支払承諾書
A3: =初期入力!B4 -> 0 | D3: =IF(初期入力!B6="","",初期入力!B6) | G3: (以下「甲」という。)と株式会社Ｇハウス（以下「乙」と
A4: いう。）とは、甲が乙に対して紹介したお客様（以下「丙」という）が、乙にて建築工事請負契約を締結し、
A5: 当該契約に基づく基礎着工が完了した際、乙が甲に対して紹介料を支払うことを以下のとおり定める。
A7: 第１条（紹介料の支払い）
A8: 乙は、甲が紹介した丙が乙にて建築工事請負契約を締結し,当該契約に基づく基礎着工が完了した際、次条に
A9: 基づき、甲に紹介料を支払う。
A11: 第２条（紹介料支払金額及び支払い方法） | O11: ２．支払時期は、本承諾書締結後の翌月末までとします。
A12: １．支払金額は、1人目の契約時は10万円、2人目は20万円、3人目以降は30万円とする。 | O12: 紹介料について
A13: ２．支払時期は、丙の基礎着工月の翌月末までとする。
A14: ３．支払方法は、甲が指定する以下の金融機関口座へ振込にて支払うものとする。
A16: 金融機関名： | H16: 支店・出張所：
A17: 口座番号： | H17: 預金種別：
A18: 口座名義： | H18: フリガナ：
A20: 第３条（契約の成立）
A21: 本契約は、電子契約によって締結するものとし、契約の成立を証するため、本書の電磁的記録を | O21: 上記承諾書締結の証として本書2通を作成し、甲乙各1通を保有するものとする。
A22: 作成し、甲および乙が合意の後電子署名を行い、各自で電磁的記録を保管するものとする。 | O22: 上記承諾書締結の証として本書正本１通を作成し、各自記名押印の上、甲が原本、乙が写し
O23: をそれぞれ保有する。
A24: =初期入力!C13 -> 2025 | C24: 年 | D24: =初期入力!E13 -> 7 | E24: 月 | F24: =初期入力!G13 -> 25 | G24: 日
B26: 甲住所： | D26: =IF(初期入力!B5="","",初期入力!B5)
B28: 甲氏名： | D28: =初期入力!B4 -> 0 | M28: 印
B30: 甲住所： | D30: =IF(初期入力!B7="","",初期入力!B7)
B32: 甲氏名： | D32: =IF(初期入力!B6="","",初期入力!B6) | M32: 印
B34: 乙住所： | D34: 大阪府大阪市旭区新森2-23-12
B36: 乙氏名： | D36: 株式会社Gハウス 代表取締役 趙晃啓 | M36: 印

Sheet 作業用タブ3
A1: LIFE LIMITED | I1: 【商品を選択】
D2: 項目 | E2: 標準内容 | F2: 備考 | I2: LIFE+ LIMITED(キャンペーン)
B3: □ | C3: 1 | D3: キャンペーン 適応 | E3: 年度末決算キャンペーン（坪単価税別50万円）が対象です。 | F3: 解体工事(古家付き土地の場合)･外構工事･火災保険･登記手続きを当社にご依頼をいただける方が条件です。
B4: □ | C4: 2 | D4: キャンペーン 適応 | E4: 上棟後現場見学･完成後現場立会い･カギお渡し日を平日に行っていただける方が条件です。
B5: □ | C5: 3 | D5: キャンペーン 適応 | E5: 当社の工期に合わせて打ち合わせをしていただける方が条件です。 打ち合わせ回数：最大5回(5回目が全仕様確認日) 打ち合わせ期間：初回ヒアリング打ち合わせから間取り確定まで25日 間取り確定から最終打ち合わせまで50日 合計打ち合わせ期間は75日です。 | F5: ※当社定休日での打ち合わせは不可となります。 打ち合わせ回数5回以下で下記の特典があります。 5回：★★20万円相当 ※初回ヒアリングは除く ※WEBキャンペーンとの併用は出来ません。
B6: □ | C6: 4 | D6: 間取り | E6: 完全自由設計 ※4マス×910mm間隔に柱または壁の設置が必要です。 | F6: 申請業務に進んでいくため、基本設計確定後の変更は出来ません。
B7: □ | C7: 5 | D7: 坪単価 | E7: 30坪未満の場合割増計算となり、1坪下がる度に15,000円×坪数＝追加費用が発生します。 3階建ての場合は坪単価＋40,000円UP 下屋の場合は下屋部分㎡×30,000円UP | F7: 例）28坪の場合、30坪に対して2坪下がる 30,000円×28坪＝840,000円UP
B8: □ | C8: 6 | D8: 住宅ローン | E8: 住宅ローンの手続きはお施主様自身でお願いします。 当社でしかご用意ができない書類や図面等はお渡しします。 | F8: ※事前審査も同様
B9: □ | C9: 7 | D9: 仕様 | E9: セミオーダー制 当社の設計士がこだわり抜いた【 STYLE BOOK 】からのみ選択できます。
B10: □ | C10: 8 | D10: 長期優良住宅 | E10: 認定基準として、少なくとも1の階の床面積が階段部分を除いて40㎡以上必要です。 また、都市計画法第53条許可の対象となる地域では認定対象外です。 | F10: 詳細は設計打ち合わせにてご確認ください。
B11: □ | C11: 9 | D11: Ua値 | E11: 0.46W/㎡･Kを目安としております。但し、間取りや窓の個数・種類によって数値が変わり、0.46W/㎡･Kを確保できない場合があります。
B12: □ | C12: 10 | D12: 窓 | E12: 施工面積が35坪未満10ヵ所、35～40坪11ヵ所、40～45坪12ヵ所、45～50坪13ヵ所、50坪以上14ヵ所までが標準個数です。 ※既製品のみ選定可能とし特注品の選択不可。 | F12: 掃き出し窓H2200は2ヵ所まで （手動シャッター2ヵ所まで）
B13: □ | C13: 11 | D13: 建具 | E13: 開き扉H2000㎜標準(各居室・トイレ・脱衣室・ランドリーそれぞれ1ヵ所ずつ) ※片引き戸2ヵ所まで標準 | F13: 建具高さH2400㎜、片引き戸3枚目以上及び収納扉等、リビング・書斎・洗面室・ファミリーCL・その他の部屋はオプションです。
B14: □ | C14: 12 | D14: 床材 | E14: 無垢床材を使用した場合、伸縮、床鳴り、及び経年劣化による変色が発生 する場合があります。
B15: □ | C15: 13 | D15: 換気システム | E15: 換気システムは全熱交換型第一種換気システム(Panasonic)が標準です。 | F15: DSDD換気システム(okatomi)はオプションとなり、請負契約までに確定が必要です。請負契約後は変更できません。
B16: □ | C16: 14 | D16: エコキュート タンク | E16: 室外置き | F16: 室内置きはオプションです。
B17: □ | C17: 15 | D17: ユニットバス | E17: 天井有り | F17: 天井無しの施工はDSDD換気システムをオプションで採用される場合のみ対応可能です。ご選択いただけるメーカーが限られますのでご注意ください。
B18: □ | C18: 16 | D18: 点検口 | E18: 換気システムや配管の定期点検および不具合が起きた場合に備えて1Fに必要な箇所に天井･床下点検口を3～4つ以上設置しています。 | F18: 点検口の個数および位置については間取りプランにより変動します。
B19: □ | C19: 17 | D19: 大工工事 | E19: 造作工事はSTYLE BOOKに記載の内容のみ対応しています。 | F19: 記載無き内容については提携リフォーム会社様へご相談ください。
B20: □ | C20: 18 | D20: トラブル防止 | E20: 本キャンペーン内容に関して、SNS･YouTube･ブログ等あらゆるウェブメディアへの投稿、または知人への情報共有を固く禁じます。 STYLE BOOKに掲載の商品は、告知無しで変更になる場合があります。 ※各メーカーの商品改定及び更新が定期的に行われるため、打ち合わせスタート時のSTYLE BOOKの内容が適応されます。 | F20: 打ち合わせ中に選定商品が廃番になることもありますのでご注意ください。 SNS等へのデータのUPはご遠慮ください。
B21: □ | C21: 19 | D21: オプション | E21: 標準仕様の一部をやめることによる減額（＝マイナスオプション）は対応不可です。
B22: □ | C22: 20 | D22: 式典 | E22: 地鎮祭および上棟式は省略しています。 | F22: ご希望の方は鎮め物や上棟札を着工の2週間前までに担当者にお預けください。
B23: □ | C23: 21 | D23: 施工会社 | E23: 施工については協力会社に委託する場合があります（協力会社は当社指定の一定の施工技術の基準を超えた会社）。
B24: □ | C24: 22 | D24: YouTube･見学会 | E24: 完成後、1ヵ月間の見学会･YouTube撮影のご協力お願いします。
B25: □ | C25: 23 | D25: お引渡し | E25: 最終金のご入金を確認後、鍵をお渡しします。 | F25: 鍵のお渡し日は平日にてお願いします。 外構工事の手配はお引渡し後にお願いします。
B26: □ | C26: 24 | D26: お引越し | E26: お引越しにあたり、階段手摺の取り外しおよび設置が必要となる場合は別途25,000円(税別)発生します。 | F26: お引越しに伴い必要となる工事は別途費用が発生します。
B27: □ | C27: 25 | D27: 補助金 | E27: 補助金の手続きはお施主様自身でお願いします。 | F27: ※当社で代理申請する場合は別途費用が発生します。 ZEH補助金はGハウスの行程では対応不可となります。 GX補助金は条件により申請できない場合があります。
B28: □ | C28: 26 | D28: LINE メール | E28: 間違い防止のため、設計･コーディネーター担当へのご要望･ご質問等、ご相談内容をLINEやメールにてお伝えいただくことをお断りしております。打ち合わせの際にまとめて担当者にご相談いただくようにご協力お願いします。

Sheet 紹介料支払承諾書 (2)
D1: 紹介料支払承諾書
A3: =初期入力!B4 -> 0 | D3: =IF(初期入力!B6="","",初期入力!B6) | G3: (以下「甲」という。)と株式会社Ｇハウス（以下「乙」と
A4: いう。）とは、甲が乙に対して紹介したお客様（以下「丙」という）が、乙にて建築工事請負契約を締結し、
A5: 当該契約に基づく基礎着工が完了した際、乙が甲に対して紹介料を支払うことを以下のとおり定める。
A7: 第１条（紹介料の支払い）
A8: 乙は、甲が紹介した丙が乙にて建築工事請負契約を締結し,当該契約に基づく基礎着工が完了した際、次条に
A9: 基づき、甲に紹介料を支払う。
A11: 第２条（紹介料支払金額及び支払い方法） | O11: ２．支払時期は、本承諾書締結後の翌月末までとします。
A12: １．支払金額は、1人目の契約時は10万円、2人目は20万円、3人目以降は30万円とする。 | O12: 紹介料について
A13: ２．支払時期は、丙の基礎着工月の翌月末までとする。
A14: ３．支払方法は、甲が指定する以下の金融機関口座へ振込にて支払うものとする。
A16: 金融機関名： | H16: 支店・出張所：
A17: 口座番号： | H17: 預金種別：
A18: 口座名義： | H18: フリガナ：
B19: ※ご契約内容により太陽光売電代金や補助金交付がある場合は、こちらの口座を振込先として登録は
F20: □可能 | I20: □不可
A21: 第３条（契約の成立）
A22: 本契約は、電子契約によって締結するものとし、契約の成立を証するため、本書の電磁的記録を | O22: 上記承諾書締結の証として本書2通を作成し、甲乙各1通を保有するものとする。
A23: 作成し、甲および乙が合意の後電子署名を行い、各自で電磁的記録を保管するものとする。 | O23: 上記承諾書締結の証として本書正本１通を作成し、各自記名押印の上、甲が原本、乙が写し
O24: をそれぞれ保有する。
A25: =初期入力!C13 -> 2025 | C25: 年 | D25: =初期入力!E13 -> 7 | E25: 月 | F25: =初期入力!G13 -> 25 | G25: 日
B27: 甲住所： | D27: =IF(初期入力!B5="","",初期入力!B5)
B29: 甲氏名： | D29: =初期入力!B4 -> 0 | M29: 印
B31: 甲住所： | D31: =IF(初期入力!B7="","",初期入力!B7)
B33: 甲氏名： | D33: =IF(初期入力!B6="","",初期入力!B6) | M33: 印
B35: 乙住所： | D35: 大阪府大阪市旭区新森2-23-12
B37: 乙氏名： | D37: 株式会社Gハウス 代表取締役 趙晃啓 | M37: 印

Sheet 補助金の覚書
A1: 子育てグリーン住宅支援事業補助金申請に関する覚書
A3: 発注者： | D3: =初期入力!B4 -> 0 | I3: =初期入力!B6 -> 0 | N3: (以下「甲」という。)と受注者：株式会社Ｇハウス(以下「乙」
A4: という。)は、子育てグリーン住宅支援事業補助金(以下｢補助金｣という。)申請手続きについて互いに以下
A5: のとおり合意する。
A7: 第1条(申請手続き)
A8: (1) | B8: 乙は、甲の代わりに補助金交付申請手続きを代行する。甲と乙は、「子育てグリーン住宅支援事業事務局」
B9: が発行する「共同事業実施規約」にそれぞれ署名・捺印する。乙は、提携先の設計事務所に対し、本規約
B10: の写しを交付し、補助金申請手続きを委託する場合がある。甲は、当該設計事務所または乙から補助金
B11: 申請手続きに必要な書類の提出を求められた場合、速やかにこれを用意し提出するものとする。
B12: （提出期限に間に合わない場合、補助金の交付が受けられない可能性がある。）
A14: (2) | B14: 甲は、乙が申請手続きを行っても、国（国土交通省）の予算枠超過など何らかの事情により申請が要件を
B15: 満たさず、補助金の交付を受けられない場合があることをあらかじめ承諾する。
B16: 甲と乙は、いかなる理由で補助金が受けられない場合でも、甲乙間には何らの債権債務も存在しないことを
B17: 相互に確認する。
A19: (3) | B19: 建築する住宅を本事業のGX志向型住宅補助金の対象とする場合には、乙が指定するGXオプションパック
B20: を追加する必要がある。 GXオプションパックを利用した場合でも、本補助金の取得が確約されるもので
B21: はないことを甲は承諾する。また、大きな窓を採用した建築計画や間取りにより、補助金の要件基準を
B22: 満たさない可能性がある。補助金対象か否かは間取り確定し仕様打ち合わせ後に確定するため、補助金
B23: 取得のための設計変更ができないことについても甲は承諾する。
A25: (4) | B25: GX志向型住宅の申請要件に該当しない場合には、乙は長期優良住宅またはZEH水準住宅として補助金申請
B26: する。各種要件が異なるため、要件に該当しない場合は補助金申請の対象外となる可能性があることを
B27: 甲は承諾する。
A29: 第2条(振り込み)
B30: 補助金が乙に交付された場合、乙は、補助金が乙名義の口座に入金され、かつ甲より新居の住民票の写し
B31: を受領した日から起算して20日以内に、交付申請手数料（税込20万円）および振込手数料を差し引いた
B32: 残額を、紹介料支払承諾書に記載された甲指定の口座へ振込むものとする。
A34: 第3条(規定外事項)
B35: 甲および乙は、本覚書に定めのない事項については、本件契約に基づき処理するものとする。また、
B36: 将来的に本事業の後継として国等により実施される補助金制度においても、補助金制度の趣旨や申請内容
B37: に大きな相違がない限り、本覚書の内容を適用するものとする。
A39: 以上、本覚書の成立を証するため、本電子契約書を作成し、甲乙双方が電子署名を施し、各自これを電磁的
A40: 記録として保管する。
D42: =初期入力!C13 -> 2025 | G42: 年 | H42: =初期入力!E13 -> 7 | J42: 月 | L42: =初期入力!G13 -> 25 | N42: 日
G44: 甲(発注者)住所 | M44: =初期入力!B5 -> 0
G46: 氏名 | M46: =初期入力!B4 -> 0 | AA46: 印
G48: 甲(発注者)住所 | M48: =初期入力!B7 -> 0
G50: 氏名 | M50: =初期入力!B6 -> 0 | AA50: 印
G52: 乙(受注者)住所 | M52: 大阪府大阪市旭区新森2-23-12
G54: 氏名 | M54: 株式会社Gハウス 代表取締役 趙晃啓 | AA54: 印

Sheet 解体承諾書
H2: 解体工事承諾書
N4: 年 | P4: 月 | R4: 日
B6: 株式会社 Gハウス
B7: 代表取締役 趙 晃啓 様
J8: 住所 | K8: =初期入力!B5 -> 0
J9: 氏名 | K9: =初期入力!B4 -> 0
J10: 氏名 | K10: =IF(初期入力!B6="","",初期入力!B6)
C15: 私は、下記建築物の建築確認申請許可前の解体工事について、
C16: 以下の事項を確認のうえ承諾いたします。
I19: 記
D21: 1．解体する建造物
E22: 所在地： | G22: =初期入力!B15 -> 大阪府大阪市旭区新森
E23: 家屋番号：
E24: 種類：
E25: 構造：
E26: 床面積：
D28: 2．特記事項
E29: 確認申請時に法的な制限等による新築予定の建築図面の変更や、
E30: 工期の遅れが発生する可能性があることを承知し、この場合に
E31: 異議申し立て、契約解除および損害賠償請求をしません。
Q34: 以上

Sheet 契約金振り込み依頼書
AB2: =TODAY() -> 46026
B4: =初期入力!B4&"様 "&初期入力!B6 -> 様 | O4: 様
Y6: 株 式 会 社 G ハ ウ ス
U8: 大阪府大阪市旭区新森2-23-12
U9: 営業担当： | Y9: =初期入力!B12 -> 田畑 美香
A11: 銀行振込のご案内
B14: 拝啓 日頃は格別のお引き立てをいただき誠にありがとうございます。
B15: 標記の件、下記の通りご案内申し上げます。
B17: 甚だお手数ですが、ご送金のお手配を | O17: =初期入力!B37+7 -> 45383 | W17: までにお願い申し上げます。
B18: 尚、お振込は下記の合計にてお願い致します。（振込手数料お客様ご負担でお願い致します）
B20: また、金融機関発行の振込金受付書（控）が領収証となりますので、ご了承頂きますよう
B21: お願い申し上げます。 | AG21: 敬具
O22: 記
B24: 内訳 | N24: 金額 | X24: 入金予定日
B25: ご契約金 | N25: =初期入力!B36 -> 1000000 | W25: 円 | X25: =初期入力!B37+7 -> 45383
W26: 円
W27: 円
W28: 円
W29: 円
W30: 円
B32: 合計金額 | N32: =SUM(N25:V30) -> 1000000 | AG32: 円
B34: 【お振込み先】
B35: 銀行/支店名 | N35: 口座番号 | X35: 口座名義人
B36: 三井住友銀行/関目支店 | N36: (普通)6599766 | X36: 株式会社Gハウス
A39: 【振込の際のお願い】
A40: ①入金確認を確実に行うため、お振込の際、営業担当に「お振込日」をお知らせください。
A41: ②お振込の際、振込名義を主たるご契約者様(代表者1名)に統一ください。
A42: 口座がどなた名義でも振込の際、振込名義は変更可能です。

Sheet 着工金・中間金振り込み依頼書
AB2: =TODAY() -> 46026
B4: =初期入力!B4&"様 "&初期入力!B6 -> 様 | O4: 様
Y6: 株 式 会 社 G ハ ウ ス
U8: 大阪府大阪市旭区新森2-23-12
U9: 営業担当： | Y9: =初期入力!B12 -> 田畑 美香
A11: 銀行振込のご案内
B14: 拝啓 日頃は格別のお引き立てをいただき誠にありがとうございます。
B15: 標記の件、下記の通りご案内申し上げます。
B17: 甚だお手数ですが、ご送金のお手配を | O17: 下記の各入金予定日 | W17: までにお願い申し上げます。
B18: 尚、お振込は下記の合計にてお願い致します。（振込手数料お客様ご負担でお願い致します）
B20: また、金融機関発行の振込金受付書（控）が領収証となりますので、ご了承頂きますよう
B21: お願い申し上げます。 | AG21: 敬具
O22: 記
B24: 内訳 | N24: 金額 | X24: 入金予定日
B25: 着工金 | N25: =初期入力!F38 -> 8300000 | W25: 円 | X25: =初期入力!F39 -> 46233
B26: 上棟金 | N26: =初期入力!F38 -> 8300000 | W26: 円 | X26: =初期入力!F41 -> 46273
W27: 円
W28: 円
W29: 円
W30: 円
B33: 【お振込み先】
B34: 銀行/支店名 | N34: 口座番号 | X34: 口座名義人
B35: 三井住友銀行/関目支店 | N35: (普通)6599766 | X35: 株式会社Gハウス
A38: 【振込の際のお願い】
A39: ①入金確認を確実に行うため、お振込の際、営業担当に「お振込日」をお知らせください。
A40: ②お振込の際、振込名義を主たるご契約者様(代表者1名)に統一ください。
A41: 口座がどなた名義でも振込の際、振込名義は変更可能です。

Sheet ▲太陽光明細書・蓄電池サインURL
AZ1: ※iedench NX蓄電池を採用される場合、 こちらのＵＲＬからダウンロードして、 お客様にサインをもらう
B2: 部材明細書 | AZ2: https://drive.google.com/open?id=1k28Of_cBzy7cpO7yXsV_d3xwIkYlHet6&authuser=my%40g-house.osaka.jp&usp=drive_fs
B4: 名 称 | Z4: 仕様 | AT4: 数 量 | AW4: 呼称
B5: 単)NER108-435w [30-BF-8.E] | Z5: NER108M435E-ND(D) | AT5: 20 | AW5: 枚
B6: NER)屋外集中型PCS 5.5kW | Z6: SPSS-55E-NX | AT6: 1 | AW6: 台
B7: NER)電力検出ﾕﾆｯﾄ | Z7: SPW277-NX | AT7: 1 | AW7: ｾｯﾄ
B8: NER)一括制御ﾘﾓｺﾝ | Z8: SPUR-1MB-NX | AT8: 1 | AW8: 台
B9: 片端ｹｰﾌﾞﾙ(組) HCV 30m(3.5SQ MC4) | AT9: 6 | AW9: 組
B10: 栄信)ｻﾝﾛｯｸGripⅡ端部30㎜ｾｯﾄ | Z10: ESG2E30A | AT10: 30 | AW10: ｾｯﾄ
B11: 栄信)ｻﾝﾛｯｸGripⅡ中間30-36㎜ｾｯﾄ | Z11: ESG2M01A | AT11: 90 | AW11: ｾｯﾄ
B12: ﾐﾙｴｺmini | Z12: MIRUECO mini | AT12: 1 | AW12: 台
B13: 住友電工蓄電池 | Z13: POWER DEPO H 12.8kWh | AT13: 1 | AW13: 台

Sheet 約定書
H3: 変更･追加工事代金支払い約定書
H6: =初期入力!B15 -> 大阪府大阪市旭区新森
D7: 工事場所
H8: =初期入力!B3 -> 大阪市旭区新森 池田様邸新築工事
D9: 工事名
D11: 株式会社 Ｇハウス 殿
D13: 次の変更・追加工事について完成時に支払うことを約定します。
W15: 年 | Z15: 月 | AC15: 日
D18: 住所 | H18: =初期入力!B5 -> 0
D20: 氏名 | H20: =初期入力!B4 -> 0 | Z20: 印
D22: 氏名 | H22: =初期入力!B6 -> 0 | Z22: 印
D24: No | F24: 名 称 | Y24: 変更後・追加代金 | AE24: お客様確認
D25: 1 | Y25: 50000
D27: 2
D29: 3
D31: 4
D33: 5
D35: 6
D37: 7
D39: 8
D41: 9
D43: 10
D45: 11
D47: 12
F49: 総計(税別) | Y49: =SUM(Y25:AD48) -> 50000
F51: 本契約より差額分(税込) | S51: =SUM(Y49:AD50)*1.1 -> 55000

Sheet 追加工事契約書
B2: NO. | C2: =初期入力!B44 -> 103824
E3: 追加工事契約書
B7: 注文者： | E7: =初期入力!B4 -> 0 | I7: =初期入力!B6 -> 0 | S7: (以下「甲」という)と
B9: 請負者： | E9: 株式会社 Gハウス | S9: (以下「乙」という)とは
E11: =初期入力!B3 -> 大阪市旭区新森 池田様邸新築工事
B13: の施工について、次の変更・追加について追加工事請負契約を締結し、契約成立を
B14: 証するため、本書の電磁的記録を作成し、甲および乙が合意の後電子署名を施し、
B15: 各自電磁的記録を保管する。
E17: 1. 変更内容 | I17: 別紙のとおり
E18: 2. 変更金額 | I18: 別紙のとおり
E19: 3. 支払い条件 | I19: 完成引渡し時
E20: 4. 特記事項 | I20: なし
L22: 年 | O22: 月 | R22: 日
B24: 甲１住所 | E24: =初期入力!B5 -> 0
B26: 甲１氏名 | E26: =初期入力!B4 -> 0
B28: 甲２住所 | E28: =初期入力!B7 -> 0
B30: 甲２氏名 | E30: =初期入力!B6 -> 0
B32: 乙住所 | E32: 大阪府大阪市旭区新森2-23-12
B34: 乙氏名 | E34: 株式会社 Gハウス | J34: 代表取締役 趙晃啓

Sheet 最終精算書
A1: 最終精算書
N2: =TODAY() -> 46026
A3: =初期入力!B4&" "&初期入力!B6 | H3: 様 | L3: 〒535-0022 大阪府大阪市旭区新森2-23-12
L4: 株式会社 Gハウス | P4: 代表取締役 趙晃啓
A6: ■下記の通り、精算申し上げます
A7: 契約日 | C7: =初期入力!B30 -> 45741 | H7: 工事№ | J7: =初期入力!B44 -> 103824 | O7: 営業担当 | Q7: =初期入力!B12 -> 田畑 美香
A8: ■工事代金の部 Ａ | Y8: =初期入力!B44 -> 103824
A9: 項 目 | L9: 金額(税込) | Q9: 備考
A10: 工事請負金額総額 | B10: 変更契約(イ) | L10: =初期入力!F33 -> 0 | P10: 円
B11: 追加契約 | P11: 円 | T11: =IF(Q11="","","締結分")
P12: 円 | T12: =IF(Q12="","","締結分")
P13: 円 | T13: =IF(Q13="","","締結分")
P14: 円 | T14: =IF(Q14="","","締結分")
B15: 小 計（ロ） | L15: =SUM(L11:O14) -> 0 | P15: 円
B16: 合 計① | H16: （イ）+（ロ） | L16: =L10+L15 -> 0 | P16: 円
A17: 入金済 | B17: 建築申し込み | G17: 金額 | H17: =初期入力!F34 -> 100000 | K17: 円 | L17: 請負契約時 | Q17: 金額 | R17: =初期入力!F36 -> 1000000 | U17: 円
B18: 着工時 | G18: 金額 | H18: =初期入力!F38 -> 8300000 | K18: 円 | L18: 上棟時 | Q18: 金額 | R18: =初期入力!F40 -> 8300000 | U18: 円
G19: 金額 | K19: 円 | Q19: 金額 | U19: 円
B20: 総 合 計 ② | L20: =SUM(H17+H18+H19+R17+R18+R19) -> 17700000 | U20: 円
B21: 差引残金 Ａ＝①-② | M21: =L16-L20 -> -17700000 | U21: 円
A22: ■契約書印紙代 B
B23: 請負契約時 | G23: 金額 | K23: 円 | L23: 変更契約時 | Q23: 金額 | U23: 円
B24: 太陽光契約時 | G24: 金額 | K24: 円 | Q24: 金額 | U24: 円
B25: 合 計 | M25: =SUM(H23+H24+R23+R24) -> 0 | U25: 円
A26: 入金済 | B26: 請負契約時 | G26: 金額 | K26: 円 | L26: 変更契約時 | Q26: 金額 | U26: 円
B27: 太陽光契約時 | G27: 金額 | K27: 円 | Q27: 金額 | U27: 円
B28: 総 合 計 ④ | L28: =SUM(H26+R26+H27+R27) -> 0 | U28: 円
B29: 差引残金 B＝③-④ | M29: =M25-L28 -> 0 | U29: 円
A30: 残金 | B30: お支払予定日 | I30: 最終精算額（A+B+C） | P30: お支払方法
B31: =初期入力!B43 -> 46066 | I31: =M21+M29 -> -17700000 | P31: 下記振込下さい
A32: お振込先：
A33: 三井住友銀行 関目支店 (普通)6599766 カ）ジーハウス
A35: ※入金確認の都合上、「何時頃入金されたのか」を担当営業までお知らせください
A43: ※融資金代理受領の関係上、返金が生じる場合は、以下返金口座をご記入下さい
A44: 金融機関名 | H44: 支店名
A45: 口座番号 | H45: 名義人

Sheet 紹介料支払依頼書
C1: 紹 介 料 支 払 依 頼 書
J3: =TODAY() -> 46026
K5: 所属長
B8: 下記ご紹介者様の紹介により建築工事請負契約を締結した物件の
B9: 基礎着工が完了しましたので、紹介料の振込を依頼します。
B11: ＊ | C11: 特に指定の無い場合、基礎着工日翌月末日迄に振込みます。
B12: ＊ | C12: 振込手数料は当社負担です。
B13: ＊ | C13: 現金での支払いはしません。
B14: ＊ | C14: 以下添付
B15: ○ | C15: 紹介料支払承諾書
F17: (所 属) | G17: 営業部
F18: (担当者) | G18: =初期入力!B12 -> 田畑 美香 | K18: ㊞
A20: 振込理由 | B20: 紹介者様名 | D20: =初期入力!B4 -> 0 | H20: =初期入力!B6 -> 0
B21: 契約者様名
B22: 請負契約日 | G22: 基礎着工日
B23: ＜備考＞
A27: 支払金額(税込) | G27: 振込先 | H27: 紹介料支払承諾書記載の口座 | L27: 紹介料について
L28: 1件目は10万円
L29: 2件目は20万円
B30: (税込・振込手数料当社負担) | L30: 3件目以降は30万円

Sheet 振込依頼書
D1: 振込み依頼書
L2: =TODAY() -> 46026
A4: 株式会社 Gハウス | D4: 殿
B6: 下記の指定口座に振り込みをお願いいたします。
A9: 金融機関名： | H9: 支店・出張所：
A10: 口座番号： | H10: 預金種別：
A11: 口座名義： | H11: フリガナ：
O14: 上記承諾書締結の証として本書2通を作成し、甲乙各1通を保有するものとする。
O15: 上記承諾書締結の証として本書正本１通を作成し、各自記名押印の上、甲が原本、乙が写し
O16: をそれぞれ保有する。
C17: 年 | E17: 月 | G17: 日
B19: 住所： | D19: =IF(初期入力!B5="","",初期入力!B5)
B21: お名前： | M21: 印
B23: 電話番号： | D23: =IF(初期入力!B7="","",初期入力!B7)
